Workbook
Name Cost_Lever: [1]Segmentation2!#REF!
Name Cost_Lever: [1]Segmentation2!#REF!
Name Cost_Lever: [1]Segmentation2!#REF!
Name Cost_Lever: [1]Segmentation2!#REF!
Name Cost_Lever: [1]Segmentation2!#REF!
Name Cost_Lever: #REF!
Name Cost_Lever: #REF!
Name Cost_Lever: [1]Segmentation2!#REF!
Name Cost_Lever: [1]Segmentation2!#REF!
Name Cost_Lever: [1]Segmentation2!#REF!
Name Cost_Lever: #REF!
Name Cost_Lever: #REF!
Name Cost_Lever: [1]Segmentation2!#REF!
Name Cost_Lever: #REF!
Name Cost_Lever: [1]Segmentation2!#REF!
Name Cost_Lever: [1]Segmentation2!#REF!
Name Cost_Lever: #REF!
Name Cost_Lever: [1]Segmentation2!#REF!
Name Cost_Lever: #REF!
Name Cost_Lever: #REF!
Name Cost_Lever: #REF!
Name Cost_Lever: [1]Segmentation2!#REF!
Name Cost_Lever: #REF!
Name Cost_Lever: #REF!
Name Cost_Lever: [1]Segmentation2!#REF!
Name Cost_Lever: #REF!
Name Cost_Lever: #REF!
Name Cost_Lever: [1]Segmentation2!#REF!
Name Cost_Lever: [1]Segmentation2!#REF!
Name DOA: #REF!
Name DOA: #REF!
Name DOA: #REF!
Name DOA: #REF!
Name DOA: #REF!
Name DOA: #REF!
Name DOA: #REF!
Name DOA: #REF!
Name DOA: #REF!
Name DOA: #REF!
Name DOA: #REF!
Name DOA: #REF!
Name DOA: #REF!
Name DOA: #REF!
Name DOA: #REF!
Name DOA: [1]references!$W$2:$W$6
Name Niv0: #REF!
Name Niv0: #REF!
Name Niv0: #REF!
Name Niv0: #REF!
Name Niv0: #REF!
Name Niv0: #REF!
Name Niv0: #REF!
Name Niv0: #REF!
Name Niv0: #REF!
Name Niv0: #REF!
Name Niv0: #REF!
Name Niv0: #REF!
Name Niv0: #REF!
Name Niv0: #REF!
Name Niv0: #REF!

Sheet End dates
A3: Étiquettes de lignes | B3: End Dates of lease
A4: 1. Europe
A5: Allianz Global Benefits
A6: Germany
A7: Seidlstrasse 24-24a
A8: Munich | B8: 48913
A9: Uhlandstrasse 2
A10: Stuttgart | B10: 0
A11: BU Austria
A12: Austria
A13: Linzer Strasse 225
A14: Vienna | B14: 47635
A15: Bulgaria
A16: 16 Srebarna Str.
A17: Sofia | B17: 48029
A18: Hungary
A19: Könyves Kalman krt. 48-52
A20: Budapest | B20: 46477
A21: Romania
A22: Globalworth Campus, C Building · 2-4, Ing. George Constantinescu 11th floor, 2nd District
A23: Bucharest | B23: 47483
A24: BU Czech Republic
A25: Czech Republic
A26: Čajakova 18
A27: Bratislava | B27: 0
A28: Jankovcova 1596/14B
A29: Prague | B29: 46599
A30: BU France
A31: France
A32: 151 Boulevard Victor Hugo
A33: Saint Ouen | B33: 46356
A34: 7 rue Dora Maar
A35: Saint Ouen | B35: 49064
A36: 79-81 Rue Pierre Semard
A37: Chatillon | B37: 46295
A38: 85 Quai de Beauvais
A39: Armentières | B39: 47026
A40: Chemin aux bœuf & les Hunaudières
A41: Le Mans | B41: 47177
A42: BU Germany (AHS)
A43: Germany
A44: Albert-Einstein-Strasse 1a
A45: Berlin | B45: 46157
A46: Heltorfer Strasse 4
A47: Düsseldorf | B47: 0
A48: Herriotstraße 1
A49: Frankfurt | B49: 0
A50: Heßbrühlstraße 2
A51: Stuttgart | B51: 0
A52: Kapstadtring 2
A53: Hamburg | B53: 0
A54: Maximilianstr. 5
A55: Neustadt | B55: 47149
A56: Springerstrasse 25
A57: Leipzig | B57: 47452
A58: BU Germany (AVS)
A59: Germany
A60: Ferdinand-Stuttmann-Str. 10
A61: Rüsselsheim | B61: 0
A62: BU Germany (AZ Warranty)
A63: Germany
A64: Beta-Str. 13
A65: Unterföhring | B65: 0
A66: BU Germany (MAWISTA)
A67: Germany
A68: Esslinger Str. 83
A69: Plochingen | B69: 46477
A70: BU Germany (MKS)
A71: Germany
A72: Deutschherrnstraße 15-19
A73: Nürnberg | B73: 46326
A74: BU Germany (REHACARE)
A75: Germany
A76: Dornburger Str. 161
A77: Jena | B77: 0
A78: Frankfurter Str. 40
A79: Bad Vilbel | B79: 0
A80: Hildastr. 10
A81: Weinheim | B81: 0
A82: Kapuzinerstraße 9D
A83: München | B83: 0
A84: Karl-Grillenberger-Str. 1
A85: Nürnberg | B85: 0
A86: Marktgasse 7b
A87: Meisenheim | B87: 0
A88: Max-Planck-Str. 7
A89: Unna | B89: 0
A90: Otto-von-Guericke-Straße 87a
A91: Magdeburg | B91: 0
A92: Robert-Koch-Straße 9
A93: Pulsnitz | B93: 0
A94: Stormsweg 3
A95: Hamburg | B95: 0
A96: Voithstr. 4
A97: Ludwigsburg | B97: 46112
A98: Weidenauer Str. 167a
A99: Siegen | B99: 0
A100: BU Greece
A101: Greece
A102: 10 Premetis Str.
...

Sheet DataCube
A2: New Region | B2: BU | C2: Country | D2: City | E2: Postal code | F2: Street Address | G2: Rental/Owned/ Sublease | H2: Location unique ID | I2: Located at AZ entity (Yes/No) | J2: Unit description | K2: Size (m²or Ft) | L2: Currency code | M2: Rental Cost/m² | N2: Indexation | O2: Rental Cost | P2: Facility Costs | Q2: # of Employees | R2: # of workstation | S2: Ratio workstation/ employee | T2: sqm/workstation | U2: sqm/employee | V2: Lease Start Date | W2: Lease End Date | X2: Next Break Date | Y2: Sublease Contract in Place (Yes/No) | Z2: Renewable energy? Yes/No | AA2: Sustainability Certification | AB2: CRE & FM Function | AC2: Last update | AD2: Lease Notes/ Comments
A3: 2. Asia | B3: =Thailand!$F$4 -> 0 | C3: =Thailand!$F$17 -> 0 | D3: =Thailand!$F$15 -> 0 | E3: =Thailand!$F$16 -> 0 | F3: =Thailand!$F$14 -> 0 | G3: =Thailand!$F$18 -> 0 | H3: =Thailand!$F$11 -> 0 | I3: =Thailand!$F$19 -> 0 | J3: =Thailand!$F$13 -> 0 | K3: =Thailand!$F$24 -> 0 | L3: =Thailand!$F$26 -> 0 | M3: =Thailand!$F$28 -> 0 | N3: =Thailand!$F$29 -> 0 | O3: =Thailand!$F$27 -> 0 | P3: =Thailand!$F$30 -> 0 | Q3: =Thailand!$F$46 -> 0 | R3: =Thailand!$F$50 -> 0 | S3: =R3/Q3 -> #DIV/0! | T3: =K3/R3 -> #DIV/0! | U3: =K3/Q3 -> #DIV/0! | V3: =Thailand!$F$33 -> 0 | W3: =Thailand!$F$40 -> 0 | X3: =Thailand!$F$34 -> 0 | Y3: =Thailand!$F$42 -> 0 | Z3: =Thailand!$F$43 -> 0 | AA3: =Thailand!$F$44 -> 0 | AB3: =Thailand!$F$9 -> 0 | AC3: =Thailand!$D$2 -> 46058
A4: 2. Asia | B4: =Australia!$D$4 -> BU Australia | C4: =Australia!$D$17 -> Australia | D4: =Australia!$D$15 -> Brisbane | E4: =Australia!$D$16 -> 4000 | F4: =Australia!$D$14 -> 310 Ann St | G4: =Australia!$D$18 -> Rental | H4: =Australia!$D$11 -> AU01 | I4: =Australia!$D$19 -> No | J4: =Australia!$D$13 -> Levels 12-18 | K4: =Australia!$D$24 -> 7993 | L4: =Australia!$D$26 -> AUD | M4: =Australia!$D$28 -> 805.4 | N4: =Australia!$D$29 -> 3.75% per annum on anniversary date | P4: =Australia!$D$30 -> 731245 | Q4: =Australia!$D$46 -> 619 | R4: =Australia!$D$50 -> 386 | S4: =R4/Q4 -> 0.62358643 | T4: =K4/R4 -> 20.707254 | U4: =K4/Q4 -> 12.912763 | V4: =Australia!$D$33 -> 43497 | W4: =Australia!$D$40 -> 47361 | X4: =Australia!$D$34 -> 47361 | Y4: =Australia!$D$42 -> Yes | Z4: =Australia!$D$43 -> No | AA4: =Australia!$D$44 -> Yes- NABERS 5.5 star energy rating & working on NABERS rating for waste | AB4: =Australia!$D$9 -> sbishop@allianz-assistance.com.au | AC4: =Australia!$D$2 -> 0
A5: 2. Asia | B5: =Australia!$D$4 -> BU Australia | C5: =Australia!$E$17 -> Australia | D5: =Australia!$E$15 -> Brisbane | E5: =Australia!$E$16 -> 4000 | F5: =Australia!$E$14 -> 310 Ann St | G5: =Australia!$E$18 -> Rental | H5: =Australia!$E$11 -> AU01 | I5: =Australia!$E$19 -> No | J5: =Australia!$E$13 -> Levels 12-14 | K5: =Australia!$E$24 -> 3441 | L5: =Australia!$E$26 -> AUD | M5: =Australia!$E$28 -> $565/ sqm Less incentive of $88.25 / sqm Net rent $476.75 | N5: =Australia!$E$29 -> 3.75% per annum on anniversary date | O5: =Australia!$E$27 -> 0 | P5: =Australia!$E$30 -> Base building charges recovered from sub tenant of $98,000 per yr plus a proportion of some of the direct vendor costs that relate to the maintenance of the tenancy | S5: =R5/Q5 -> #DIV/0! | T5: =K5/R5 -> #DIV/0! | U5: =K5/Q5 -> #DIV/0! | V5: =Australia!E33 -> 44743 | W5: =Australia!E40 -> 46568 | X5: =Australia!E34 -> 46568 | Y5: =Australia!$E$42 -> subleaser | AC5: =Australia!$D$2 -> 0
A6: 1. Europe | B6: =Austria!$D$4 -> BU Austria | C6: =Austria!$D$17 -> Austria | D6: =Austria!$D$15 -> Vienna | E6: =Austria!$D$16 -> 1140 | F6: =Austria!$D$14 -> Linzer Strasse 225 | G6: =Austria!$D$18 -> Rental | H6: =Austria!$D$11 -> AT01 | I6: =Austria!$D$19 -> Yes | J6: =Austria!$D$13 -> 3rd floor | K6: =Austria!$D$24 -> 890 | L6: =Austria!$D$26 -> EUR | M6: =Austria!$D$28 -> 16,80/m² | N6: =Austria!$D$29 -> CPI | O6: =Austria!$D$27 -> 0 | P6: =Austria!$D$30 -> 173.4 | Q6: =Austria!$D$46 -> 220 | R6: =Austria!$D$50 -> 87 | S6: =R6/Q6 -> 0.39545455 | T6: =K6/R6 -> 10.229885 | U6: =K6/Q6 -> 4.0454545 | V6: =Austria!$D$33 -> 45261 | W6: =Austria!$D$40 -> 47635 | X6: =Austria!$D$34 -> 45444 | Y6: =Austria!$D$42 -> No | Z6: =Austria!$D$43 -> Yes | AA6: =Austria!$D$44 -> No | AB6: =Austria!$D$9 -> 0 | AC6: =Austria!$D$2 -> 45919
A7: 4. H&L | B7: =Belgium!$D$4 -> International Health | C7: =Belgium!$D$17 -> Belgium | D7: =Belgium!$D$15 -> Brussels | E7: =Belgium!$D$16 -> 1000 | F7: =Belgium!$D$14 -> Allianz Tower Koning Boulevard du Roi Albert II, 32 (Albert II Laan) | G7: =Belgium!$D$18 -> Rental | H7: =Belgium!$D$11 -> BE01 | I7: =Belgium!$D$19 -> Yes | J7: =Belgium!$D$13 -> 4th floor & 50% of the 5th floor | K7: =Belgium!$D$24 -> 1658 | L7: =Belgium!$D$26 -> EUR | M7: =Belgium!$D$28 -> 373 | N7: =Belgium!$D$29 -> app. 3% | O7: =Belgium!$D$27 -> 618434 | P7: =Belgium!$D$30 -> 259 | Q7: =Belgium!$D$46 -> 222 | R7: =Belgium!$D$50 -> 142 | S7: =R7/Q7 -> 0.63963964 | T7: =K7/R7 -> 11.676056 | U7: =K7/Q7 -> 7.4684685 | V7: =Belgium!$D$33 -> 43922 | W7: =Belgium!$D$40 -> 47208 | X7: =Belgium!$D$34 -> 47208 | Y7: =Belgium!$D$42 -> No | Z7: =Belgium!$D$43 -> Yes | AA7: =Belgium!$D$44 -> Unknown | AB7: =Belgium!$D$9 -> 0 | AC7: =Belgium!$D$2 -> 46070
A8: 3. Americas | B8: =Brazil!$D$4 -> BU Brazil | C8: =Brazil!$D$17 -> Brazil | D8: =Brazil!$D$15 -> São Bernardo do Campo | E8: =Brazil!$D$16 -> 09751-020 | F8: =Brazil!$D$14 -> Rua José Versolato, 101 | G8: =Brazil!$D$18 -> Rental | H8: =Brazil!$D$11 -> BR01 | I8: =Brazil!$D$19 -> No | J8: =Brazil!$D$13 -> 5th, 6th, 8th and 9th floor | K8: =Brazil!$D$24 -> 3256 | L8: =Brazil!$D$26 -> BRL | M8: =Brazil!$D$28 -> 577 | N8: =Brazil!$D$29 -> 0.09 | O8: =Brazil!$D$27 -> 0 | P8: =Brazil!$D$30 -> 114 | Q8: =Brazil!$D$46 -> 1300 | R8: =Brazil!$D$50 -> 752 | S8: =R8/Q8 -> 0.57846154 | T8: =K8/R8 -> 4.3297872 | U8: =K8/Q8 -> 2.5046154 | V8: =Brazil!$D$33 -> 42614 | W8: =Brazil!$D$40 -> 46234 | X8: =Brazil!$D$34 -> 42582 | Y8: =Brazil!$D$42 -> N/A | Z8: =Brazil!$D$43 -> No | AA8: =Brazil!$D$44 -> No | AB8: =Brazil!$D$9 -> 0 | AC8: =Brazil!$D$2 -> 45961
A9: 3. Americas | B9: =Brazil!$D$4 -> BU Brazil | C9: =Brazil!$E$17 -> Brazil | D9: =Brazil!$E$15 -> São Bernardo do Campo | E9: =Brazil!$E$16 -> 09751-020 | F9: =Brazil!$E$14 -> Rua José Versolato, 101 (2nd contract) | G9: =Brazil!$E$18 -> Rental | H9: =Brazil!$E$11 -> BR01 | I9: =Brazil!$E$19 -> No | J9: =Brazil!$E$13 -> 50% of the 6th floor | K9: =Brazil!$E$24 -> 711 | L9: =Brazil!$E$26 -> BRL | M9: =Brazil!$E$28 -> 600 | N9: =Brazil!$E$29 -> 0.09 | O9: =Brazil!$E$27 -> 0 | P9: =Brazil!$E$30 -> 21 | Q9: =Brazil!$E$46 -> 200 | R9: =Brazil!$E$50 -> 154 | S9: =R9/Q9 -> 0.77 | T9: =K9/R9 -> 4.6168831 | U9: =K9/Q9 -> 3.555 | V9: =Brazil!$E$33 -> 44927 | W9: =Brazil!$E$40 -> 46387 | X9: =Brazil!$E$34 -> 46387 | Y9: =Brazil!$E$42 -> N/A | Z9: =Brazil!$E$43 -> No | AA9: =Brazil!$E$44 -> No | AB9: =Brazil!$E$9 -> 0 | AC9: =Brazil!$E$2 -> 0
A10: 1. Europe | B10: =Bulgaria!$D$4 -> BU Austria | C10: =Bulgaria!$D$17 -> Bulgaria | D10: =Bulgaria!$D$15 -> Sofia | E10: =Bulgaria!$D$16 -> 1407 | F10: =Bulgaria!$D$14 -> 16 Srebarna Str. | G10: =Bulgaria!$D$18 -> Rental | H10: =Bulgaria!$D$11 -> BU01 | I10: =Bulgaria!$D$19 -> No | J10: =Bulgaria!$D$13 -> part of a floor | K10: =Bulgaria!$D$24 -> 45.77 | L10: =Bulgaria!$D$26 -> EUR | M10: =Bulgaria!$D$28 -> 156 | N10: =Bulgaria!$D$29 -> CPI | O10: =Bulgaria!$D$27 -> 0 | P10: =Bulgaria!$D$30 -> 53.6 | Q10: =Bulgaria!$D$46 -> 6 | R10: =Bulgaria!$D$50 -> 6 | S10: =R10/Q10 -> 1 | T10: =K10/R10 -> 7.6283333 | U10: =K10/Q10 -> 7.6283333 | V10: =Bulgaria!$D$33 -> 44378 | W10: =Bulgaria!$D$40 -> 48029 | X10: =Bulgaria!$D$34 -> 48029 | Y10: =Bulgaria!$D$42 -> No | Z10: =Bulgaria!$D$43 -> No | AA10: =Bulgaria!$D$44 -> No | AB10: =Bulgaria!$D$9 -> 0 | AC10: =Bulgaria!$D$2 -> 45919
A11: 3. Americas | B11: =Canada!$D$4 -> BU Canada | C11: =Canada!$D$17 -> Canada | D11: =Canada!$D$15 -> Cambridge | E11: =Canada!$D$16 -> N3C 4N6 | F11: =Canada!$D$14 -> 700 Jamieson Pkwy. Cambridge | G11: =Canada!$E$18 -> Sublease | H11: =Canada!$E$11 -> CA01 | I11: =Canada!$E$19 -> 0 | J11: =Canada!$E$13 -> 0 | K11: =Canada!$E$24 -> 3376.4666 | L11: =Canada!$E$26 -> CAD | M11: =Canada!$E$28 -> 17 | N11: =Canada!$E$29 -> Year 1-5 - $17.00 Year 6-10 - $18.00 Year 11-14 - $19.00 | O11: =Canada!$E$27 -> 0 | P11: =Canada!$E$30 -> 0 | Q11: =Canada!$E$46 -> 0 | R11: =Canada!$E$50 -> 0 | S11: =R11/Q11 -> #DIV/0! | T11: =K11/R11 -> #DIV/0! | U11: =K11/Q11 -> #DIV/0! | V11: =Canada!$E$33 -> 44075 | W11: =Canada!$E$40 -> 49033 | X11: =Canada!$E$34 -> N/A | Y11: =Canada!$E$42 -> Sublet: Superior Propane Aug 01/20-Mar 30/34 | Z11: =Canada!$E$43 -> 0 | AA11: =Canada!$E$44 -> 0 | AB11: =Canada!$E$9 -> 0 | AC11: =Canada!$E$2 -> 0
A12: 3. Americas | B12: =Canada!$D$4 -> BU Canada | C12: =Canada!$D$17 -> Canada | D12: =Canada!$D$15 -> Cambridge | E12: =Canada!$D$16 -> N3C 4N6 | F12: =Canada!$D$14 -> 700 Jamieson Pkwy. Cambridge | G12: =Canada!$F$18 -> Sublease | H12: =Canada!$F$11 -> CA01 | I12: =Canada!$F$19 -> 0 | J12: =Canada!$F$13 -> 0 | K12: =Canada!$F$24 -> 2319.3234 | L12: =Canada!$F$26 -> CAD | M12: =Canada!$F$28 -> 18.5 | N12: =Canada!$F$29 -> Year 1-4 - $18.50 Year 5-8- $19.50 Year 9-11 - $20.50 | O12: =Canada!$F$27 -> 0 | P12: =Canada!$F$30 -> 0 | Q12: =Canada!$F$46 -> 0 | R12: =Canada!$F$50 -> 0 | S12: =R12/Q12 -> #DIV/0! | T12: =K12/R12 -> #DIV/0! | U12: =K12/Q12 -> #DIV/0! | V12: =Canada!$F$33 -> 45078 | W12: =Canada!$F$40 -> 49033 | X12: =Canada!$F$34 -> N/A | Y12: =Canada!$F$42 -> 2nd Sublet: Reeds Heritage Homes(no details at this time) | Z12: =Canada!$F$43 -> 0 | AA12: =Canada!$F$44 -> 0 | AB12: =Canada!$F$9 -> 0 | AC12: =Canada!$F$2 -> 0
A13: 3. Americas | B13: =Canada!$D$4 -> BU Canada | C13: =Canada!$D$17 -> Canada | D13: =Canada!$D$15 -> Cambridge | E13: =Canada!$D$16 -> N3C 4N6 | F13: =Canada!$D$14 -> 700 Jamieson Pkwy. Cambridge | G13: =Canada!$D$18 -> Rental | H13: =Canada!$D$11 -> CA01 | I13: =Canada!$D$19 -> No | J13: =Canada!$D$13 -> Single story unattached office dwelling | K13: =Canada!$D$24 -> 10334.716 | L13: =Canada!$D$26 -> CAD | M13: =Canada!$D$28 -> 17.5 | N13: =Canada!$D$29 -> Year 1-5 - $17.50 Year 6-10 - $19.35 Year 11-15- $21.35 | O13: =Canada!$D$27 -> 0 | P13: =Canada!$D$30 -> 20.559078 | Q13: =Canada!$D$46 -> 668 | R13: =Canada!$D$50 -> 420 | S13: =R13/Q13 -> 0.62874251 | T13: =K13/R13 -> 24.606466 | U13: =K13/Q13 -> 15.471131 | V13: =Canada!$D$33 -> 43459 | W13: =Canada!$D$40 -> 49058 | X13: =Canada!$D$34 -> 49302 | Y13: =Canada!$D$42 -> Yes | Z13: =Canada!$D$43 -> Yes | AA13: =Canada!$D$44 -> LEED Silver | AB13: =Canada!$D$9 -> 0 | AC13: =Canada!$D$2 -> 45961
A14: 2. Asia | B14: =China!$D$4 -> BU China | C14: =China!$D$17 -> China | D14: =China!$D$15 -> Beijing | E14: =China!$D$16 -> 100123 | F14: =China!$D$14 -> Huitong Office Park, No.1 Yaojiayuan South Road, Chaoyang | G14: =China!$D$18 -> Rental | H14: =China!$D$11 -> CN01 | I14: =China!$D$19 -> No | J14: =China!$D$13 -> A Zone, Building 7# Floor 3-5 | K14: =China!$D$24 -> 2845 | L14: =China!$D$26 -> CNY | M14: =China!$D$28 -> 1766.6 | N14: =China!$D$29 -> 0 | O14: =China!$D$27 -> 0 | P14: =China!$D$30 -> 837.86 | Q14: =China!$D$46 -> 319 | R14: =China!$D$50 -> 303 | S14: =R14/Q14 -> 0.94984326 | T14: =K14/R14 -> 9.3894389 | U14: =K14/Q14 -> 8.9184953 | V14: =China!$D$33 -> 45301 | W14: =China!$D$40 -> 46396 | X14: =China!$D$34 -> 46031 | Y14: =China!$D$42 -> - | Z14: =China!$D$43 -> N | AA14: =China!$D$44 -> No | AB14: =China!$D$9 -> 0 | AC14: =China!$D$2 -> 0
A15: 2. Asia | B15: =China!$D$4 -> BU China | C15: =China!$D$17 -> China | D15: =China!$E$15 -> Chengdu | E15: =China!$E$16 -> 610041 | F15: =China!$E$14 -> E zone, Tianfu Software Park, Gaoxin District, Chengdu | G15: =China!$E$18 -> Rental | H15: =China!$E$11 -> CN02 | I15: =China!$E$19 -> No | J15: =China!$E$13 -> 9F, Tower E2 | K15: =China!$E$24 -> 2197 | L15: =China!$E$26 -> CNY | M15: =China!$E$28 -> 840 | N15: =China!$E$29 -> 0 | O15: =China!$E$27 -> 0 | P15: =China!$E$30 -> 624.35321 | Q15: =China!$E$46 -> 256 | R15: =China!$E$50 -> 398 | S15: =R15/Q15 -> 1.5546875 | T15: =K15/R15 -> 5.5201005 | U15: =K15/Q15 -> 8.5820312 | V15: =China!$E$33 -> 45246 | W15: =China!$E$40 -> 46934 | X15: =China!$E$34 -> 46022 | Y15: =China!$E$42 -> - | Z15: =China!$E$43 -> N | AA15: =China!$E$44 -> No | AB15: =China!$E$9 -> 0 | AC15: =China!$E$2 -> 0
A16: 2. Asia | B16: =China!$D$4 -> BU China | C16: =China!$F$17 -> China | D16: =China!$F$15 -> Shanghai | E16: =China!$F$16 -> 200120 | F16: =China!$F$14 -> Shanghai Tower, No.501 Yincheng Zhong Road, Pudong District | G16: =China!$F$18 -> Rental | H16: =China!$F$11 -> CN03 | I16: =China!$F$19 -> No | J16: =China!$F$13 -> Unit 1401 | K16: =China!$F$24 -> 550.16 | L16: =China!$F$26 -> CNY | M16: =China!$F$28 -> 3650.04 | N16: =China!$F$29 -> 0 | O16: =China!$F$27 -> 0 | P16: =China!$F$30 -> 1231.5327 | Q16: =China!$F$46 -> 37 | R16: =China!$F$50 -> 52 | S16: =R16/Q16 -> 1.4054054 | T16: =K16/R16 -> 10.58 | U16: =K16/Q16 -> 14.869189 | V16: =China!$F$33 -> 42975 | W16: =China!$F$40 -> 46644 | X16: =China!$F$34 -> 45940 | Y16: =China!$F$42 -> - | Z16: =China!$F$43 -> N | AA16: =China!$F$44 -> No | AB16: =China!$F$9 -> 0 | AC16: =China!$F$2 -> 0
A17: 3. Americas | B17: =Colombia!$D$4 -> BU Colombia | C17: =Colombia!$D$17 -> Colombia | D17: =Colombia!$D$15 -> Bogota | E17: =Colombia!$D$16 -> 110110 | F17: =Colombia!$D$14 -> 72b Street # 6-44 | G17: =Colombia!$D$18 -> Rental | H17: =Colombia!$D$11 -> CO01 | I17: =Colombia!$D$19 -> Yes | J17: =Colombia!$D$13 -> Location from floor 2 to floor 4 | K17: =Colombia!$D$24 -> 863.93 | L17: =Colombia!$D$26 -> COP | M17: =Colombia!$D$28 -> 475787.52 | N17: =Colombia!$D$29 -> IPC (CPI) | O17: =Colombia!$D$27 -> 0 | P17: =Colombia!$D$30 -> 266162.49 | Q17: =Colombia!$D$46 -> 136 | R17: =Colombia!$D$50 -> 116 | S17: =R17/Q17 -> 0.85294118 | T17: =K17/R17 -> 7.4476724 | U17: =K17/Q17 -> 6.3524265 | V17: =Colombia!$D$33 -> 44652 | W17: =Colombia!$D$40 -> 46477 | X17: =Colombia!$D$34 -> 46112 | Y17: =Colombia!$D$42 -> No | Z17: =Colombia!$D$43 -> No | AA17: =Colombia!$D$44 -> No | AB17: =Colombia!$D$9 -> 0 | AC17: =Colombia!$D$2 -> 45961
A18: 1. Europe | B18: =CzechRepublic!$D$4 -> BU Czech Republic | C18: =CzechRepublic!$D$17 -> Czech Republic | D18: =CzechRepublic!$D$15 -> Prague | E18: =CzechRepublic!$D$16 -> 170 00 | F18: =CzechRepublic!$D$14 -> Jankovcova 1596/14B | G18: =CzechRepublic!$D$18 -> Rental | H18: =CzechRepublic!$D$11 -> CZ01 | I18: =CzechRepublic!$D$19 -> No | J18: =CzechRepublic!$D$13 -> 2nd floor in new constructed bulding | K18: =CzechRepublic!$D$24 -> 1293.19 | L18: =CzechRepublic!$D$26 -> CZK/EUR | M18: =CzechRepublic!$D$28 -> 144 | N18: =CzechRepublic!$D$29 -> indexation only for the price per offices - for 2025 = 2,5% | O18: =CzechRepublic!$D$27 -> 0 | P18: =CzechRepublic!$D$30 -> 90855.8 | Q18: =CzechRepublic!$D$46 -> 171 | R18: =CzechRepublic!$D$50 -> 126 | S18: =R18/Q18 -> 0.73684211 | T18: =K18/R18 -> 10.263413 | U18: =K18/Q18 -> 7.5625146 | V18: =CzechRepublic!$D$33 -> 40210 | W18: =CzechRepublic!$D$40 -> 46599 | X18: =CzechRepublic!$D$34 -> 45900 | Y18: =CzechRepublic!$D$42 -> No | Z18: =CzechRepublic!$D$43 -> No | AA18: =CzechRepublic!$D$44 -> No | AB18: =CzechRepublic!$D$9 -> 0 | AC18: =CzechRepublic!$D$2 -> 45925
A19: 1. Europe | B19: =CzechRepublic!$D$4 -> BU Czech Republic | C19: =CzechRepublic!$D$17 -> Czech Republic | D19: =CzechRepublic!$E$15 -> Bratislava | E19: =CzechRepublic!$E$16 -> 811 05 | F19: =CzechRepublic!$E$14 -> Čajakova 18 | G19: =CzechRepublic!$E$18 -> Rental | H19: =CzechRepublic!$E$11 -> CZ02 | I19: =CzechRepublic!$E$19 -> No | J19: =CzechRepublic!$E$13 -> 2nd floor old bulding, downtown of the city | K19: =CzechRepublic!$E$24 -> 74 | L19: =CzechRepublic!$E$26 -> EUR | M19: =CzechRepublic!$E$28 -> 168 | N19: =CzechRepublic!$E$29 -> no indexation | O19: =CzechRepublic!$E$27 -> 0 | P19: =CzechRepublic!$E$30 -> 50.4 | Q19: =CzechRepublic!$E$46 -> 5 | R19: =CzechRepublic!$E$50 -> 6 | S19: =R19/Q19 -> 1.2 | T19: =K19/R19 -> 12.333333 | U19: =K19/Q19 -> 14.8 | V19: =CzechRepublic!$E$33 -> 37669 | W19: =CzechRepublic!$E$40 -> Indefinite | X19: =CzechRepublic!$E$34 -> 3 months notice at any given time | Y19: =CzechRepublic!$E$42 -> No | Z19: =CzechRepublic!$E$43 -> No | AA19: =CzechRepublic!$E$44 -> No | AB19: =CzechRepublic!$E$9 -> 0 | AC19: =CzechRepublic!$E$2 -> 0
A20: 4. H&L | B20: =Egypt!$D$4 -> Nextcare | C20: =Egypt!$D$17 -> Egypt | D20: =Egypt!$D$15 -> New Cairo | E20: =Egypt!$D$16 -> N/A | F20: =Egypt!$D$14 -> Emerald Twin Plaza, Plot No. (6), 1st settlement, New Cairo, Cairo, Egypt | G20: =Egypt!$D$18 -> Rental | H20: =Egypt!$D$11 -> EG01 | I20: =Egypt!$D$19 -> No | J20: =Egypt!$D$13 -> 2nd floor | K20: =Egypt!$D$24 -> 5380 | L20: =Egypt!$D$26 -> EGP | M20: =Egypt!$D$28 -> 4898.88 | N20: =Egypt!$D$29 -> 8% annual | O20: =Egypt!$D$27 -> 26355974 | P20: =Egypt!$D$30 -> 1554.8204 | Q20: =Egypt!$D$46 -> 1251 | R20: =Egypt!$D$50 -> 769 | S20: =R20/Q20 -> 0.61470823 | T20: =K20/R20 -> 6.9960988 | U20: =K20/Q20 -> 4.3005596 | V20: =Egypt!$D$33 -> 45078 | W20: =Egypt!$D$40 -> 48365 | X20: =Egypt!$D$34 -> 48365 | Y20: =Egypt!$D$42 -> No | Z20: =Egypt!$D$43 -> N/A | AA20: =Egypt!$D$44 -> No | AB20: =Egypt!$D$9 -> Ismail Abdelfatah /Amal Evram | AC20: =Egypt!$D$2 -> 46042
A21: 4. H&L | B21: =Egypt!$D$4 -> Nextcare | C21: =Egypt!$D$17 -> Egypt | D21: =Egypt!$E$15 -> New Cairo | E21: =Egypt!$E$16 -> N/A | F21: =Egypt!$E$14 -> Emerald Twin Plaza, Plot No. (6), 1st settlement, New Cairo, Cairo, Egypt | G21: =Egypt!$E$18 -> Rental | H21: =Egypt!$E$11 -> EG01 | I21: =Egypt!$E$19 -> No | J21: =Egypt!$E$13 -> M1 | K21: =Egypt!$E$24 -> 130 | L21: =Egypt!$E$26 -> EGP | M21: =Egypt!$E$28 -> 9000 | N21: =Egypt!$E$29 -> NA | O21: =Egypt!$E$27 -> 1170000 | P21: =Egypt!$E$30 -> 0 | Q21: =Egypt!$E$46 -> 0 | R21: =Egypt!$E$50 -> 0 | S21: =R21/Q21 -> #DIV/0! | T21: =K21/R21 -> #DIV/0! | U21: =K21/Q21 -> #DIV/0! | V21: =Egypt!$E$33 -> 45261 | W21: =Egypt!$E$40 -> 46356 | X21: =Egypt!$E$34 -> 46356 | Y21: =Egypt!$E$42 -> No | Z21: =Egypt!$E$43 -> NO | AA21: =Egypt!$E$44 -> NO | AB21: =Egypt!$E$9 -> Ismail Abdelfatah /Amal Evram | AC21: =Egypt!$E$2 -> 0
A22: 4. H&L | B22: =Egypt!$D$4 -> Nextcare | C22: =Egypt!$F$17 -> Egypt | D22: =Egypt!$F$15 -> Mokattem city | E22: =Egypt!$F$16 -> N/A | F22: =Egypt!$F$14 -> Street 9, Plot no. 8230, Mokattam city, Cairo | G22: =Egypt!$F$18 -> Rental | H22: =Egypt!$F$11 -> EG02 | I22: =Egypt!$F$19 -> No | J22: =Egypt!$F$13 -> ground floor | K22: =Egypt!$F$24 -> 37.16 | L22: =Egypt!$F$26 -> EGP | M22: =Egypt!$F$28 -> 8073.197 | N22: =Egypt!$F$29 -> 10% Annual | O22: =Egypt!$F$27 -> 300000 | P22: =Egypt!$F$30 -> 0 | Q22: =Egypt!$F$46 -> 0 | R22: =Egypt!$F$50 -> 0 | S22: =R22/Q22 -> #DIV/0! | T22: =K22/R22 -> #DIV/0! | U22: =K22/Q22 -> #DIV/0! | V22: =Egypt!$F$33 -> 44501 | W22: =Egypt!$F$40 -> 46325 | X22: =Egypt!$F$34 -> 46325 | Y22: =Egypt!$F$42 -> NO | Z22: =Egypt!$F$43 -> NO | AA22: =Egypt!$F$44 -> NO | AB22: =Egypt!$F$9 -> Ismail Abdelfatah /Amal Evram | AC22: =Egypt!$F$2 -> 0
A23: 1. Europe | B23: =UK!$F$4 -> BU United Kingdom | C23: =UK!$F$17 -> England | D23: =UK!$F$15 -> London | E23: =UK!$F$16 -> EC2 | F23: =UK!$F$14 -> 15 Bishopsgate, London, EC2 | G23: =UK!$F$18 -> Sublease | H23: =UK!$F$11 -> 0 | I23: =UK!$F$19 -> Y | J23: =UK!$F$13 -> 7 desks - hotdesking for sales and pricing | K23: =UK!$F$24 -> 7 desks | L23: =UK!$F$26 -> Stg | M23: =UK!$F$28 -> 140k approx | N23: =UK!$F$29 -> Advised by Az Mgt Serv annaully | O23: =UK!$F$27 -> 20k per desk p/a. Final figures to be advised | P23: =UK!$F$30 -> Included in cost per desk | Q23: =UK!$F$46 -> 27 currently | R23: =UK!$F$50 -> 0 | S23: =R23/Q23 -> #VALUE! | T23: =K23/R23 -> #VALUE! | U23: =K23/Q23 -> #VALUE! | V23: =UK!$F$33 -> Nov 25 approx | W23: =UK!$F$40 -> 1 year approval | X23: =UK!$F$34 -> We have 1 year rolling approval | Y23: =UK!$F$42 -> Once signed it will be provided | Z23: =UK!$F$43 -> Yes | AA23: =UK!$F$44 -> Unknown | AB23: =UK!$F$9 -> International Health | AC23: =UK!$F$2 -> 0
A24: 1. Europe | B24: =France!$D$4 -> BU France | C24: =France!$G$17 -> France | D24: =France!$G$15 -> Chatillon | E24: =France!$G$16 -> 92320 | F24: =France!$G$14 -> 79-81 Rue Pierre Semard | G24: =France!$G$18 -> Rental | H24: =France!$G$11 -> FR05 | I24: =France!$G$19 -> No | J24: =France!$G$13 -> Ground, 1st and 2nd Floor | K24: =France!$G$24 -> 1269 | L24: =France!$G$26 -> EUR | M24: =France!$G$28 -> 308.12 | N24: =France!$G$29 -> yearly ILAT | O24: =France!$G$27 -> 0 | P24: =France!$G$30 -> 195000 | Q24: =France!$G$46 -> 99 | R24: =France!$G$50 -> 117 | S24: =R24/Q24 -> 1.1818182 | T24: =K24/R24 -> 10.846154 | U24: =K24/Q24 -> 12.818182 | V24: =France!$G$33 -> 43009 | W24: =France!$G$40 -> 46295 | X24: =France!$G$34 -> 46295 | Y24: =France!$G$42 -> No | Z24: =France!$G$43 -> No | AA24: =France!$G$44 -> No | AB24: =France!$G$9 -> 0 | AC24: =France!$G$2 -> 0
A25: 1. Europe | B25: =France!$D$4 -> BU France | C25: =France!$F$17 -> France | D25: =France!$F$15 -> Saint Ouen | E25: =France!$F$16 -> 93400 | F25: =France!$F$14 -> 151 Boulevard Victor Hugo | G25: =France!$F$18 -> Rental | H25: =France!$F$11 -> FR03 | I25: =France!$F$19 -> No | J25: =France!$F$13 -> 3rd floor | K25: =France!$F$24 -> 2127 | L25: =France!$F$26 -> EUR | M25: =France!$F$28 -> 368.4598 | N25: =France!$F$29 -> ILAT | O25: =France!$F$27 -> 0 | P25: =France!$F$30 -> 235.07287 | Q25: =France!$F$46 -> 123 | R25: =France!$F$50 -> 136 | S25: =R25/Q25 -> 1.1056911 | T25: =K25/R25 -> 15.639706 | U25: =K25/Q25 -> 17.292683 | V25: =France!$F$33 -> 45078 | W25: =France!$F$40 -> 46356 | X25: =France!$F$34 -> 46173 | Y25: =France!$F$42 -> Yes | Z25: =France!$F$43 -> Yes | AA25: =France!$F$44 -> HQE exploitation | AB25: =France!$F$9 -> 0 | AC25: =France!$F$2 -> 0
A26: 1. Europe | B26: =France!$D$4 -> BU France | C26: =France!$H$17 -> France | D26: =France!$H$15 -> Armentières | E26: =France!$H$16 -> 59280 | F26: =France!$H$14 -> 85 Quai de Beauvais | G26: =France!$H$18 -> Rental | H26: =France!$H$11 -> FR06 | I26: =France!$H$19 -> No | J26: =France!$H$13 -> Whole Building | K26: =France!$H$24 -> 235 | L26: =France!$H$26 -> EUR | M26: =France!$H$28 -> 129.31 | N26: =France!$H$29 -> yearly ILC | O26: =France!$H$27 -> 0 | P26: =France!$H$30 -> 50000 | Q26: =France!$H$46 -> 13 | R26: =France!$H$50 -> 27 | S26: =R26/Q26 -> 2.0769231 | T26: =K26/R26 -> 8.7037037 | U26: =K26/Q26 -> 18.076923 | V26: =France!$H$33 -> 43739 | W26: =France!$H$40 -> 47026 | X26: =France!$H$34 -> 45930 | Y26: =France!$H$42 -> No | Z26: =France!$H$43 -> No | AA26: =France!$H$44 -> No | AB26: =France!$H$9 -> 0 | AC26: =France!$H$2 -> 0
A27: 1. Europe | B27: =France!$D$4 -> BU France | C27: =France!$D$17 -> France | D27: =France!$E$15 -> Le Mans | E27: =France!$E$16 -> 72000 | F27: =France!$E$14 -> Chemin aux bœuf & les Hunaudières | G27: =France!$E$18 -> Rental | H27: =France!$E$11 -> FR02 | I27: =France!$E$19 -> No | J27: =France!$E$13 -> Group of 2 buildings | K27: =France!$E$24 -> 4403 | L27: =France!$E$26 -> EUR | M27: =France!$E$28 -> 127.46 | N27: =France!$E$29 -> ILAT indice | O27: =France!$E$27 -> 0 | P27: =France!$E$30 -> 78.128549 | Q27: =France!$E$46 -> 602 | R27: =France!$E$50 -> 430 | S27: =R27/Q27 -> 0.71428571 | T27: =K27/R27 -> 10.239535 | U27: =K27/Q27 -> 7.3139535 | V27: =France!$E$33 -> 43891 | W27: =France!$E$40 -> 47177 | X27: =France!$E$34 -> 46082 | Y27: =France!$E$42 -> No | Z27: =France!$E$43 -> NO | AA27: =France!$E$44 -> No | AB27: =France!$E$9 -> 0 | AC27: =France!$E$2 -> 0
A28: 1. Europe | B28: =France!$D$4 -> BU France | C28: =France!$D$17 -> France | D28: =France!$D$15 -> Saint Ouen | E28: =France!$D$16 -> 93400 | F28: =France!$D$14 -> 7 rue Dora Maar | G28: =France!$D$18 -> Rental | H28: =France!$D$11 -> FR01 | I28: =France!$D$19 -> No | J28: =France!$D$13 -> Group of 2 buildings composed of all ground floor part of 1st floor 2nd, 3rd, 4th, 5th,7th floors | K28: =France!$D$24 -> 12407 | L28: =France!$D$26 -> EUR | M28: =France!$D$28 -> 353.15 | N28: =France!$D$29 -> ILAT Indice | O28: =France!$D$27 -> 0 | P28: =France!$D$30 -> 258.64431 | Q28: =France!$D$46 -> 1193 | R28: =France!$D$50 -> 1020 | S28: =R28/Q28 -> 0.85498743 | T28: =K28/R28 -> 12.163725 | U28: =K28/Q28 -> 10.399832 | V28: =France!$D$33 -> 42125 | W28: =France!$D$40 -> 49064 | X28: =France!$D$34 -> 47968 | Y28: =France!$D$42 -> Yes | Z28: =France!$D$43 -> NO | AA28: =France!$D$44 -> No | AB28: =France!$D$9 -> 0 | AC28: =France!$D$2 -> 45979
A29: 1. Europe | B29: =LaReunion!$D$4 -> BU Reunion | C29: =LaReunion!$D$17 -> France | D29: =LaReunion!$D$15 -> Sainte-Marie, La Réserve | E29: =LaReunion!$D$16 -> 97438 | F29: =LaReunion!$D$14 -> 32 rue du Général de Gaulle | G29: =LaReunion!$D$18 -> Rental | H29: =LaReunion!$D$11 -> FR04 | I29: =LaReunion!$D$19 -> No | J29: =LaReunion!$D$13 -> 2nd floor | K29: =LaReunion!$D$24 -> 1100 | L29: =LaReunion!$D$26 -> EUR | M29: =LaReunion!$D$28 -> 11.47 | N29: =LaReunion!$D$29 -> 0.035 | O29: =LaReunion!$D$27 -> 0 | P29: =LaReunion!$D$30 -> 125,39€ m²/year soit 12,54€ m²/month | Q29: =LaReunion!$D$46 -> 286 | R29: =LaReunion!$D$50 -> 292 | S29: =R29/Q29 -> 1.020979 | T29: =K29/R29 -> 3.7671233 | U29: =K29/Q29 -> 3.8461538 | V29: =LaReunion!$D$33 -> 42736 | W29: =LaReunion!$D$40 -> 47118 | X29: =LaReunion!$D$34 -> 46022 | Y29: =LaReunion!$D$42 -> No | Z29: =LaReunion!$D$43 -> No | AA29: =LaReunion!$D$44 -> No | AB29: =LaReunion!$D$9 -> 0 | AC29: =LaReunion!$D$2 -> 45988
A30: 1. Europe | B30: =LaReunion!$F$4 -> BU Reunion | C30: =LaReunion!$F$17 -> France | D30: =LaReunion!$F$15 -> Sainte-Marie, La Réserve | E30: =LaReunion!$F$16 -> 97438 | F30: =LaReunion!$F$14 -> 32 rue du Général de Gaulle | G30: =LaReunion!$F$18 -> Rental | H30: =LaReunion!$F$11 -> FR04 | I30: =LaReunion!$F$19 -> No | J30: =LaReunion!$F$13 -> 1st floor | K30: =LaReunion!$F$24 -> 550 | L30: =LaReunion!$F$26 -> EUR | M30: =LaReunion!$F$28 -> 12.42 | N30: =LaReunion!$F$29 -> 0.035 | O30: =LaReunion!$F$27 -> 0 | P30: =LaReunion!$F$30 -> 0 | Q30: =LaReunion!$F$46 -> 59 | R30: =LaReunion!$F$50 -> 59 | S30: =R30/Q30 -> 1 | T30: =K30/R30 -> 9.3220339 | U30: =K30/Q30 -> 9.3220339 | V30: =LaReunion!$F$33 -> 44986 | W30: =LaReunion!$F$40 -> 48273 | X30: =LaReunion!$F$34 -> 46081 | Y30: =LaReunion!$F$42 -> No | Z30: =LaReunion!$F$43 -> No | AA30: =LaReunion!$F$44 -> No | AB30: =LaReunion!$F$9 -> 0 | AC30: =LaReunion!$F$2 -> 0
A31: 1. Europe | B31: =LaReunion!$E$4 -> BU Reunion | C31: =LaReunion!$E$17 -> France | D31: =LaReunion!$E$15 -> Sainte-Marie, La Réserve | E31: =LaReunion!$E$16 -> 97438 | F31: =LaReunion!$E$14 -> 32 rue du Général de Gaulle | G31: =LaReunion!$E$18 -> Rental | H31: =LaReunion!$E$11 -> FR04 | I31: =LaReunion!$E$19 -> No | J31: =LaReunion!$E$13 -> 2nd floor | K31: =LaReunion!$E$24 -> 326 | L31: =LaReunion!$E$26 -> EUR | M31: =LaReunion!$E$28 -> 12.83 | N31: =LaReunion!$E$29 -> 0.035 | O31: =LaReunion!$E$27 -> 0 | P31: =LaReunion!$E$30 -> 0 | Q31: =LaReunion!$E$46 -> 85 | R31: =LaReunion!$E$50 -> 89 | S31: =R31/Q31 -> 1.0470588 | T31: =K31/R31 -> 3.6629213 | U31: =K31/Q31 -> 3.8352941 | V31: =LaReunion!$E$33 -> 41944 | W31: =LaReunion!$E$40 -> 48518 | X31: =LaReunion!$E$34 -> 48518 | Y31: =LaReunion!$E$42 -> No | Z31: =LaReunion!$E$43 -> No | AA31: =LaReunion!$E$44 -> No | AB31: =LaReunion!$E$9 -> 0 | AC31: =LaReunion!$E$2 -> 0
A32: 1. Europe | B32: =LaReunion!$G$4 -> BU Reunion | C32: =LaReunion!$G$17 -> France | D32: =LaReunion!$G$15 -> Sainte-Marie, La Réserve | E32: =LaReunion!$G$16 -> 97438 | F32: =LaReunion!$G$14 -> 32 rue du Général de Gaulle | G32: =LaReunion!$G$18 -> Rental | H32: =LaReunion!$G$11 -> FR04 | I32: =LaReunion!$G$19 -> No | J32: =LaReunion!$G$13 -> 1st floor | K32: =LaReunion!$G$24 -> 213 | L32: =LaReunion!$G$26 -> EUR | M32: =LaReunion!$G$28 -> 15.14 | N32: =LaReunion!$G$29 -> 0.035 | O32: =LaReunion!$G$27 -> 0 | P32: =LaReunion!$G$30 -> 0 | Q32: =LaReunion!$G$46 -> 42 | R32: =LaReunion!$G$50 -> 42 | S32: =R32/Q32 -> 1 | T32: =K32/R32 -> 5.0714286 | U32: =K32/Q32 -> 5.0714286 | V32: =LaReunion!$G$33 -> 45387 | W32: =LaReunion!$G$40 -> 48673 | X32: =LaReunion!$G$34 -> 48673 | Y32: =LaReunion!$G$42 -> No | Z32: =LaReunion!$G$43 -> No | AA32: =LaReunion!$G$44 -> No | AB32: =LaReunion!$G$9 -> 0 | AC32: =LaReunion!$G$2 -> 0
A33: 1. Europe | B33: =France!$I$4 -> Global Office | C33: =France!$I$17 -> France | D33: =France!$I$15 -> Saint Ouen | E33: =France!$I$16 -> 93400 | F33: =France!$I$14 -> 7rue Dora Maar | G33: =France!$I$18 -> Rental | H33: =France!$I$11 -> FR01 | I33: =France!$I$19 -> No | J33: =France!$I$13 -> 6 & 8th floor | K33: =France!$I$24 -> 5148 | L33: =France!$I$26 -> EUR | M33: =France!$I$28 -> 349.65035 | N33: =France!$I$29 -> 0.03 | O33: =France!$I$27 -> 0 | P33: =France!$I$30 -> 213.67521 | Q33: =France!$I$46 -> 350 | R33: =France!$I$50 -> 298 | S33: =R33/Q33 -> 0.85142857 | T33: =K33/R33 -> 17.275168 | U33: =K33/Q33 -> 14.708571 | V33: =France!$I$33 -> 42491 | W33: =France!$I$40 -> 49064 | X33: =France!$I$34 -> 47968 | Y33: =France!$I$42 -> Yes | Z33: =France!$I$43 -> Yes | AA33: =France!$I$44 -> No | AB33: =France!$I$9 -> 0 | AC33: =France!$I$2 -> 0
A34: 1. Europe | B34: =Germany!$AC$4 -> Allianz Global Benefits | C34: =Germany!$AC$17 -> Germany | D34: =Germany!$AC$15 -> Munich | E34: =Germany!$AC$16 -> 80335 | F34: =Germany!$AC$14 -> Seidlstrasse 24-24a | G34: =Germany!$AC$18 -> Rental | H34: =Germany!$AC$11 -> AGB01 | I34: =Germany!$AC$19 -> Yes | J34: =Germany!$AC$13 -> part of ground floor | K34: =Germany!$AC$24 -> 191.14 | L34: =Germany!$AC$26 -> EUR | M34: =Germany!$AC$28 -> 984 | N34: =Germany!$AC$29 -> N/A | O34: =Germany!$AC$27 -> 188081.76 | P34: =Germany!$AC$30 -> 252 | Q34: =Germany!$AC$46 -> 30 | R34: =Germany!$AC$50 -> 22 | S34: =R34/Q34 -> 0.73333333 | T34: =K34/R34 -> 8.6881818 | U34: =K34/Q34 -> 6.3713333 | V34: =Germany!$AC$33 -> 45261 | W34: =Germany!$AC$40 -> 48913 | X34: =Germany!$AC$34 -> 47087 | Y34: =Germany!$AC$42 -> No | Z34: =Germany!$AC$43 -> Yes | AA34: =Germany!$AC$44 -> No | AB34: =Germany!$AC$9 -> 0 | AC34: =Germany!$AC$2 -> 0
A35: 1. Europe | B35: =Germany!$AD$4 -> Allianz Global Benefits | C35: =Germany!$AD$17 -> Germany | D35: =Germany!$AD$15 -> Stuttgart | E35: =Germany!$AD$16 -> 70182 | F35: =Germany!$AD$14 -> Uhlandstrasse 2 | G35: =Germany!$AD$18 -> Rental | H35: =Germany!$AD$11 -> AGB02 | I35: =Germany!$AD$19 -> Yes | J35: =Germany!$AD$13 -> part of 1st floor | K35: =Germany!$AD$24 -> 360 | L35: =Germany!$AD$26 -> EUR | M35: =Germany!$AD$28 -> 408 | N35: =Germany!$AD$29 -> N/A | O35: =Germany!$AD$27 -> 146880 | P35: =Germany!$AD$30 -> 108 | Q35: =Germany!$AD$46 -> 30 | R35: =Germany!$AD$50 -> 26 | S35: =R35/Q35 -> 0.86666667 | T35: =K35/R35 -> 13.846154 | U35: =K35/Q35 -> 12 | V35: =Germany!$AD$33 -> 43101 | W35: =Germany!$AD$40 -> indefinite | X35: =Germany!$AD$34 -> anytime | Y35: =Germany!$AD$42 -> No | Z35: =Germany!$AD$43 -> Yes | AA35: =Germany!$AD$44 -> No | AB35: =Germany!$AD$9 -> 0 | AC35: =Germany!$AD$2 -> 0
A36: 1. Europe | B36: =Germany!$F$4 -> BU Germany (AHS) | C36: =Germany!$F$17 -> Germany | D36: =Germany!$F$15 -> Berlin | E36: =Germany!$F$16 -> 12489 | F36: =Germany!$F$14 -> Albert-Einstein-Strasse 1a | G36: =Germany!$F$18 -> Rental | H36: =Germany!$F$11 -> DE02 | I36: =Germany!$F$19 -> No | J36: =Germany!$F$13 -> Ground floor, 1st and 2nd floor | K36: =Germany!$F$24 -> 2391.74 | L36: =Germany!$F$26 -> EUR | M36: =Germany!$F$28 -> 21.212118 | N36: =Germany!$F$29 -> 0.05 | O36: =Germany!$F$27 -> 50733.87 | P36: =Germany!$F$30 -> --- | Q36: =Germany!$F$46 -> 0 | R36: =Germany!$F$50 -> 0 | S36: =R36/Q36 -> #DIV/0! | T36: =K36/R36 -> #DIV/0! | U36: =K36/Q36 -> #DIV/0! | V36: =Germany!$F$33 -> 01.05.2019 | W36: =Germany!$F$40 -> 46157 | X36: =Germany!$F$34 -> 46143 | Y36: =Germany!$F$42 -> No | Z36: =Germany!$F$43 -> No | AA36: =Germany!$F$44 -> No | AB36: =Germany!$F$9 -> Daniel Krauss | AC36: =Germany!$F$2 -> 0
A37: 1. Europe | B37: =Germany!$R$4 -> BU Germany (AHS) | C37: =Germany!$R$17 -> Germany | D37: =Germany!$R$15 -> Neustadt | E37: =Germany!$R$16 -> 67433 | F37: =Germany!$R$14 -> Maximilianstr. 5 | G37: =Germany!$R$18 -> Rental | H37: =Germany!$R$11 -> DE07 | I37: =Germany!$R$19 -> No | J37: =Germany!$R$13 -> 1st floor | K37: =Germany!$R$24 -> 349 | L37: =Germany!$R$26 -> EUR | M37: =Germany!$R$28 -> 8.739255 | N37: =Germany!$R$29 -> 0.05 | O37: =Germany!$R$27 -> 3050 | P37: =Germany!$R$30 -> --- | Q37: =Germany!$R$46 -> 0 | R37: =Germany!$R$50 -> 0 | S37: =R37/Q37 -> #DIV/0! | T37: =K37/R37 -> #DIV/0! | U37: =K37/Q37 -> #DIV/0! | V37: =Germany!$R$33 -> 43497 | W37: =Germany!$R$40 -> 47149 | X37: =Germany!$R$34 -> 46418 | Y37: =Germany!$R$42 -> No | Z37: =Germany!$R$43 -> No | AA37: =Germany!$R$44 -> No | AB37: =Germany!$R$9 -> Daniel Krauss | AC37: =Germany!$R$2 -> 0
A38: 1. Europe | B38: =Germany!$M$4 -> BU Germany (AHS) | C38: =Germany!$M$17 -> Germany | D38: =Germany!$M$15 -> Leipzig | E38: =Germany!$M$16 -> 04105 | F38: =Germany!$M$14 -> Springerstrasse 25 | G38: =Germany!$M$18 -> Rental | H38: =Germany!$M$11 -> DE06 | I38: =Germany!$M$19 -> No | J38: =Germany!$M$13 -> 2nd floor | K38: =Germany!$M$24 -> 322.97 | L38: =Germany!$M$26 -> EUR | M38: =Germany!$M$28 -> 9.2499923 | N38: =Germany!$M$29 -> 0.05 | O38: =Germany!$M$27 -> 2987.47 | P38: =Germany!$M$30 -> 2.23 | Q38: =Germany!$M$46 -> 0 | R38: =Germany!$M$50 -> 0 | S38: =R38/Q38 -> #DIV/0! | T38: =K38/R38 -> #DIV/0! | U38: =K38/Q38 -> #DIV/0! | V38: =Germany!$M$33 -> 43070 | W38: =Germany!$M$40 -> 47452 | X38: =Germany!$M$34 -> 46356 | Y38: =Germany!$M$42 -> 0 | Z38: =Germany!$M$43 -> No | AA38: =Germany!$M$44 -> No | AB38: =Germany!$M$9 -> Daniel Krauss | AC38: =Germany!$M$2 -> 0
A39: 1. Europe | B39: =Germany!$J$4 -> BU Germany (AHS) | C39: =Germany!$J$17 -> Germany | D39: =Germany!$J$15 -> Hamburg | E39: =Germany!$J$16 -> 22297 | F39: =Germany!$J$14 -> Kapstadtring 2 | G39: =Germany!$J$18 -> Rental | H39: =Germany!$J$11 -> DE05 | I39: =Germany!$J$19 -> Yes | J39: =Germany!$J$13 -> part of second floor | K39: =Germany!$J$24 -> 144.85 | L39: =Germany!$J$26 -> EUR | M39: =Germany!$J$28 -> 94.868554 | N39: =Germany!$J$29 -> --- | O39: =Germany!$J$27 -> 13741.71 | P39: =Germany!$J$30 -> --- | Q39: =Germany!$J$46 -> 0 | R39: =Germany!$J$50 -> 0 | S39: =R39/Q39 -> #DIV/0! | T39: =K39/R39 -> #DIV/0! | U39: =K39/Q39 -> #DIV/0! | V39: =Germany!$J$33 -> 43101 | W39: =Germany!$J$40 -> undetermined | X39: =Germany!$J$34 -> undetermined | Y39: =Germany!$J$42 -> No | Z39: =Germany!$J$43 -> Yes | AA39: =Germany!$J$44 -> Yes | AB39: =Germany!$J$9 -> Daniel Krauss | AC39: =Germany!$J$2 -> 0
A40: 1. Europe | B40: =Germany!$Y$4 -> BU Germany (AHS) | C40: =Germany!$Y$17 -> Germany | D40: =Germany!$Y$15 -> Stuttgart | E40: =Germany!$Y$16 -> 70565 | F40: =Germany!$Y$14 -> Heßbrühlstraße 2 | G40: =Germany!$Y$18 -> Rental | H40: =Germany!$Y$11 -> DE08 | I40: =Germany!$Y$19 -> Yes | J40: =Germany!$Y$13 -> part of the 4th floor | K40: =Germany!$Y$24 -> 81.16 | L40: =Germany!$Y$26 -> EUR | M40: =Germany!$Y$28 -> 78.65 | N40: =Germany!$Y$29 -> --- | O40: =Germany!$Y$27 -> 6383.234 | P40: =Germany!$Y$30 -> --- | Q40: =Germany!$Y$46 -> 0 | R40: =Germany!$Y$50 -> 0 | S40: =R40/Q40 -> #DIV/0! | T40: =K40/R40 -> #DIV/0! | U40: =K40/Q40 -> #DIV/0! | V40: =Germany!$Y$33 -> 45839 | W40: =Germany!$Y$40 -> undetermined | X40: =Germany!$Y$34 -> undetermined | Y40: =Germany!$Y$42 -> No | Z40: =Germany!$Y$43 -> Yes | AA40: =Germany!$Y$44 -> Yes | AB40: =Germany!$Y$9 -> Daniel Krauss | AC40: =Germany!$Y$2 -> 0
A41: 1. Europe | B41: =Germany!$H$4 -> BU Germany (AHS) | C41: =Germany!$H$17 -> Germany | D41: =Germany!$H$15 -> Düsseldorf | E41: =Germany!$H$16 -> 40472 | F41: =Germany!$H$14 -> Heltorfer Strasse 4 | G41: =Germany!$H$18 -> Rental | H41: =Germany!$H$11 -> DE03 | I41: =Germany!$H$19 -> No | J41: =Germany!$H$13 -> 3rd floor | K41: =Germany!$H$24 -> 480.14 | L41: =Germany!$H$26 -> EUR | M41: =Germany!$H$28 -> 16.27 | N41: =Germany!$H$29 -> 0.05 | O41: =Germany!$H$27 -> 7811.8778 | P41: =Germany!$H$30 -> 3.5 | Q41: =Germany!$H$46 -> 0 | R41: =Germany!$H$50 -> 0 | S41: =R41/Q41 -> #DIV/0! | T41: =K41/R41 -> #DIV/0! | U41: =K41/Q41 -> #DIV/0! | V41: =Germany!$H$33 -> 43466 | W41: =Germany!$H$40 -> undetermined | X41: =Germany!$H$34 -> 46477 | Y41: =Germany!$H$42 -> No | Z41: =Germany!$H$43 -> No | AA41: =Germany!$H$44 -> No | AB41: =Germany!$H$9 -> Daniel Krauss | AC41: =Germany!$H$2 -> 0
A42: 1. Europe | B42: =Germany!$I$4 -> BU Germany (AHS) | C42: =Germany!$I$17 -> Germany | D42: =Germany!$I$15 -> Frankfurt | E42: =Germany!$I$16 -> 60528 | F42: =Germany!$I$14 -> Herriotstraße 1 | G42: =Germany!$I$18 -> Rental | H42: =Germany!$I$11 -> DE04 | I42: =Germany!$I$19 -> No | J42: =Germany!$I$13 -> 2nd floor | K42: =Germany!$I$24 -> 497 | L42: =Germany!$I$26 -> EUR | M42: =Germany!$I$28 -> 20.071972 | N42: =Germany!$I$29 -> 0.05 | O42: =Germany!$I$27 -> 9975.77 | P42: =Germany!$I$30 -> --- | Q42: =Germany!$I$46 -> 0 | R42: =Germany!$I$50 -> 0 | S42: =R42/Q42 -> #DIV/0! | T42: =K42/R42 -> #DIV/0! | U42: =K42/Q42 -> #DIV/0! | V42: =Germany!$I$33 -> 39692 | W42: =Germany!$I$40 -> undetermined | X42: =Germany!$I$34 -> 46266 | Y42: =Germany!$I$42 -> No | Z42: =Germany!$I$43 -> No | AA42: =Germany!$I$44 -> No | AB42: =Germany!$I$9 -> Daniel Krauss | AC42: =Germany!$I$2 -> 0
A43: 1. Europe | B43: =Germany!$W$4 -> BU Germany (AVS) | C43: =Germany!$W$17 -> Germany | D43: =Germany!$W$15 -> Rüsselsheim | E43: =Germany!$W$16 -> 65428 | F43: =Germany!$W$14 -> Ferdinand-Stuttmann-Str. 10 | G43: =Germany!$W$18 -> Rental | H43: =Germany!$W$11 -> DE09 | I43: =Germany!$W$19 -> No | J43: =Germany!$W$13 -> ? | K43: =Germany!$W$24 -> 0 | L43: =Germany!$W$26 -> 0 | M43: =Germany!$W$28 -> 0 | N43: =Germany!$W$29 -> 0 | O43: =Germany!$W$27 -> 0 | P43: =Germany!$W$30 -> 0 | Q43: =Germany!$W$46 -> 0 | R43: =Germany!$W$50 -> 0 | S43: =R43/Q43 -> #DIV/0! | T43: =K43/R43 -> #DIV/0! | U43: =K43/Q43 -> #DIV/0! | V43: =Germany!$W$33 -> 0 | W43: =Germany!$W$40 -> 0 | X43: =Germany!$W$34 -> 0 | Y43: =Germany!$W$42 -> 0 | Z43: =Germany!$W$43 -> 0 | AA43: =Germany!$W$44 -> 0 | AB43: =Germany!$W$9 -> Daniel Krauss | AC43: =Germany!$W$2 -> 0
A44: 1. Europe | B44: =Germany!$AB$4 -> BU Germany (AZ Warranty) | C44: =Germany!$AB$17 -> Germany | D44: =Germany!$AB$15 -> Unterföhring | E44: =Germany!$AB$16 -> 85774 | F44: =Germany!$AB$14 -> Beta-Str. 13 | G44: =Germany!$AB$18 -> Rental | H44: =Germany!$AB$11 -> DE10 | I44: =Germany!$AB$19 -> Yes | J44: =Germany!$AB$13 -> 50% ground floor | K44: =Germany!$AB$24 -> 320.36 | L44: =Germany!$AB$26 -> EUR | M44: =Germany!$AB$28 -> 0 | N44: =Germany!$AB$29 -> --- | O44: =Germany!$AB$27 -> ??? | P44: =Germany!$AB$30 -> --- | Q44: =Germany!$AB$46 -> 0 | R44: =Germany!$AB$50 -> 0 | S44: =R44/Q44 -> #DIV/0! | T44: =K44/R44 -> #DIV/0! | U44: =K44/Q44 -> #DIV/0! | V44: =Germany!$AB$33 -> 45870 | W44: =Germany!$AB$40 -> undetermined | X44: =Germany!$AB$34 -> undetermined | Y44: =Germany!$AB$42 -> No | Z44: =Germany!$AB$43 -> Yes | AA44: =Germany!$AB$44 -> Yes | AB44: =Germany!$AB$9 -> Daniel Krauss | AC44: =Germany!$AB$2 -> 0
A45: 1. Europe | B45: =Germany!$U$4 -> BU Germany (MAWISTA) | C45: =Germany!$U$17 -> Germany | D45: =Germany!$U$15 -> Plochingen | E45: =Germany!$U$16 -> 73207 | F45: =Germany!$U$14 -> Esslinger Str. 83 | G45: =Germany!$U$18 -> Rental | H45: =Germany!$U$11 -> DE12 | I45: =Germany!$U$19 -> No | J45: =Germany!$U$13 -> Whole 1st floor | K45: =Germany!$U$24 -> 394.61 | L45: =Germany!$U$26 -> EUR | M45: =Germany!$U$28 -> 15 | N45: =Germany!$U$29 -> Indexation according to Consumer Price Index (VPI); adjustment if VPI increases by ≥ 5 %. No fixed annual percentage. | O45: =Germany!$U$27 -> 5148.69 | P45: =Germany!$U$30 -> 2.0222498 | Q45: =Germany!$U$46 -> 14, possible second workplace line (20-24) | R45: =Germany!$U$50 -> 14 | S45: =R45/Q45 -> #VALUE! | T45: =K45/R45 -> 28.186429 | U45: =K45/Q45 -> #VALUE! | V45: =Germany!$U$33 -> 43922 | W45: =Germany!$U$40 -> 46477 | X45: =Germany!$U$34 -> 46477 | Y45: =Germany!$U$42 -> No sublease agreement currently in place | Z45: =Germany!$U$43 -> No | AA45: =Germany!$U$44 -> No | AB45: =Germany!$U$9 -> Daniel Krauss | AC45: =Germany!$U$2 -> 0
A46: 1. Europe | B46: =Germany!$S$4 -> BU Germany (MKS) | C46: =Germany!$S$17 -> Germany | D46: =Germany!$S$15 -> Nürnberg | E46: =Germany!$S$16 -> 90429 | F46: =Germany!$S$14 -> Deutschherrnstraße 15-19 | G46: =Germany!$S$18 -> Rental | H46: =Germany!$S$11 -> DE13 | I46: =Germany!$S$19 -> No | J46: =Germany!$S$13 -> 2nd Floor Building B | K46: =Germany!$S$24 -> 660 | L46: =Germany!$S$26 -> EUR | M46: =Germany!$S$28 -> 3,57 EUR/m² | N46: =Germany!$S$29 -> 0 | O46: =Germany!$S$27 -> 13.135,67 EUR | P46: =Germany!$S$30 -> --- | Q46: =Germany!$S$46 -> 0 | R46: =Germany!$S$50 -> 0 | S46: =R46/Q46 -> #DIV/0! | T46: =K46/R46 -> #DIV/0! | U46: =K46/Q46 -> #DIV/0! | V46: =Germany!$S$33 -> 43770 | W46: =Germany!$S$40 -> 46326 | X46: =Germany!$S$34 -> 46326 | Y46: =Germany!$S$42 -> 0 | Z46: =Germany!$S$43 -> No | AA46: =Germany!$S$44 -> No | AB46: =Germany!$S$9 -> Daniel Krauss | AC46: =Germany!$S$2 -> 0
A47: 1. Europe | B47: =Germany!$T$4 -> BU Germany (REHACARE) | C47: =Germany!$T$17 -> Germany | D47: =Germany!$T$15 -> Nürnberg | E47: =Germany!$T$16 -> 90402 | F47: =Germany!$T$14 -> Karl-Grillenberger-Str. 1 | G47: =Germany!$T$18 -> Rental | H47: =Germany!$T$11 -> DE22 | I47: =Germany!$T$19 -> No | J47: =Germany!$T$13 -> 3rd Floor | K47: =Germany!$T$24 -> 53.4 | L47: =Germany!$T$26 -> EUR | M47: =Germany!$T$28 -> 21.52191 | N47: =Germany!$T$29 -> 0 | O47: =Germany!$T$27 -> 1149.27 | P47: =Germany!$T$30 -> --- | Q47: =Germany!$T$46 -> 3 | R47: =Germany!$T$50 -> 3 | S47: =R47/Q47 -> 1 | T47: =K47/R47 -> 17.8 | U47: =K47/Q47 -> 17.8 | V47: =Germany!$T$33 -> 43497 | W47: =Germany!$T$40 -> 0 | X47: =Germany!$T$34 -> undetermined | Y47: =Germany!$T$42 -> 0 | Z47: =Germany!$T$43 -> No | AA47: =Germany!$T$44 -> No | AB47: =Germany!$T$9 -> Daniel Krauss | AC47: =Germany!$T$2 -> 0
A48: 1. Europe | B48: =Germany!$V$4 -> BU Germany (REHACARE) | C48: =Germany!$V$17 -> Germany | D48: =Germany!$V$15 -> Pulsnitz | E48: =Germany!$V$16 -> 01896 | F48: =Germany!$V$14 -> Robert-Koch-Straße 9 | G48: =Germany!$V$18 -> Rental | H48: =Germany!$V$11 -> DE24 | I48: =Germany!$V$19 -> No | J48: =Germany!$V$13 -> 1st Floor | K48: =Germany!$V$24 -> 40 | L48: =Germany!$V$26 -> EUR | M48: =Germany!$V$28 -> 9.375 | N48: =Germany!$V$29 -> 0 | O48: =Germany!$V$27 -> 375 | P48: =Germany!$V$30 -> --- | Q48: =Germany!$V$46 -> 3 | R48: =Germany!$V$50 -> 3 | S48: =R48/Q48 -> 1 | T48: =K48/R48 -> 13.333333 | U48: =K48/Q48 -> 13.333333 | V48: =Germany!$V$33 -> 43891 | W48: =Germany!$V$40 -> 0 | X48: =Germany!$V$34 -> undetermined | Y48: =Germany!$V$42 -> no | Z48: =Germany!$V$43 -> No | AA48: =Germany!$V$44 -> No | AB48: =Germany!$V$9 -> Daniel Krauss | AC48: =Germany!$V$2 -> 0
A49: 1. Europe | B49: =Germany!$Z$4 -> BU Germany (REHACARE) | C49: =Germany!$Z$17 -> Germany | D49: =Germany!$Z$15 -> Weinheim | E49: =Germany!$Z$16 -> 69469 | F49: =Germany!$Z$14 -> Hildastr. 10 | G49: =Germany!$Z$18 -> Rental | H49: =Germany!$Z$11 -> DE27 | I49: =Germany!$Z$19 -> No | J49: =Germany!$Z$13 -> 1st Floor | K49: =Germany!$Z$24 -> 70 | L49: =Germany!$Z$26 -> EUR | M49: =Germany!$Z$28 -> 16.861429 | N49: =Germany!$Z$29 -> 0 | O49: =Germany!$Z$27 -> 1180.3 | P49: =Germany!$Z$30 -> 0 | Q49: =Germany!$Z$46 -> 3 | R49: =Germany!$Z$50 -> 3 | S49: =R49/Q49 -> 1 | T49: =K49/R49 -> 23.333333 | U49: =K49/Q49 -> 23.333333 | V49: =Germany!$Z$33 -> 43466 | W49: =Germany!$Z$40 -> 0 | X49: =Germany!$Z$34 -> undetermined | Y49: =Germany!$Z$42 -> no | Z49: =Germany!$Z$43 -> no | AA49: =Germany!$Z$44 -> 0 | AB49: =Germany!$Z$9 -> Daniel Krauss | AC49: =Germany!$Z$2 -> 0
A50: 1. Europe | B50: =Germany!$X$4 -> BU Germany (REHACARE) | C50: =Germany!$X$17 -> Germany | D50: =Germany!$X$15 -> Siegen | E50: =Germany!$X$16 -> 57076 | F50: =Germany!$X$14 -> Weidenauer Str. 167a | G50: =Germany!$X$18 -> Rental | H50: =Germany!$X$11 -> DE25 | I50: =Germany!$X$19 -> No | J50: =Germany!$X$13 -> 5th Floor | K50: =Germany!$X$24 -> 20 | L50: =Germany!$X$26 -> EUR | M50: =Germany!$X$28 -> 20.381 | N50: =Germany!$X$29 -> 0 | O50: =Germany!$X$27 -> 407.62 | P50: =Germany!$X$30 -> --- | Q50: =Germany!$X$46 -> 1 | R50: =Germany!$X$50 -> 1 | S50: =R50/Q50 -> 1 | T50: =K50/R50 -> 20 | U50: =K50/Q50 -> 20 | V50: =Germany!$X$33 -> 41730 | W50: =Germany!$X$40 -> 0 | X50: =Germany!$X$34 -> undetermined | Y50: =Germany!$X$42 -> no | Z50: =Germany!$X$43 -> no | AA50: =Germany!$X$44 -> No | AB50: =Germany!$X$9 -> Daniel Krauss | AC50: =Germany!$X$2 -> 0
A51: 1. Europe | B51: =Germany!$AA$4 -> BU Germany (REHACARE) | C51: =Germany!$AA$17 -> Germany | D51: =Germany!$AA$15 -> Unna | E51: =Germany!$AA$16 -> 59423 | F51: =Germany!$AA$14 -> Max-Planck-Str. 7 | G51: =Germany!$AA$18 -> Rental | H51: =Germany!$AA$11 -> DE28 | I51: =Germany!$AA$19 -> No | J51: =Germany!$AA$13 -> Ground Floor | K51: =Germany!$AA$24 -> 25 | L51: =Germany!$AA$26 -> EUR | M51: =Germany!$AA$28 -> 10.96 | N51: =Germany!$AA$29 -> 0 | O51: =Germany!$AA$27 -> 274 | P51: =Germany!$AA$30 -> 0 | Q51: =Germany!$AA$46 -> 1 | R51: =Germany!$AA$50 -> 1 | S51: =R51/Q51 -> 1 | T51: =K51/R51 -> 25 | U51: =K51/Q51 -> 25 | V51: =Germany!$AA$33 -> 42979 | W51: =Germany!$AA$40 -> 0 | X51: =Germany!$AA$34 -> undetermined | Y51: =Germany!$AA$42 -> no | Z51: =Germany!$AA$43 -> no | AA51: =Germany!$AA$44 -> No | AB51: =Germany!$AA$9 -> Daniel Krauss | AC51: =Germany!$AA$2 -> 0
A52: 1. Europe | B52: =Germany!$N$4 -> BU Germany (REHACARE) | C52: =Germany!$N$17 -> Germany | D52: =Germany!$N$15 -> Ludwigsburg | E52: =Germany!$N$16 -> 71640 | F52: =Germany!$N$14 -> Voithstr. 4 | G52: =Germany!$N$18 -> Rental | H52: =Germany!$N$11 -> DE18 | I52: =Germany!$N$19 -> No | J52: =Germany!$N$13 -> 1st Floor | K52: =Germany!$N$24 -> 108 | L52: =Germany!$N$26 -> EUR | M52: =Germany!$N$28 -> 13.817222 | N52: =Germany!$N$29 -> 0 | O52: =Germany!$N$27 -> 1492.26 | P52: =Germany!$N$30 -> --- | Q52: =Germany!$N$46 -> 3 | R52: =Germany!$N$50 -> 3 | S52: =R52/Q52 -> 1 | T52: =K52/R52 -> 36 | U52: =K52/Q52 -> 36 | V52: =Germany!$N$33 -> 42826 | W52: =Germany!$N$40 -> 46112 | X52: =Germany!$N$34 -> Contract terminated as of 31 March 2026 | Y52: =Germany!$N$42 -> 0 | Z52: =Germany!$N$43 -> No | AA52: =Germany!$N$44 -> No | AB52: =Germany!$N$9 -> Daniel Krauss | AC52: =Germany!$N$2 -> 0
A53: 1. Europe | B53: =Germany!$Q$4 -> BU Germany (REHACARE) | C53: =Germany!$Q$17 -> Germany | D53: =Germany!$Q$15 -> München | E53: =Germany!$Q$16 -> 80337 | F53: =Germany!$Q$14 -> Kapuzinerstraße 9D | G53: =Germany!$Q$18 -> Rental | H53: =Germany!$Q$11 -> DE21 | I53: =Germany!$Q$19 -> No | J53: =Germany!$Q$13 -> 2nd Floor | K53: =Germany!$Q$24 -> 385.15 | L53: =Germany!$Q$26 -> EUR | M53: =Germany!$Q$28 -> 29.808958 | N53: =Germany!$Q$29 -> 5 % index if consumer-index is high enough | O53: =Germany!$Q$27 -> 11480.92 | P53: =Germany!$Q$30 -> --- | Q53: =Germany!$Q$46 -> 16 | R53: =Germany!$Q$50 -> 16 | S53: =R53/Q53 -> 1 | T53: =K53/R53 -> 24.071875 | U53: =K53/Q53 -> 24.071875 | V53: =Germany!$Q$33 -> 43770 | W53: =Germany!$Q$40 -> undetermined | X53: =Germany!$Q$34 -> 46691 | Y53: =Germany!$Q$42 -> 0 | Z53: =Germany!$Q$43 -> yes | AA53: =Germany!$Q$44 -> No | AB53: =Germany!$Q$9 -> Daniel Krauss | AC53: =Germany!$Q$2 -> 0
A54: 1. Europe | B54: =Germany!$O$4 -> BU Germany (REHACARE) | C54: =Germany!$O$17 -> Germany | D54: =Germany!$O$15 -> Magdeburg | E54: =Germany!$O$16 -> 39104 | F54: =Germany!$O$14 -> Otto-von-Guericke-Straße 87a | G54: =Germany!$O$18 -> Rental | H54: =Germany!$O$11 -> DE19 | I54: =Germany!$O$19 -> No | J54: =Germany!$O$13 -> 6th Floor | K54: =Germany!$O$24 -> 433 | L54: =Germany!$O$26 -> EUR | M54: =Germany!$O$28 -> 10.332656 | N54: =Germany!$O$29 -> 0 | O54: =Germany!$O$27 -> 4474.04 | P54: =Germany!$O$30 -> --- | Q54: =Germany!$O$46 -> 11 | R54: =Germany!$O$50 -> 11 | S54: =R54/Q54 -> 1 | T54: =K54/R54 -> 39.363636 | U54: =K54/Q54 -> 39.363636 | V54: =Germany!$O$33 -> 40269 | W54: =Germany!$O$40 -> undetermined | X54: =Germany!$O$34 -> 47573 | Y54: =Germany!$O$42 -> 0 | Z54: =Germany!$O$43 -> yes | AA54: =Germany!$O$44 -> no | AB54: =Germany!$O$9 -> Daniel Krauss | AC54: =Germany!$O$2 -> 0
A55: 1. Europe | B55: =Germany!$G$4 -> BU Germany (REHACARE) | C55: =Germany!$G$17 -> Germany | D55: =Germany!$G$15 -> Bad Vilbel | E55: =Germany!$G$16 -> 61118 | F55: =Germany!$G$14 -> Frankfurter Str. 40 | G55: =Germany!$G$18 -> Rental | H55: =Germany!$G$11 -> DE14 | I55: =Germany!$G$19 -> No | J55: =Germany!$G$13 -> 1st Floor | K55: =Germany!$G$24 -> 45 | L55: =Germany!$G$26 -> EUR | M55: =Germany!$G$28 -> 15.555556 | N55: =Germany!$G$29 -> 0 | O55: =Germany!$G$27 -> 700 | P55: =Germany!$G$30 -> 0 | Q55: =Germany!$G$46 -> 2 | R55: =Germany!$G$50 -> 2 | S55: =R55/Q55 -> 1 | T55: =K55/R55 -> 22.5 | U55: =K55/Q55 -> 22.5 | V55: =Germany!$G$33 -> 43922 | W55: =Germany!$G$40 -> undetermined | X55: =Germany!$G$34 -> not fixed | Y55: =Germany!$G$42 -> 0 | Z55: =Germany!$G$43 -> No | AA55: =Germany!$G$44 -> No | AB55: =Germany!$G$9 -> Daniel Krauss | AC55: =Germany!$G$2 -> 0
A56: 1. Europe | B56: =Germany!$K$4 -> BU Germany (REHACARE) | C56: =Germany!$K$17 -> Germany | D56: =Germany!$K$15 -> Hamburg | E56: =Germany!$K$16 -> 22805 | F56: =Germany!$K$14 -> Stormsweg 3 | G56: =Germany!$K$18 -> Rental | H56: =Germany!$K$11 -> DE16 | I56: =Germany!$K$19 -> No | J56: =Germany!$K$13 -> 1st Floor | K56: =Germany!$K$24 -> 42 | L56: =Germany!$K$26 -> EUR | M56: =Germany!$K$28 -> 17.85 | N56: =Germany!$K$29 -> 2 % per year starting 2027 | O56: =Germany!$K$27 -> 749.7 | P56: =Germany!$K$30 -> --- | Q56: =Germany!$K$46 -> 2 | R56: =Germany!$K$50 -> 2 | S56: =R56/Q56 -> 1 | T56: =K56/R56 -> 21 | U56: =K56/Q56 -> 21 | V56: =Germany!$K$33 -> 45884 | W56: =Germany!$K$40 -> undetermined | X56: =Germany!$K$34 -> undetermined | Y56: =Germany!$K$42 -> 0 | Z56: =Germany!$K$43 -> No | AA56: =Germany!$K$44 -> No | AB56: =Germany!$K$9 -> Daniel Krauss | AC56: =Germany!$K$2 -> 0
A57: 1. Europe | B57: =Germany!$L$4 -> BU Germany (REHACARE) | C57: =Germany!$L$17 -> Germany | D57: =Germany!$L$15 -> Jena | E57: =Germany!$L$16 -> 07743 | F57: =Germany!$L$14 -> Dornburger Str. 161 | G57: =Germany!$L$18 -> Rental | H57: =Germany!$L$11 -> DE17 | I57: =Germany!$L$19 -> No | J57: =Germany!$L$13 -> 1st Floor | K57: =Germany!$L$24 -> 48.16 | L57: =Germany!$L$26 -> EUR | M57: =Germany!$L$28 -> 12.377492 | N57: =Germany!$L$29 -> 0 | O57: =Germany!$L$27 -> 596.1 | P57: =Germany!$L$30 -> --- | Q57: =Germany!$L$46 -> 2 | R57: =Germany!$L$50 -> 2 | S57: =R57/Q57 -> 1 | T57: =K57/R57 -> 24.08 | U57: =K57/Q57 -> 24.08 | V57: =Germany!$L$33 -> 43040 | W57: =Germany!$L$40 -> undetermined | X57: =Germany!$L$34 -> undetermined | Y57: =Germany!$L$42 -> 0 | Z57: =Germany!$L$43 -> No | AA57: =Germany!$L$44 -> No | AB57: =Germany!$L$9 -> Daniel Krauss | AC57: =Germany!$L$2 -> 0
A58: 1. Europe | B58: =Germany!$P$4 -> BU Germany (REHACARE) | C58: =Germany!$P$17 -> Germany | D58: =Germany!$P$15 -> Meisenheim | E58: =Germany!$P$16 -> 55590 | F58: =Germany!$P$14 -> Marktgasse 7b | G58: =Germany!$P$18 -> Rental | H58: =Germany!$P$11 -> DE20 | I58: =Germany!$P$19 -> No | J58: =Germany!$P$13 -> 1st Floor | K58: =Germany!$P$24 -> 30 | L58: =Germany!$P$26 -> EUR | M58: =Germany!$P$28 -> 10.71 | N58: =Germany!$P$29 -> 0 | O58: =Germany!$P$27 -> 321.3 | P58: =Germany!$P$30 -> --- | Q58: =Germany!$P$46 -> 1 | R58: =Germany!$P$50 -> 1 | S58: =R58/Q58 -> 1 | T58: =K58/R58 -> 30 | U58: =K58/Q58 -> 30 | V58: =Germany!$P$33 -> 43282 | W58: =Germany!$P$40 -> undetermined | X58: =Germany!$P$34 -> undetermined | Y58: =Germany!$P$42 -> 0 | Z58: =Germany!$P$43 -> No | AA58: =Germany!$P$44 -> No | AB58: =Germany!$P$9 -> Daniel Krauss | AC58: =Germany!$P$2 -> 0
A59: 1. Europe | B59: =Germany!$AE$4 -> Global Office | C59: =Germany!$AE$17 -> Germany | D59: =Germany!$AE$15 -> Munich | E59: =Germany!$AE$16 -> 81671 | F59: =Germany!$AE$14 -> Atelierstrasse 14 | G59: =Germany!$AE$18 -> Rental | H59: =Germany!$AE$11 -> DE29 | I59: =Germany!$AE$19 -> No | J59: =Germany!$AE$13 -> 4th and 5th floor | K59: =Germany!$AE$24 -> 1266 | L59: =Germany!$AE$26 -> EUR | M59: =Germany!$AE$28 -> 434 | N59: =Germany!$AE$29 -> CPI | O59: =Germany!$AE$27 -> 0 | P59: =Germany!$AE$30 -> 400000 | Q59: =Germany!$AE$46 -> 150 | R59: =Germany!$AE$50 -> 65 | S59: =R59/Q59 -> 0.43333333 | T59: =K59/R59 -> 19.476923 | U59: =K59/Q59 -> 8.44 | V59: =Germany!$AE$33 -> 44317 | W59: =Germany!$AE$40 -> 46142 | X59: =Germany!$AE$34 -> 46142 | Y59: =Germany!$AE$42 -> No | Z59: =Germany!$AE$43 -> Yes | AA59: =Germany!$AE$44 -> No | AB59: =Germany!$AE$9 -> 0 | AC59: =Germany!$AE$2 -> 0
A60: 1. Europe | B60: =Greece!$F$4 -> BU Greece | C60: =Greece!$F$17 -> Greece | D60: =Greece!$F$15 -> Thessaloniki | E60: =Greece!$F$16 -> 57001 | F60: =Greece!$F$14 -> 17km Poligirou, Thermi | G60: =Greece!$F$18 -> Rental | H60: =Greece!$F$11 -> GR03 | I60: =Greece!$F$19 -> No | J60: =Greece!$F$13 -> whole building | K60: =Greece!$F$24 -> 440 | L60: =Greece!$F$26 -> EUR | M60: =Greece!$F$28 -> 62.73 | N60: =Greece!$F$29 -> 0.03 | O60: =Greece!$F$27 -> 0 | P60: =Greece!$F$30 -> 75267.141 | Q60: =Greece!$F$46 -> 70 | R60: =Greece!$F$50 -> 60 | S60: =R60/Q60 -> 0.85714286 | T60: =K60/R60 -> 7.3333333 | U60: =K60/Q60 -> 6.2857143 | V60: =Greece!$F$33 -> 44562 | W60: =Greece!$F$40 -> 46752 | X60: =Greece!$F$34 -> 46752 | Y60: =Greece!$F$42 -> No | Z60: =Greece!$F$43 -> NO | AA60: =Greece!$F$44 -> No | AB60: =Greece!$F$9 -> 0 | AC60: =Greece!$F$2 -> 0
A61: 1. Europe | B61: =Greece!$D$4 -> BU Greece | C61: =Greece!$D$17 -> Greece | D61: =Greece!$D$15 -> Athens | E61: =Greece!$D$16 -> 17342 | F61: =Greece!$D$14 -> 10 Premetis Str. | G61: =Greece!$D$18 -> Rental | H61: =Greece!$D$11 -> GR01 | I61: =Greece!$D$19 -> No | J61: =Greece!$D$13 -> whole building | K61: =Greece!$D$24 -> 843.18 | L61: =Greece!$D$26 -> EUR | M61: =Greece!$D$28 -> 136.16 | N61: =Greece!$D$29 -> 0.03 | O61: =Greece!$D$27 -> 0 | P61: =Greece!$D$30 -> 144235.79 | Q61: =Greece!$D$46 -> 54 | R61: =Greece!$D$50 -> 50 | S61: =R61/Q61 -> 0.92592593 | T61: =K61/R61 -> 16.8636 | U61: =K61/Q61 -> 15.614444 | V61: =Greece!$D$33 -> 44927 | W61: =Greece!$D$40 -> 46752 | X61: =Greece!$D$34 -> 46752 | Y61: =Greece!$D$42 -> No | Z61: =Greece!$D$43 -> NO | AA61: =Greece!$D$44 -> No | AB61: =Greece!$D$9 -> 0 | AC61: =Greece!$D$2 -> 45926
A62: 1. Europe | B62: =Greece!$G$4 -> BU Greece | C62: =Greece!$G$17 -> Greece | D62: =Greece!$G$15 -> Athens | E62: =Greece!$G$16 -> 17342 | F62: =Greece!$G$14 -> 370 Vouliagmenis Av | G62: =Greece!$G$18 -> Rental | H62: =Greece!$G$11 -> GR04 | I62: =Greece!$G$19 -> No | J62: =Greece!$G$13 -> 2 floors | K62: =Greece!$G$24 -> 687.32 | L62: =Greece!$G$26 -> EUR | M62: =Greece!$G$28 -> 66.92 | N62: =Greece!$G$29 -> 0.03 | O62: =Greece!$G$27 -> 0 | P62: =Greece!$G$30 -> 85500 | Q62: =Greece!$G$46 -> 181 | R62: =Greece!$G$50 -> 50 | S62: =R62/Q62 -> 0.27624309 | T62: =K62/R62 -> 13.7464 | U62: =K62/Q62 -> 3.7973481 | V62: =Greece!$G$33 -> not provided | W62: =Greece!$G$40 -> indefinite | X62: =Greece!$G$34 -> indefinite | Y62: =Greece!$G$42 -> No | Z62: =Greece!$G$43 -> NO | AA62: =Greece!$G$44 -> No | AB62: =Greece!$G$9 -> 0 | AC62: =Greece!$G$2 -> 0
A63: 1. Europe | B63: =Greece!$E$4 -> BU Greece | C63: =Greece!$E$17 -> Greece | D63: =Greece!$E$15 -> Athens | E63: =Greece!$E$16 -> 17342 | F63: =Greece!$E$14 -> 3 Premetis Str. | G63: =Greece!$E$18 -> Rental | H63: =Greece!$E$11 -> GR02 | I63: =Greece!$E$19 -> No | J63: =Greece!$E$13 -> 2 floors | K63: =Greece!$E$24 -> 210 | L63: =Greece!$E$26 -> EUR | M63: =Greece!$E$28 -> 161.65 | N63: =Greece!$E$29 -> 0.03 | O63: =Greece!$E$27 -> 0 | P63: =Greece!$E$30 -> 48000 | Q63: =Greece!$E$46 -> 55 | R63: =Greece!$E$50 -> 53 | S63: =R63/Q63 -> 0.96363636 | T63: =K63/R63 -> 3.9622642 | U63: =K63/Q63 -> 3.8181818 | V63: =Greece!$E$33 -> not provided | W63: =Greece!$E$40 -> indefinite | X63: =Greece!$E$34 -> indefinite | Y63: =Greece!$E$42 -> No | Z63: =Greece!$E$43 -> NO | AA63: =Greece!$E$44 -> No | AB63: =Greece!$E$9 -> 0 | AC63: =Greece!$E$2 -> 0
A64: 2. Asia | B64: =Hongkong!$D$4 -> BU Hongkong | C64: =Hongkong!$D$17 -> Hongkong, China | D64: =Hongkong!$D$15 -> Hongkong | E64: =Hongkong!$D$16 -> 999077 | F64: =Hongkong!$D$14 -> 12 Taikoo Wan Road, Taikoo Shing | G64: =Hongkong!$D$18 -> Rental | H64: =Hongkong!$D$11 -> HK01 | I64: =Hongkong!$D$19 -> Yes | J64: =Hongkong!$D$13 -> Suites 304 - 306 | K64: =Hongkong!$D$24 -> 471.94724 | L64: =Hongkong!$D$26 -> HKD | M64: =Hongkong!$D$28 -> 6716.683 | N64: =Hongkong!$D$29 -> N/A | O64: =Hongkong!$D$27 -> 0 | P64: =Hongkong!$D$30 -> 955.83566 | Q64: =Hongkong!$D$46 -> 62 | R64: =Hongkong!$D$50 -> 73 | S64: =R64/Q64 -> 1.1774194 | T64: =K64/R64 -> 6.4650307 | U64: =K64/Q64 -> 7.6120523 | V64: =Hongkong!$D$33 -> 45031 | W64: =Hongkong!$D$40 -> 46491 | X64: =Hongkong!$D$34 -> 46491 | Y64: =Hongkong!$D$42 -> No | Z64: =Hongkong!$D$43 -> No | AA64: =Hongkong!$D$44 -> No | AB64: =Hongkong!$D$9 -> 0 | AC64: =Hongkong!$D$2 -> 0
A65: 1. Europe | B65: =Hungary!$D$4 -> BU Austria | C65: =Hungary!$D$17 -> Hungary | D65: =Hungary!$D$15 -> Budapest | E65: =Hungary!$D$16 -> 1087 | F65: =Hungary!$D$14 -> Könyves Kalman krt. 48-52 | G65: =Hungary!$D$18 -> Rental | H65: =Hungary!$D$11 -> HU01 | I65: =Hungary!$D$19 -> Yes | J65: =Hungary!$D$13 -> part of a floor | K65: =Hungary!$D$24 -> 158.6 | L65: =Hungary!$D$26 -> EUR | M65: =Hungary!$D$28 -> 11,4/m² | N65: =Hungary!$D$29 -> CPI | O65: =Hungary!$D$27 -> 0 | P65: =Hungary!$D$30 -> 7,8/m2 | Q65: =Hungary!$D$46 -> 22 +3 from Jan 2026 | R65: =Hungary!$D$50 -> 13 | S65: =R65/Q65 -> #VALUE! | T65: =K65/R65 -> 12.2 | U65: =K65/Q65 -> #VALUE! | V65: =Hungary!$D$33 -> 44652 | W65: =Hungary!$D$40 -> 46477 | X65: =Hungary!$D$34 -> 46477 | Y65: =Hungary!$D$42 -> No | Z65: =Hungary!$D$43 -> Yes | AA65: =Hungary!$D$44 -> No | AB65: =Hungary!$D$9 -> 0 | AC65: =Hungary!$D$2 -> 45919
A66: 2. Asia | B66: =India!$E$4 -> BU India | C66: =India!$E$17 -> India | D66: =India!$E$15 -> Gurgaon, Haryana | E66: =India!$E$16 -> 122002 | F66: =India!$E$14 -> Unit No. 601-620 And 701-724, Spaze Business Park, Sec - 66 | G66: =India!$E$18 -> Rental | H66: =India!$E$11 -> IN02 | I66: =India!$E$19 -> No | J66: =India!$E$13 -> 6th and 7th floor | K66: =India!$E$24 -> 3532.4523 | L66: =India!$E$26 -> INR | M66: =India!$E$28 -> 9687.5194 | N66: =India!$E$29 -> Next escalation iis 10% in 2024 Sept | O66: =India!$E$27 -> 0 | P66: =India!$E$30 -> 5861.2204 | Q66: =India!$E$46 -> 1425 | R66: =India!$E$50 -> 782 | S66: =R66/Q66 -> 0.54877193 | T66: =K66/R66 -> 4.5172024 | U66: =K66/Q66 -> 2.4789139 | V66: =India!$E$33 -> 44606 | W66: =India!$E$40 -> 46796 | X66: =India!$E$34 -> anytime - 6 months notice | Y66: =India!$E$42 -> No | Z66: =India!$E$43 -> No | AA66: =India!$E$44 -> Yes | AB66: =India!$E$9 -> 0 | AC66: =India!$E$2 -> 0
A67: 2. Asia | B67: =India!$G$4 -> BU India | C67: =India!$G$17 -> India | D67: =India!$G$15 -> Gurugram | E67: =India!$G$16 -> 122101 | F67: =India!$G$14 -> International Tech Park Gurgaon, Block-1, 8th Floor | IT/ITES SEZ, Village Behrampur, Near Sector 59 Gurugram 122101 Haryana | India | G67: =India!$G$18 -> Rental | H67: =India!$G$11 -> IN04 | I67: =India!$G$19 -> No | J67: =India!$G$13 -> 8th Floor, Block-1 | K67: =India!$G$24 -> 1836.6931 | L67: =India!$G$26 -> INR | M67: =India!$G$28 -> 67.781993 | N67: =India!$G$29 -> 0.05 | O67: =India!$G$27 -> 1340050 | P67: =India!$G$30 -> 135.94911 | Q67: =India!$G$46 -> 639 | R67: =India!$G$50 -> 227 | S67: =R67/Q67 -> 0.35524257 | T67: =K67/R67 -> 8.091159 | U67: =K67/Q67 -> 2.8743241 | V67: =India!$G$33 -> 45689 | W67: =India!$G$40 -> 47514 | X67: =India!$G$34 -> 46783 | Y67: =India!$G$42 -> NA | Z67: =India!$G$43 -> No | AA67: =India!$G$44 -> Yes (LEED) | AB67: =India!$G$9 -> India GSD | AC67: =India!$G$2 -> 0
A68: 2. Asia | B68: =India!$F$4 -> BU India | C68: =India!$F$17 -> India | D68: =India!$F$15 -> Noida, Uttar Pradesh | E68: =India!$F$16 -> 201301 | F68: =India!$F$14 -> 11th Floor, Tower -03, Candor Techspace IT Park, Plot No. B-2, Sector 62, Noida | G68: =India!$F$18 -> Rental | H68: =India!$F$11 -> IN03 | I68: =India!$F$19 -> No | J68: =India!$F$13 -> 11th floor | K68: =India!$F$24 -> 1243.0427 | L68: =India!$F$26 -> INR | M68: =India!$F$28 -> 6716.6801 | N68: =India!$F$29 -> Next escaltion is 15% in 2025 Jun | O68: =India!$F$27 -> 0 | P68: =India!$F$30 -> 4977.2513 | Q68: =India!$F$46 -> 352 | R68: =India!$F$50 -> 286 | S68: =R68/Q68 -> 0.8125 | T68: =K68/R68 -> 4.3463031 | U68: =K68/Q68 -> 3.5313713 | V68: =India!$F$33 -> 44727 | W68: =India!$F$40 -> 46918 | X68: =India!$F$34 -> anytime - 6 months notice | Y68: =India!$F$42 -> No | Z68: =India!$F$43 -> No | AA68: =India!$F$44 -> Yes | AB68: =India!$F$9 -> 0 | AC68: =India!$F$2 -> 0
A69: 2. Asia | B69: =India!$D$4 -> BU India | C69: =India!$D$17 -> India | D69: =India!$D$15 -> Gurgaon, Haryana | E69: =India!$D$16 -> 122002 | F69: =India!$D$14 -> DLF Square, M- Block, Jacaranda Marg, DLF City Phase-2 | G69: =India!$D$18 -> Rental | H69: =India!$D$11 -> IN01 | I69: =India!$D$19 -> No | J69: =India!$D$13 -> 1st floor | K69: =India!$D$24 -> 945.75 | L69: =India!$D$26 -> INR | M69: =India!$D$28 -> 14079.195 | N69: =India!$D$29 -> Next escaltion is 15% in 2024 Nov | O69: =India!$D$27 -> 0 | P69: =India!$D$30 -> 3623.0037 | Q69: =India!$D$46 -> 79 | R69: =India!$D$50 -> 87 | S69: =R69/Q69 -> 1.1012658 | T69: =K69/R69 -> 10.87069 | U69: =K69/Q69 -> 11.971519 | V69: =India!$D$33 -> 44501 | W69: =India!$D$40 -> 46326 | X69: =India!$D$34 -> anytime - 6 months notice | Y69: =India!$D$42 -> No | Z69: =India!$D$43 -> No | AA69: =India!$D$44 -> No | AB69: =India!$D$9 -> 0 | AC69: =India!$D$2 -> 45925
A70: 2. Asia | B70: =Indonesia!$D$4 -> BU Indonesia | C70: =Indonesia!$D$17 -> Indonesia | D70: =Indonesia!$D$15 -> Jakarta | E70: =Indonesia!$D$16 -> 12980 | F70: =Indonesia!$D$14 -> Gedung World Trade Centre, 6 Lantai 3A, JL Jenoral Sudirman Kavling 29-21 Karet Setiabudi Kota Adm, Jakarta Selantan Dki Jakarta | G70: =Indonesia!$D$18 -> Rental | H70: =Indonesia!$D$11 -> ID01 | I70: =Indonesia!$D$19 -> No | J70: =Indonesia!$D$13 -> 1 floor at level 6 | K70: =Indonesia!$D$24 -> 332.06 | L70: =Indonesia!$D$26 -> IDR | M70: =Indonesia!$D$28 -> 1740000 | N70: =Indonesia!$D$29 -> 0 | O70: =Indonesia!$D$27 -> 0 | P70: =Indonesia!$D$30 -> 1416000 | Q70: =Indonesia!$D$46 -> 38 | R70: =Indonesia!$D$50 -> 51 | S70: =R70/Q70 -> 1.3421053 | T70: =K70/R70 -> 6.5109804 | U70: =K70/Q70 -> 8.7384211 | V70: =Indonesia!$D$33 -> 44317 | W70: =Indonesia!$D$40 -> 47968 | X70: =Indonesia!$D$34 -> 47968 | Y70: =Indonesia!$D$42 -> No | Z70: =Indonesia!$D$43 -> 0 | AA70: =Indonesia!$D$44 -> No | AB70: =Indonesia!$D$9 -> 0 | AC70: =Indonesia!$D$2 -> 0
A71: 4. H&L | B71: =Ireland!$G$4 -> 0 | C71: =Ireland!$G$17 -> Ireland | D71: =Ireland!$G$15 -> Dublin | E71: =Ireland!$G$16 -> D12 XE93 | F71: =Ireland!$G$14 -> Building 12 B Joyce Way, Park West Business Campus, Nangor Road, | G71: =Ireland!$G$18 -> Owned | H71: =Ireland!$G$11 -> IR04 | I71: =Ireland!$G$19 -> N/A | J71: =Ireland!$G$13 -> Whole Building | K71: =Ireland!$G$24 -> 1773.08 | L71: =Ireland!$G$26 -> EUR | M71: =Ireland!$G$28 -> 190 | N71: =Ireland!$G$29 -> N/A | O71: =Ireland!$G$27 -> 0 | P71: =Ireland!$G$30 -> 346138.17 | Q71: =Ireland!$G$46 -> 310 | R71: =Ireland!$G$50 -> 206 | S71: =R71/Q71 -> 0.66451613 | T71: =K71/R71 -> 8.6071845 | U71: =K71/Q71 -> 5.7196129 | V71: =Ireland!$G$33 -> N/A | W71: =Ireland!$G$40 -> N/A | X71: =Ireland!$G$34 -> N/A | Y71: =Ireland!$G$42 -> No | Z71: =Ireland!$G$43 -> Yes | AA71: =Ireland!$G$44 -> No | AB71: =Ireland!$G$9 -> 0 | AC71: =Ireland!$G$2 -> 0
A72: 4. H&L | B72: =Ireland!$H$4 -> 0 | C72: =Ireland!$H$17 -> Ireland | D72: =Ireland!$H$15 -> Dublin | E72: =Ireland!$H$16 -> D12 P651 | F72: =Ireland!$H$14 -> Building 15 Joyce Way, Park West Business Campus, Nangor Road, | G72: =Ireland!$H$18 -> Owned | H72: =Ireland!$H$11 -> IR05 | I72: =Ireland!$H$19 -> N/A | J72: =Ireland!$H$13 -> Whole Building | K72: =Ireland!$H$24 -> 2530.52 | L72: =Ireland!$H$26 -> EUR | M72: =Ireland!$H$28 -> 190 | N72: =Ireland!$H$29 -> N/A | O72: =Ireland!$H$27 -> 0 | P72: =Ireland!$H$30 -> 494004.53 | Q72: =Ireland!$H$46 -> 305 | R72: =Ireland!$H$50 -> 192 | S72: =R72/Q72 -> 0.6295082 | T72: =K72/R72 -> 13.179792 | U72: =K72/Q72 -> 8.2967869 | V72: =Ireland!$H$33 -> N/A | W72: =Ireland!$H$40 -> N/A | X72: =Ireland!$H$34 -> N/A | Y72: =Ireland!$H$42 -> No | Z72: =Ireland!$H$43 -> yes | AA72: =Ireland!$H$44 -> No | AB72: =Ireland!$H$9 -> 0 | AC72: =Ireland!$H$2 -> 0
A73: 4. H&L | B73: =Ireland!$E$4 -> 0 | C73: =Ireland!$E$17 -> Ireland | D73: =Ireland!$E$15 -> Dublin | E73: =Ireland!$E$16 -> D12 C4V6 | F73: =Ireland!$E$14 -> Building 11 B Joyce Way, Park West Business Campus, Nangor Road, | G73: =Ireland!$E$18 -> Owned | H73: =Ireland!$E$11 -> IR02 | I73: =Ireland!$E$19 -> N/A | J73: =Ireland!$E$13 -> Whole Building | K73: =Ireland!$E$24 -> 1968.2 | L73: =Ireland!$E$26 -> EUR | M73: =Ireland!$E$28 -> 190 | N73: =Ireland!$E$29 -> N/A | O73: =Ireland!$E$27 -> 0 | P73: =Ireland!$E$30 -> 384229.22 | Q73: =Ireland!$E$46 -> 203 | R73: =Ireland!$E$50 -> 125 | S73: =R73/Q73 -> 0.61576355 | T73: =K73/R73 -> 15.7456 | U73: =K73/Q73 -> 9.6955665 | V73: =Ireland!$E$33 -> N/A | W73: =Ireland!$E$40 -> N/A | X73: =Ireland!$E$34 -> N/A | Y73: =Ireland!$E$42 -> Yes | Z73: =Ireland!$E$43 -> Yes | AA73: =Ireland!$E$44 -> No | AB73: =Ireland!$E$9 -> 0 | AC73: =Ireland!$E$2 -> 0
A74: 4. H&L | B74: =Ireland!$I$4 -> 0 | C74: =Ireland!$I$17 -> Ireland | D74: =Ireland!$I$15 -> Dublin | E74: =Ireland!$I$16 -> D12 C4V6 | F74: =Ireland!$I$14 -> Building 11 B Joyce Way, Park West Business Campus, Nangor Road, | G74: =Ireland!$I$18 -> Sublease | H74: =Ireland!$I$11 -> IR02 | I74: =Ireland!$I$19 -> N/A - we own building | J74: =Ireland!$I$13 -> Part of 2nd Floor | K74: =Ireland!$I$24 -> 198 | L74: =Ireland!$I$26 -> EUR | M74: =Ireland!$I$28 -> 75.757576 | N74: =Ireland!$I$29 -> Fixed | O74: =Ireland!$I$27 -> 45000 | P74: =Ireland!$I$30 -> Pro rata - 10.72% of 11B | Q74: =Ireland!$I$46 -> 25 | R74: =Ireland!$I$50 -> 16 | S74: =R74/Q74 -> 0.64 | T74: =K74/R74 -> 12.375 | U74: =K74/Q74 -> 7.92 | V74: =Ireland!$I$33 -> 24/10/2015 - revised Jan 25 | W74: =Ireland!$I$40 -> open end | X74: =Ireland!$I$34 -> 3 months notice required | Y74: =Ireland!$I$42 -> Licences with AGA for area of 11B. AGA pay a licence fee per sqm, pay a portion of the buildng charges. No end date and 3 months termiantion for both parties | Z74: =Ireland!$I$43 -> Yes | AA74: =Ireland!$I$44 -> No | AB74: =Ireland!$I$9 -> 0 | AC74: =Ireland!$I$2 -> 0
A75: 4. H&L | B75: =Ireland!$J$4 -> 0 | C75: =Ireland!$J$17 -> Ireland | D75: =Ireland!$J$15 -> Dublin | E75: =Ireland!$J$16 -> D12 C4V6 | F75: =Ireland!$J$14 -> Building 11 B Joyce Way, Park West Business Campus, Nangor Road, | G75: =Ireland!$J$18 -> Sublease | H75: =Ireland!$J$11 -> IR02 | I75: =Ireland!$J$19 -> N/A - we own building | J75: =Ireland!$J$13 -> Part of 2nd Floor | K75: =Ireland!$J$24 -> 96 | L75: =Ireland!$J$26 -> EUR | M75: =Ireland!$J$28 -> 208.33333 | N75: =Ireland!$J$29 -> Fixed | O75: =Ireland!$J$27 -> 20000 | P75: =Ireland!$J$30 -> Rates only | Q75: =Ireland!$J$46 -> 0 | R75: =Ireland!$J$50 -> 0 | S75: =R75/Q75 -> #DIV/0! | T75: =K75/R75 -> #DIV/0! | U75: =K75/Q75 -> #DIV/0! | V75: =Ireland!$J$33 -> 44503 | W75: =Ireland!$J$40 -> open end | X75: =Ireland!$J$34 -> N/A | Y75: =Ireland!$J$42 -> Licences with Allianz Ireland for area of 11B. Allianz Ireland pay a licence fee per sqm, pay aportion of the buildng charges. No end date and 3 months termiantion for both parties | Z75: =Ireland!$J$43 -> 0 | AA75: =Ireland!$J$44 -> Yes - we own the building | AB75: =Ireland!$J$9 -> 0 | AC75: =Ireland!$J$2 -> 0
A76: 4. H&L | B76: =Ireland!$K$4 -> 0 | C76: =Ireland!$K$17 -> Ireland | D76: =Ireland!$K$15 -> Dublin | E76: =Ireland!$K$16 -> D12 C4V6 | F76: =Ireland!$K$14 -> Building 11 B Joyce Way, Park West Business Campus, Nangor Road, | G76: =Ireland!$K$18 -> Sublease | H76: =Ireland!$K$11 -> IR02 | I76: =Ireland!$K$19 -> N/A - we own building | J76: =Ireland!$K$13 -> Part of 1st Floor | K76: =Ireland!$K$24 -> 179 | L76: =Ireland!$K$26 -> EUR | M76: =Ireland!$K$28 -> 181,47 year/m² (true up) | N76: =Ireland!$K$29 -> Fi9xed | O76: =Ireland!$K$27 -> 160000 | P76: =Ireland!$K$30 -> 35.41% of 11B | Q76: =Ireland!$K$46 -> 0 | R76: =Ireland!$K$50 -> 0 | S76: =R76/Q76 -> #DIV/0! | T76: =K76/R76 -> #DIV/0! | U76: =K76/Q76 -> #DIV/0! | V76: =Ireland!$K$33 -> 18/12/2019 - - in revision currently - awating their variations | W76: =Ireland!$K$40 -> open end | X76: =Ireland!$K$34 -> N/A | Y76: =Ireland!$K$42 -> Licences with Allianz Technology for area of 11B. Allianz Technology pay a licence fee per sqm, pay aportion of the buildng charges. No end date and 3 months termiantion for both parties | Z76: =Ireland!$K$43 -> Yes | AA76: =Ireland!$K$44 -> Yes - we own the building | AB76: =Ireland!$K$9 -> 0 | AC76: =Ireland!$K$2 -> 0
A77: 4. H&L | B77: =Ireland!$F$4 -> 0 | C77: =Ireland!$F$17 -> Ireland | D77: =Ireland!$F$15 -> Dublin | E77: =Ireland!$F$16 -> D12 KD63 | F77: =Ireland!$F$14 -> Building 12 A Joyce Way, Park West Business Campus, Nangor Road, | G77: =Ireland!$F$18 -> Owned | H77: =Ireland!$F$11 -> IR03 | I77: =Ireland!$F$19 -> N/A | J77: =Ireland!$F$13 -> Whole Building | K77: =Ireland!$F$24 -> 1523.88 | L77: =Ireland!$F$26 -> EUR | M77: =Ireland!$F$28 -> 190 | N77: =Ireland!$F$29 -> N/A | O77: =Ireland!$F$27 -> 0 | P77: =Ireland!$F$30 -> 297489.69 | Q77: =Ireland!$F$46 -> 0 | R77: =Ireland!$F$50 -> 0 | S77: =R77/Q77 -> #DIV/0! | T77: =K77/R77 -> #DIV/0! | U77: =K77/Q77 -> #DIV/0! | V77: =Ireland!$F$33 -> N/A | W77: =Ireland!$F$40 -> N/A | X77: =Ireland!$F$34 -> N/A | Y77: =Ireland!$F$42 -> No | Z77: =Ireland!$F$43 -> Yes | AA77: =Ireland!$F$44 -> No | AB77: =Ireland!$F$9 -> 0 | AC77: =Ireland!$F$2 -> 0
A78: 4. H&L | B78: =Ireland!$D$4 -> International Health | C78: =Ireland!$D$17 -> Ireland | D78: =Ireland!$D$15 -> Dublin | E78: =Ireland!$D$16 -> D12 C4V6 | F78: =Ireland!$D$14 -> Building 11 A Joyce Way, Park West Business Campus, Nangor Road, | G78: =Ireland!$D$18 -> Owned | H78: =Ireland!$D$11 -> IR01 | I78: =Ireland!$D$19 -> N/A | J78: =Ireland!$D$13 -> Whole Building | K78: =Ireland!$D$24 -> 1937 | L78: =Ireland!$D$26 -> EUR | M78: =Ireland!$D$28 -> 190 | N78: =Ireland!$D$29 -> N/A | O78: =Ireland!$D$27 -> 0 | P78: =Ireland!$D$30 -> 378138.4 | Q78: =Ireland!$D$46 -> 130 | R78: =Ireland!$D$50 -> 137 | S78: =R78/Q78 -> 1.0538462 | T78: =K78/R78 -> 14.138686 | U78: =K78/Q78 -> 14.9 | V78: =Ireland!$D$33 -> N/A | W78: =Ireland!$D$40 -> N/A | X78: =Ireland!$D$34 -> N/A | Y78: =Ireland!$D$42 -> No | Z78: =Ireland!$D$43 -> Yes | AA78: =Ireland!$D$44 -> No | AB78: =Ireland!$D$9 -> seamus.reilly@allianz.com | AC78: =Ireland!$D$2 -> 45919
A79: 1. Europe | B79: =Italy!$E$4 -> BU Italy | C79: =Italy!$E$17 -> Italy | D79: =Italy!$E$15 -> Casarano (LE) | E79: =Italy!$E$16 -> 73042 | F79: =Italy!$E$14 -> Z.I. Tronco I | G79: =Italy!$E$18 -> Rental | H79: =Italy!$E$11 -> IT02 | I79: =Italy!$E$19 -> No | J79: =Italy!$E$13 -> Ground & 1st floor | K79: =Italy!$E$24 -> 1305 | L79: =Italy!$E$26 -> EUR | M79: =Italy!$E$28 -> 40.353257 | N79: =Italy!$E$29 -> annual adjustment through revaluation equal to 75% of the change in the ISTAT index, starting from the second year | O79: =Italy!$E$27 -> 50895 € / year | P79: =Italy!$E$30 -> 70000 | Q79: =Italy!$E$46 -> 154 | R79: =Italy!$E$50 -> 295 | S79: =R79/Q79 -> 1.9155844 | T79: =K79/R79 -> 4.4237288 | U79: =K79/Q79 -> 8.474026 | V79: =Italy!$E$33 -> 43101 | W79: =Italy!$E$40 -> 47848 | X79: =Italy!$E$34 -> 47848 | Y79: =Italy!$E$42 -> No | Z79: =Italy!$E$43 -> Yes | AA79: =Italy!$E$44 -> No | AB79: =Italy!$E$9 -> 0 | AC79: =Italy!$E$2 -> 0
A80: 1. Europe | B80: =Italy!$F$4 -> BU Italy | C80: =Italy!$F$17 -> Italy | D80: =Italy!$F$15 -> Villanova Castenaso (BO) | E80: =Italy!$F$16 -> 40055 | F80: =Italy!$F$14 -> Largo Pederzana, 16 | G80: =Italy!$F$18 -> Rental | H80: =Italy!$F$11 -> IT03 | I80: =Italy!$F$19 -> No | J80: =Italy!$F$13 -> 3rd floor | K80: =Italy!$F$24 -> 120 | L80: =Italy!$F$26 -> EUR | M80: =Italy!$F$28 -> 186 | N80: =Italy!$F$29 -> NA | O80: =Italy!$F$27 -> 22380 €/ year | P80: =Italy!$F$30 -> 13500 | Q80: =Italy!$F$46 -> 15 | R80: =Italy!$F$50 -> 12 | S80: =R80/Q80 -> 0.8 | T80: =K80/R80 -> 10 | U80: =K80/Q80 -> 8 | V80: =Italy!$F$33 -> 44563 | W80: =Italy!$F$40 -> 49003 | X80: =Italy!$F$34 -> 46811 | Y80: =Italy!$F$42 -> No | Z80: =Italy!$F$43 -> N/A | AA80: =Italy!$F$44 -> No | AB80: =Italy!$F$9 -> 0 | AC80: =Italy!$F$2 -> 0
A81: 1. Europe | B81: =Italy!$D$4 -> BU Italy | C81: =Italy!$D$17 -> Italy | D81: =Italy!$D$15 -> Milano (MI) | E81: =Italy!$D$16 -> 20139 | F81: =Italy!$D$14 -> Via Oglio, 12 | G81: =Italy!$D$18 -> Rental | H81: =Italy!$D$11 -> IT01 | I81: =Italy!$D$19 -> Yes | J81: =Italy!$D$13 -> 2nd & 3rd floor | K81: =Italy!$D$24 -> 2314 | L81: =Italy!$D$26 -> EUR | M81: =Italy!$D$28 -> 291.70268 | N81: =Italy!$D$29 -> 100% of the percentage change (only if positive) in the consumer price index as determined by ISTAT in the previous year. It applies each year. | O81: =Italy!$D$27 -> 675000 € /year | P81: =Italy!$D$30 -> 335000 | Q81: =Italy!$D$46 -> 407 | R81: =Italy!$D$50 -> 203 | S81: =R81/Q81 -> 0.4987715 | T81: =K81/R81 -> 11.399015 | U81: =K81/Q81 -> 5.6855037 | V81: =Italy!$D$33 -> 45838 | W81: =Italy!$D$40 -> 50585 | X81: =Italy!$D$34 -> 48394 | Y81: =Italy!$D$42 -> No | Z81: =Italy!$D$43 -> Yes | AA81: =Italy!$D$44 -> Yes (Breeam) | AB81: =Italy!$D$9 -> 0 | AC81: =Italy!$D$2 -> 23/09/2025
A82: 2. Asia | B82: =Japan!$D$4 -> Japan | C82: =Japan!$D$17 -> Japan | D82: =Japan!$D$15 -> Shinagawa-ku, Tokyo | E82: =Japan!$D$16 -> 1400002 | F82: =Japan!$D$14 -> 4-12-8, Higashishinagawa | G82: =Japan!$D$18 -> Rental | H82: =Japan!$D$11 -> JP01 | I82: =Japan!$D$19 -> No | J82: =Japan!$D$13 -> 2nd Floor | K82: =Japan!$D$24 -> 1247.42 | L82: =Japan!$D$26 -> JPY | M82: =Japan!$D$28 -> 36299.562 | N82: =Japan!$D$29 -> 0 | O82: =Japan!$D$27 -> 45280800 | P82: =Japan!$D$30 -> 42199.63 | Q82: =Japan!$D$46 -> 202 | R82: =Japan!$D$50 -> 235 | S82: =R82/Q82 -> 1.1633663 | T82: =K82/R82 -> 5.3081702 | U82: =K82/Q82 -> 6.1753465 | V82: =Japan!$D$33 -> 45200 | W82: =Japan!$D$40 -> 46660 | X82: =Japan!$D$34 -> 45930 | Y82: =Japan!$D$42 -> No | Z82: =Japan!$D$43 -> No | AA82: =Japan!$D$44 -> No | AB82: =Japan!$D$9 -> 0 | AC82: =Japan!$D$2 -> 46056
A83: 2. Asia | B83: =Japan!$E$4 -> Japan | C83: =Japan!$E$17 -> Japan | D83: =Japan!$E$15 -> Kokurakita-ku, Kitakyushu | E83: =Japan!$E$16 -> 8020005 | F83: =Japan!$E$14 -> 2-3-20, Sakaimach | G83: =Japan!$E$18 -> Rental | H83: =Japan!$E$11 -> JP02 | I83: =Japan!$E$19 -> No | J83: =Japan!$E$13 -> 5th Floor | K83: =Japan!$E$24 -> 352.94 | L83: =Japan!$E$26 -> JPY | M83: =Japan!$E$28 -> 34486.655 | N83: =Japan!$E$29 -> 0 | O83: =Japan!$E$27 -> 12171720 | P83: =Japan!$E$30 -> 9306.8652 | Q83: =Japan!$E$46 -> 102 | R83: =Japan!$E$50 -> 91 | S83: =R83/Q83 -> 0.89215686 | T83: =K83/R83 -> 3.8784615 | U83: =K83/Q83 -> 3.4601961 | V83: =Japan!$E$33 -> 44621 | W83: =Japan!$E$40 -> 46081 | X83: =Japan!$E$34 -> 46081 | Y83: =Japan!$E$42 -> No | Z83: =Japan!$E$43 -> No | AA83: =Japan!$E$44 -> No | AB83: =Japan!$E$9 -> 0 | AC83: =Japan!$D$2 -> 46056
A84: 4. H&L | B84: =Bahrain!$D$4 -> Nextcare | C84: =Bahrain!$D$17 -> Kingdom of Bahrain | D84: =Bahrain!$D$15 -> Manama | E84: =Bahrain!$D$16 -> N/A | F84: =Bahrain!$D$14 -> Exhibition Tower, Building No. 614, Road No. 1011, Block No. 410, Sanabis | G84: =Bahrain!$D$18 -> Rental | H84: =Bahrain!$D$11 -> BH01 | I84: =Bahrain!$D$19 -> No | J84: =Bahrain!$D$13 -> 12th floor - office 1501 + 1502 | K84: =Bahrain!$D$24 -> 275 | L84: =Bahrain!$D$26 -> BHD | M84: =Bahrain!$D$28 -> 37.090909 | N84: =Bahrain!$D$29 -> 6% every two years | O84: =Bahrain!$D$27 -> 10200 | P84: =Bahrain!$D$30 -> 3.1540727 | Q84: =Bahrain!$D$46 -> 23 | R84: =Bahrain!$D$50 -> 21 | S84: =R84/Q84 -> 0.91304348 | T84: =K84/R84 -> 13.095238 | U84: =K84/Q84 -> 11.956522 | V84: =Bahrain!$D$33 -> 44713 | W84: =Bahrain!$D$40 -> 46538 | X84: =Bahrain!$D$34 -> anytime | Y84: =Bahrain!$D$42 -> No | Z84: =Bahrain!$D$43 -> N/A | AA84: =Bahrain!$D$44 -> No | AB84: =Bahrain!$D$9 -> Angelyn Valeza | AC84: =Bahrain!$D$2 -> 26/01/2026
A85: 4. H&L | B85: =Bahrain!$D$4 -> Nextcare | C85: =Bahrain!$E$17 -> Kingdom of Bahrain | D85: =Bahrain!$E$15 -> Manama | E85: =Bahrain!$E$16 -> N/A | F85: =Bahrain!$E$14 -> Exhibition Tower, Building No. 614, Road No. 1011, Block No. 410, Sanabis | G85: =Bahrain!$E$18 -> Rental | H85: =Bahrain!$E$11 -> BH01 | I85: =Bahrain!$E$19 -> No | J85: =Bahrain!$E$13 -> 12th floor - office 1503 + 1504 | K85: =Bahrain!$E$24 -> 275 | L85: =Bahrain!$E$26 -> BHD | M85: =Bahrain!$E$28 -> 37.090909 | N85: =Bahrain!$E$29 -> 6% every two years | O85: =Bahrain!$E$27 -> 10200 | P85: =Bahrain!$E$30 -> 0 | Q85: =Bahrain!$E$46 -> 0 | R85: =Bahrain!$E$50 -> 0 | S85: =R85/Q85 -> #DIV/0! | T85: =K85/R85 -> #DIV/0! | U85: =K85/Q85 -> #DIV/0! | V85: =Bahrain!E37 -> 1 month notice can be given to vacate but after 1 year | W85: =Bahrain!E44 -> No | X85: =Bahrain!E38 -> Yes | Y85: Subleaser
A86: 4. H&L | B86: =SaudiArabia!$D$4 -> Nextcare | C86: =SaudiArabia!$D$17 -> Kingdom of Saudi Arabia | D86: =SaudiArabia!$D$15 -> Al Khobar | E86: =SaudiArabia!$D$16 -> N/A | F86: =SaudiArabia!$D$14 -> Al Khobar Al Janubiyah, 1st Floor Al Rabiah & Nassar Building | G86: =SaudiArabia!$D$18 -> Rental | H86: =SaudiArabia!$D$11 -> SA01 | I86: =SaudiArabia!$D$19 -> No | J86: =SaudiArabia!$D$13 -> 2 floors (M01-M02 : full floor \ office: 1st floor) | K86: =SaudiArabia!$D$24 -> 1003 | L86: =SaudiArabia!$D$26 -> SAR | M86: =SaudiArabia!$D$28 -> 750 | N86: =SaudiArabia!$D$29 -> N/A | O86: =SaudiArabia!$D$27 -> 752250 | P86: =SaudiArabia!$D$30 -> 122.3529 | Q86: =SaudiArabia!$D$46 -> 101 | R86: =SaudiArabia!$D$50 -> 0 | S86: =R86/Q86 -> 0 | T86: =K86/R86 -> #DIV/0! | U86: =K86/Q86 -> 9.9306931 | V86: =SaudiArabia!$D$33 -> unknown | W86: =SaudiArabia!$D$40 -> 46022 | X86: =SaudiArabia!$D$34 -> 46022 | Y86: =SaudiArabia!$D$42 -> No | Z86: =SaudiArabia!$D$43 -> N/A | AA86: =SaudiArabia!$D$44 -> No | AB86: =SaudiArabia!$D$9 -> Murtadha Abdulmuhsin | AC86: =SaudiArabia!$D$2 -> 46077
A87: 4. H&L | B87: =SaudiArabia!$E$4 -> Nextcare | C87: =SaudiArabia!$E$17 -> Kingdom of Saudi Arabia | D87: =SaudiArabia!$E$15 -> Riyadh | E87: =SaudiArabia!$E$16 -> N/A | F87: =SaudiArabia!$E$14 -> Al Immam Saud Ibn Abdul Aziz Rd.Riyadh office, Riyadh - Al Nakhil - Building no. 5288 B- Building | G87: =SaudiArabia!$E$18 -> Rental | H87: =SaudiArabia!$E$11 -> SA02 | I87: =SaudiArabia!$E$19 -> No | J87: =SaudiArabia!$E$13 -> Single office 1st floor Office B/9 | K87: =SaudiArabia!$E$24 -> 115 | L87: =SaudiArabia!$E$26 -> SAR | M87: =SaudiArabia!$E$28 -> 1300 | N87: =SaudiArabia!$E$29 -> N/A | O87: =SaudiArabia!$E$27 -> 149500 | P87: =SaudiArabia!$E$30 -> 44.082 | Q87: =SaudiArabia!$E$46 -> 3 | R87: =SaudiArabia!$E$50 -> 7 | S87: =R87/Q87 -> 2.3333333 | T87: =K87/R87 -> 16.428571 | U87: =K87/Q87 -> 38.333333 | V87: =SaudiArabia!$E$33 -> unknown | W87: =SaudiArabia!$E$40 -> 46180 | X87: =SaudiArabia!$E$34 -> 45998 | Y87: =SaudiArabia!$E$42 -> No | Z87: =SaudiArabia!$E$43 -> N/A | AA87: =SaudiArabia!$E$44 -> No | AB87: =SaudiArabia!$E$9 -> Murtadha Abdulmuhsin | AC87: =SaudiArabia!$E$2 -> 0
A88: 4. H&L | B88: =Lebanon!$D$4 -> Nextcare | C88: =Lebanon!$D$17 -> Lebanon | D88: =Lebanon!$D$15 -> Beirut | E88: =Lebanon!$D$16 -> NA | F88: =Lebanon!$D$14 -> Nextcare Bldg.,Father Naamtallah Kahale Street, Saloumi, Sin El Fil | G88: =Lebanon!$D$18 -> Rental | H88: =Lebanon!$D$11 -> LE01 | I88: =Lebanon!$D$19 -> No | J88: =Lebanon!$D$13 -> Whole Building (GF+5 Floors+Storage) | K88: =Lebanon!$D$24 -> 1750 | L88: =Lebanon!$D$26 -> USD | M88: =Lebanon!$D$28 -> 77.142857 | N88: =Lebanon!$D$29 -> 18.5% every 3 years | O88: =Lebanon!$D$27 -> 135000 | P88: =Lebanon!$D$30 -> 88.571429 | Q88: =Lebanon!$D$46 -> 174 | R88: =Lebanon!$D$50 -> 163 | S88: =R88/Q88 -> 0.93678161 | T88: =K88/R88 -> 10.736196 | U88: =K88/Q88 -> 10.057471 | V88: =Lebanon!$D$33 -> 46037 | W88: =Lebanon!$D$40 -> 48228 | X88: =Lebanon!$D$34 -> 47133 | Y88: =Lebanon!$D$42 -> No | Z88: =Lebanon!$D$43 -> No | AA88: =Lebanon!$D$44 -> No | AB88: =Lebanon!$D$9 -> Youmna Aoun | AC88: =Lebanon!$D$2 -> 46049
A89: 4. H&L | B89: =Lebanon!$E$4 -> Nextcare | C89: =Lebanon!$E$17 -> Lebanon | D89: =Lebanon!$E$15 -> Beirut | E89: =Lebanon!$E$16 -> NA | F89: =Lebanon!$E$14 -> Mkaless office, Mkaless 691 Bldg, GF | G89: =Lebanon!$E$18 -> Rental | H89: =Lebanon!$E$11 -> LE02 | I89: =Lebanon!$E$19 -> No | J89: =Lebanon!$E$13 -> GF | K89: =Lebanon!$E$24 -> 500 | L89: =Lebanon!$E$26 -> USD | M89: =Lebanon!$E$28 -> 74.8 | N89: =Lebanon!$E$29 -> 10% every 3 years | O89: =Lebanon!$E$27 -> 37400 | P89: =Lebanon!$E$30 -> 180 | Q89: =Lebanon!$E$46 -> 59 | R89: =Lebanon!$E$50 -> 119 | S89: =R89/Q89 -> 2.0169492 | T89: =K89/R89 -> 4.2016807 | U89: =K89/Q89 -> 8.4745763 | V89: =Lebanon!$E$33 -> 44927 | W89: =Lebanon!$E$40 -> 48213 | X89: =Lebanon!$E$34 -> NA | Y89: =Lebanon!$E$42 -> No | Z89: =Lebanon!$E$43 -> No | AA89: =Lebanon!$E$44 -> No | AB89: =Lebanon!$E$9 -> Youmna Aoun | AC89: =Lebanon!$E$2 -> 0
A90: 4. H&L | B90: =Lebanon!$F$4 -> Nextcare | C90: =Lebanon!$F$17 -> Lebanon | D90: =Lebanon!$F$15 -> Beirut | E90: =Lebanon!$F$16 -> NA | F90: =Lebanon!$F$14 -> Nextcare Bldg.,Father Naamtallah Kahale Street, Saloumi, Sin El Fil | G90: =Lebanon!$F$18 -> Rental | H90: =Lebanon!$F$11 -> LE01 | I90: =Lebanon!$F$19 -> No | J90: =Lebanon!$F$13 -> Plot for Parking | K90: =Lebanon!$F$24 -> 960 | L90: =Lebanon!$F$26 -> USD | M90: =Lebanon!$F$28 -> 34.375 | N90: =Lebanon!$F$29 -> 10% every 3 years | O90: =Lebanon!$F$27 -> 33000 | P90: =Lebanon!$F$30 -> NA | Q90: =Lebanon!$F$46 -> 0 | R90: =Lebanon!$F$50 -> 0 | S90: =R90/Q90 -> #DIV/0! | T90: =K90/R90 -> #DIV/0! | U90: =K90/Q90 -> #DIV/0! | V90: =Lebanon!$F$33 -> 44448 | W90: =Lebanon!$F$40 -> 48213 | X90: =Lebanon!$F$34 -> 47119 | Y90: =Lebanon!$F$42 -> No | Z90: =Lebanon!$F$43 -> NA | AA90: =Lebanon!$F$44 -> NA | AB90: =Lebanon!$F$9 -> Youmna Aoun | AC90: =Lebanon!$F$2 -> 0
A91: 4. H&L | B91: =Lebanon!$G$4 -> Nextcare | C91: =Lebanon!$G$17 -> Lebanon | D91: =Lebanon!$G$15 -> Beirut | E91: =Lebanon!$G$16 -> NA | F91: =Lebanon!$G$14 -> Nextcare Bldg.,Father Naamtallah Kahale Street, Saloumi, Sin El Fil | G91: =Lebanon!$G$18 -> Rental | H91: =Lebanon!$G$11 -> LE01 | I91: =Lebanon!$G$19 -> No | J91: =Lebanon!$G$13 -> Plot for Parking | K91: =Lebanon!$G$24 -> 1000 | L91: =Lebanon!$G$26 -> USD | M91: =Lebanon!$G$28 -> 0 | N91: =Lebanon!$G$29 -> 0 | O91: =Lebanon!$G$27 -> 0 | P91: =Lebanon!$G$30 -> 0 | Q91: =Lebanon!$G$46 -> 0 | R91: =Lebanon!$G$50 -> 0 | S91: =R91/Q91 -> #DIV/0! | T91: =K91/R91 -> #DIV/0! | U91: =K91/Q91 -> #DIV/0! | V91: =Lebanon!$G$33 -> 44345 | W91: =Lebanon!$G$40 -> 48579 | X91: =Lebanon!$G$34 -> 46022 | Y91: =Lebanon!$G$42 -> No | Z91: =Lebanon!$G$43 -> NA | AA91: =Lebanon!$G$44 -> NA | AB91: =Lebanon!$G$9 -> Youmna Aoun | AC91: =Lebanon!$G$2 -> 0
A92: 4. H&L | B92: =Libya!$D$4 -> Libya | C92: =Libya!$D$17 -> Lybia | D92: =Libya!$D$15 -> Tripoli | E92: =Libya!$D$16 -> 3722 | F92: =Libya!$D$14 -> 0011 Madlien Office, Al Nofflieen, Taqsim Ben Zaglam | G92: =Libya!$D$18 -> Sublease | H92: =Libya!$D$11 -> LY01 | I92: =Libya!$D$19 -> no | J92: =Libya!$D$13 -> First Floor | K92: =Libya!$D$24 -> 380 | L92: =Libya!$D$26 -> EUR | M92: =Libya!$D$28 -> 1196.9 | N92: =Libya!$D$29 -> 0 | O92: =Libya!$D$27 -> 72000 | P92: =Libya!$D$30 -> 230Euro /m | Q92: =Libya!$D$46 -> 7 | R92: =Libya!$D$50 -> 9 | S92: =R92/Q92 -> 1.2857143 | T92: =K92/R92 -> 42.222222 | U92: =K92/Q92 -> 54.285714 | V92: =Libya!$D$33 -> 44894 | W92: =Libya!$D$40 -> 47768 | X92: =Libya!$D$34 -> 0 | Y92: =Libya!$D$42 -> N/A | Z92: =Libya!$D$43 -> No | AA92: =Libya!$D$44 -> NO | AB92: =Libya!$D$9 -> 0 | AC92: =Libya!$D$2 -> 45980
A93: 2. Asia | B93: =Malaysia!$E$4 -> BU Malaysia | C93: =Malaysia!$E$17 -> Malaysia | D93: =Malaysia!$E$15 -> Kuala Lumpur | E93: =Malaysia!$E$16 -> 50450 | F93: =Malaysia!$E$14 -> UOA Centre · No. 19 Jalan Pinang, 50450 Kuala Lumpur · Malaysia (2nd contract) | G93: =Malaysia!$E$18 -> Rental | H93: =Malaysia!$E$11 -> MY01 | I93: =Malaysia!$E$19 -> No | J93: =Malaysia!$E$13 -> 17th floor Office suite 19-17-1 & 3 & 5 | K93: =Malaysia!$E$24 -> 635.54942 | L93: =Malaysia!$E$26 -> MYR | M93: =Malaysia!$E$28 -> 542.50132 | N93: =Malaysia!$E$29 -> no rent increase | O93: =Malaysia!$E$27 -> 0 | P93: =Malaysia!$E$30 -> 161348.86 | Q93: =Malaysia!$E$46 -> 85 | R93: =Malaysia!$E$51 -> 114 | S93: =R93/Q93 -> 1.3411765 | T93: =K93/R93 -> 5.5749949 | U93: =K93/Q93 -> 7.477052 | V93: =Malaysia!$E$33 -> 44562 | W93: =Malaysia!$E$40 -> 46752 | X93: =Malaysia!$E$34 -> 46752 | Y93: =Malaysia!$E$42 -> No | Z93: =Malaysia!$E$43 -> No | AA93: =Malaysia!$E$44 -> No | AB93: =Malaysia!$E$9 -> 0 | AC93: =Malaysia!$E$2 -> 0
A94: 2. Asia | B94: =Malaysia!$D$4 -> BU Malaysia | C94: =Malaysia!$D$17 -> Malaysia | D94: =Malaysia!$D$15 -> Kuala Lumpur | E94: =Malaysia!$D$16 -> 50450 | F94: =Malaysia!$D$14 -> UOA Centre · No. 19 Jalan Pinang, 50450 Kuala Lumpur · Malaysia | G94: =Malaysia!$D$18 -> Rental | H94: =Malaysia!$D$11 -> MY01 | I94: =Malaysia!$D$19 -> No | J94: =Malaysia!$D$13 -> 13th floor Office suite 19-13-2 | K94: =Malaysia!$D$24 -> 306.5799 | L94: =Malaysia!$D$26 -> MYR | M94: =Malaysia!$D$28 -> 542.50132 | N94: =Malaysia!$D$29 -> no rent increase | O94: =Malaysia!$D$27 -> 0 | P94: =Malaysia!$D$30 -> 78081.26 | Q94: =Malaysia!$D$46 -> 43 | R94: =Malaysia!$D$51 -> 43 | S94: =R94/Q94 -> 1 | T94: =K94/R94 -> 7.1297651 | U94: =K94/Q94 -> 7.1297651 | V94: =Malaysia!$D$33 -> 44531 | W94: =Malaysia!$D$40 -> 46752 | X94: =Malaysia!$D$34 -> 46752 | Y94: =Malaysia!$D$42 -> No | Z94: =Malaysia!$D$43 -> No | AA94: =Malaysia!$D$44 -> No | AB94: =Malaysia!$D$9 -> 0 | AC94: =Malaysia!$D$2 -> 0
A95: 3. Americas | B95: =Mexico!$F$4 -> BU Mexico | C95: =Mexico!$F$17 -> Mexico | D95: =Mexico!$F$15 -> Leon | E95: =Mexico!$F$16 -> 37510 | F95: =Mexico!$F$14 -> Nodus Busines Center, Plaza Stadium, Boulevard Adolfo Lopez Mateos, # 1702, Col. Parque Manzanares, CP 37510 floor 4, León Guanajuato | G95: =Mexico!$F$18 -> Rental | H95: =Mexico!$F$11 -> MX03 | I95: =Mexico!$F$19 -> No | J95: =Mexico!$F$13 -> 4th floor | K95: =Mexico!$F$24 -> 10 | L95: =Mexico!$F$26 -> MXN | M95: =Mexico!$F$28 -> 2397.6 | N95: =Mexico!$F$29 -> INPC | O95: =Mexico!$F$27 -> 0 | P95: =Mexico!$F$30 -> None | Q95: =Mexico!$F$46 -> 48 | R95: =Mexico!$F$50 -> 0 | S95: =R95/Q95 -> 0 | T95: =K95/R95 -> #DIV/0! | U95: =K95/Q95 -> 0.20833333 | V95: =Mexico!$F$33 -> 44927 | W95: =Mexico!$F$40 -> 46387 | X95: =Mexico!$F$34 -> 45291 | Y95: =Mexico!$F$42 -> No | Z95: =Mexico!$F$43 -> No | AA95: =Mexico!$F$44 -> No | AB95: =Mexico!$F$9 -> 0 | AC95: =Mexico!$F$2 -> 0
A96: 3. Americas | B96: =Mexico!$E$4 -> BU Mexico | C96: =Mexico!$E$17 -> Mexico | D96: =Mexico!$E$15 -> Querétaro | E96: =Mexico!$E$16 -> 76150 | F96: =Mexico!$E$14 -> Avenida Universidad No. 370 (Business center) Col. La piedad CP. Delegación Municipal Centro Histórico. Santiago de Querétaro, Querétaro. PLAZA UBIKA | G96: =Mexico!$E$18 -> Rental | H96: =Mexico!$E$11 -> MX02 | I96: =Mexico!$E$19 -> No | J96: =Mexico!$E$13 -> 4th floor (401-404) | K96: =Mexico!$E$24 -> 857.47 | L96: =Mexico!$E$26 -> MXN | M96: =Mexico!$E$28 -> 2160 | N96: =Mexico!$E$29 -> INPC | O96: =Mexico!$E$27 -> 0 | P96: =Mexico!$E$30 -> 480 | Q96: =Mexico!$E$46 -> 249 | R96: =Mexico!$E$50 -> 120 | S96: =R96/Q96 -> 0.48192771 | T96: =K96/R96 -> 7.1455833 | U96: =K96/Q96 -> 3.4436546 | V96: =Mexico!$E$33 -> 44636 | W96: =Mexico!$E$40 -> 46461 | X96: =Mexico!$E$34 -> 45731 | Y96: =Mexico!$E$42 -> No | Z96: =Mexico!$E$43 -> No | AA96: =Mexico!$E$44 -> No | AB96: =Mexico!$E$9 -> 0 | AC96: =Mexico!$E$2 -> 0
A97: 3. Americas | B97: =Mexico!$D$4 -> BU Mexico | C97: =Mexico!$D$17 -> Mexico | D97: =Mexico!$D$15 -> Ciudad de Mexico | E97: =Mexico!$D$16 -> 3940 | F97: =Mexico!$D$14 -> Av. Insurgentes Sur 1602, Crédito Constructor, Benito Juárez, 03940 Ciudad de México, CDMX, México CITIBUILDING | G97: =Mexico!$D$18 -> Rental | H97: =Mexico!$D$11 -> MX01 | I97: =Mexico!$D$19 -> No | J97: =Mexico!$D$13 -> 8th Floor | K97: =Mexico!$D$24 -> 1884.66 | L97: =Mexico!$D$26 -> MXN | M97: =Mexico!$D$28 -> 5066.77 | N97: =Mexico!$D$29 -> INPC | O97: =Mexico!$D$27 -> 9549138.7 | P97: =Mexico!$D$30 -> 354 | Q97: =Mexico!$D$46 -> 957 | R97: =Mexico!$D$50 -> 417 | S97: =R97/Q97 -> 0.43573668 | T97: =K97/R97 -> 4.5195683 | U97: =K97/Q97 -> 1.9693417 | V97: =Mexico!$D$33 -> 44440 | W97: =Mexico!$D$40 -> 47603 | X97: =Mexico!$D$34 -> 45596 | Y97: =Mexico!$D$42 -> No | Z97: =Mexico!$D$43 -> No | AA97: =Mexico!$D$44 -> No | AB97: =Mexico!$D$9 -> 0 | AC97: =Mexico!$D$2 -> 31/09/2025
A98: 1. Europe | B98: =Netherlands!$D$4 -> Netherlands | C98: =Netherlands!$D$17 -> Netherlands | D98: =Netherlands!$D$15 -> Amsterdam | E98: =Netherlands!$D$16 -> 1059 VM | F98: =Netherlands!$D$14 -> Poeldijkstraat 4 | G98: =Netherlands!$D$18 -> Rental | H98: =Netherlands!$D$11 -> NL01 | I98: =Netherlands!$D$19 -> No | J98: =Netherlands!$D$13 -> floors 1A, 3A, 4A | K98: =Netherlands!$D$24 -> 1821 | L98: =Netherlands!$D$26 -> EUR | M98: =Netherlands!$D$28 -> 189 | N98: =Netherlands!$D$29 -> 0.025 | O98: =Netherlands!$D$27 -> 0 | P98: =Netherlands!$D$30 -> 49.42 | Q98: =Netherlands!$D$46 -> 221 | R98: =Netherlands!$D$50 -> 203 | S98: =R98/Q98 -> 0.91855204 | T98: =K98/R98 -> 8.9704433 | U98: =K98/Q98 -> 8.239819 | V98: =Netherlands!$D$33 -> 45047 | W98: =Netherlands!$D$40 -> 46873 | X98: =Netherlands!$D$34 -> 46873 | Y98: =Netherlands!$D$42 -> No | Z98: =Netherlands!$D$43 -> tbd | AA98: =Netherlands!$D$44 -> No | AB98: =Netherlands!$D$9 -> 0 | AC98: =Netherlands!$D$2 -> 45987
A99: 2. Asia | B99: =NewZealand!$D$4 -> New Zealand | C99: =NewZealand!$D$17 -> New Zealand | D99: =NewZealand!$D$15 -> Auckland | E99: =NewZealand!$D$16 -> 0622 | F99: =NewZealand!$D$14 -> 1 Byron Avenue, Takapuna | G99: =NewZealand!$D$18 -> Rental | H99: =NewZealand!$D$11 -> NZ01 | I99: =NewZealand!$D$19 -> No | J99: =NewZealand!$D$13 -> 2nd and 3rd floors | K99: =NewZealand!$D$24 -> 990 | L99: =NewZealand!$D$26 -> NZD | M99: =NewZealand!$D$28 -> 352.96 | N99: =NewZealand!$D$29 -> Market indexed | O99: =NewZealand!$D$27 -> 349430.4 | P99: =NewZealand!$D$30 -> 280.96364 | Q99: =NewZealand!$D$46 -> 88 | R99: =NewZealand!$D$50 -> 98 | S99: =R99/Q99 -> 1.1136364 | T99: =K99/R99 -> 10.102041 | U99: =K99/Q99 -> 11.25 | V99: =NewZealand!$D$33 -> 42583 | W99: =NewZealand!$D$40 -> 47695 | X99: =NewZealand!$D$34 -> 45870 | Y99: =NewZealand!$D$42 -> Yes | Z99: =NewZealand!$D$43 -> Yes | AA99: =NewZealand!$D$44 -> No | AB99: =NewZealand!$D$9 -> 0 | AC99: =NewZealand!$D$2 -> 46030
A100: 4. H&L | B100: =Philippines!$D$4 -> International Health | C100: =Philippines!$D$17 -> Philippines | D100: =Philippines!$D$15 -> Makati City (Manila) | E100: =Philippines!$D$16 -> 6754 | F100: =Philippines!$D$14 -> 9th floor, Allied Bank Center, 6754 Ayala Avenue Corner Legaspi Street, Makati City, Philippines | G100: =Philippines!$D$18 -> Rental | H100: =Philippines!$D$11 -> PH01 | I100: =Philippines!$D$19 -> Yes | J100: =Philippines!$D$13 -> Whole 9th floor | K100: =Philippines!$D$24 -> 2572.04 | L100: =Philippines!$D$26 -> PHP | M100: =Philippines!$D$28 -> 957.21 | N100: =Philippines!$D$29 -> 5 every year | O100: =Philippines!$D$27 -> 2461982.4 | P100: =Philippines!$D$30 -> PHP 220 per square meter per month for the common area and maintenance charges | Q100: =Philippines!$D$46 -> 261 | R100: =Philippines!$D$50 -> 206 | S100: =R100/Q100 -> 0.78927203 | T100: =K100/R100 -> 12.485631 | U100: =K100/Q100 -> 9.8545594 | V100: =Philippines!$D$33 -> 46035 | W100: =Philippines!$D$40 -> 4/12/2026 (As per meeting 1/27/2026, PNB life will extend he contract up until this date. Initilayy, beyond 4/13/2026 , the contract will be named to AZ Partners PH | X100: =Philippines!$D$34 -> anytime | Y100: =Philippines!$D$42 -> No | Z100: =Philippines!$D$43 -> No | AA100: =Philippines!$D$44 -> No | AB100: =Philippines!$D$9 -> Ramil G. Eugenio | AC100: =Philippines!$D$2 -> 46050
A101: 1. Europe | B101: =Poland!$E$4 -> BU Poland | C101: =Poland!$E$17 -> Poland | D101: =Poland!$E$15 -> Toruń | E101: =Poland!$E$16 -> 87-100 | F101: =Poland!$E$14 -> ulica Tadeusza Kościuszki 71 | G101: =Poland!$E$18 -> Rental | H101: =Poland!$E$11 -> PL02 | I101: =Poland!$E$19 -> No | J101: =Poland!$E$13 -> 4th floor | K101: =Poland!$E$24 -> 795,32 | L101: =Poland!$E$26 -> PLN | M101: =Poland!$E$28 -> 53,50 | N101: =Poland!$E$29 -> New building | O101: =Poland!$E$27 -> 0 | P101: =Poland!$E$30 -> 0 | Q101: =Poland!$E$46 -> 0 | R101: =Poland!$E$50 -> 0 | S101: =R101/Q101 -> #DIV/0! | T101: =K101/R101 -> #DIV/0! | U101: =K101/Q101 -> #DIV/0! | V101: =Poland!$E$33 -> 45566 | W101: =Poland!$E$40 -> 47483 | X101: =Poland!$E$34 -> 31/12/2029 | Y101: =Poland!$E$42 -> 0 | Z101: =Poland!$E$43 -> no | AA101: =Poland!$E$44 -> no | AB101: =Poland!$E$9 -> 0 | AC101: =Poland!$D$2 -> 45932
...

Sheet Details-->>>

Sheet Australia
C2: Update date
C4: Country/BU | D4: BU Australia
C5: CRE & FM Function | D5: sbishop@allianz-assistance.com.au
C6: Does your BU have multiple locations? (Please choose "Yes" / "No") | E6: No
C7: How many locations does your BU have (Please enter the number of office locations in your BU) | E7: 1
C9: Contact person | D9: sbishop@allianz-assistance.com.au
C10: Location | D10: Location 1 -310 Ann St | E10: Location 1 - 310 Ann St, Sublet 3 floors | F10: Location 3 - xxx | G10: Location 4 - xxx | H10: Location 5 - xxx | I10: Location 6 - xxx | J10: Location 7 - xxx | K10: Location 8 - xxx | L10: Location 9 - xxx | M10: Location 10 - xxx | N10: Location 11 - xxx | O10: Location 12 - xxx | P10: Location 13 - xxx | Q10: Location 14 - xxx | R10: Location 15 - xxx
C11: Location unique ID | D11: AU01 | E11: AU01
D12: 44 | E12: 44
B13: Describe the space: e.g. "Whole Building" or "1st and 2nd Floors" | C13: Unit Description | D13: Levels 12-18 | E13: Levels 12-14
B14: Please provide the postal address | C14: Street Address | D14: 310 Ann St | E14: 310 Ann St
B15: Try to use the greater metro city where possible | C15: Town | D15: Brisbane | E15: Brisbane
B16: Postcode or Zip code | C16: Postcode | D16: 4000 | E16: 4000
B17: Country - NOT business unit | C17: Country | D17: Australia | E17: Australia
B18: Please choose | C18: Rental / owned? | D18: Rental | E18: Rental
B19: Is the office sublet or rented to you by an Allianz entity? | C19: Is the office located at an Allianz Premises? Yes/No | D19: No | E19: No
B20: Does the Allianz entity provide the respective services as security, cleaning, etc.? | C20: Is the office also actively managed by an Allianz entity? Yes/No | D20: No | E20: No
B21: The business name that signed the lease | C21: Tenant Name | D21: AWP Australia Pty Ltd ACN 097227177 | E21: RPM Global Holdings Limited ACN 010672321
B22: The business name that owns the property | C22: Landlord Name | D22: AM 310 Ann Street Investment Pty Ltd ACN 646 669 285 Trustee under instrument No 720672598 | E22: AWP Australia Pty Ltd ACN 097227177
B23: Please type in "sq. Ft." or "m²" | C23: Office size measured in sq. Ft. or m² | D23: m² | E23: m²
B24: Please specify the gross area of the office in sq. Ft. or m² as per lease agreement | C24: Total area gross | D24: 7993 | E24: 3441
B25: The number of parking spaces in the lease and NOT the area in sq. Ft. or m² | C25: Parking Spaces | D25: 0 | E25: 0
B26: 3 digit international currency code for the local currency e.g. EUR, GBP or USD | C26: Currency Code | D26: AUD | E26: AUD
C27: Total rental costs
B28: Total rental costs/ total sq. Ft. Or m²; in case location is owned, pls use reference prices | C28: Price per /m² Rent (in local currency) | D28: 805.4 | E28: $565/ sqm Less incentive of $88.25 / sqm Net rent $476.75
B29: Please specify, by how much the rent increases over which period of time (e.g.7% per year starting 2025) | C29: Indexation of the rent in percent per year | D29: 3.75% per annum on anniversary date | E29: 3.75% per annum on anniversary date
B30: Please do not include the rental cost | C30: Service fee and facility costs (According to Account 783*)1 - price per m² | D30: =619568+111677 -> 731245 | E30: Base building charges recovered from sub tenant of $98,000 per yr plus a proportion of some of the direct vendor costs that relate to the maintenance of the tenancy
C31: Total fee and facility costs
B32: Please specify, by how many % the costs increases over which period of time (e.g.7% per year starting 2025) | C32: Indexation of service fee and/or facility cost in percent per year | D32: 3.75% per yr for rent | E32: 3.75% per yr for rent
B33: What is the start date of the lease? | C33: Lease Start Date | D33: 43497 | E33: 44743
B34: The next fixed break date in the lease | C34: Next Break Date | D34: 47361 | E34: 46568
B35: The date by which notice must have been served | C35: Next Break Notice Expiry | D35: N | E35: N
B36: Can the contract be terminated before the end of the lease? | C36: Does a termination clause exist? Yes/No | D36: No | E36: No
B37: Please specify the exact conditions of the clause (date, notice period, penalty payments etc.) | C37: If yes, please specify the termination clause
B38: Does the lease automatically renew? | C38: Auto Renewing Lease? Yes/No | D38: No | E38: No
B39: How many months notice to prevent auto-renewal? | C39: Auto Renewal Notice Period (Months) | D39: N/A | E39: N/A
B40: The current lease expiry date (leave blank if the lease is open ended) | C40: Lease End Date | D40: 47361 | E40: 46568
B41: Please choose "Yes" / "No"; in case of yes, please specify in the comment field | C41: Does your BU have the contractual possibility to sublet your property? Yes/No | D41: Yes
B42: Please provide the details by using a separate coulmn | C42: If there is a sublet contract in place, please provide the details in a separate column | D42: Yes | E42: subleaser
B43: Please state only yes, if the whole energy consumption of the location is covered by renewable energy | C43: Is the location operated with renewable energy? Yes/No | D43: No
B44: It could be an internationally recognized certificate (LEED, BREEAM, Green Star, etc.) or a more locally recognized certificate (e.g. DGNB in Germany) | C44: Does the office building hold any sustainability certificate? Yes/No - If yes please specify | D44: Yes- NABERS 5.5 star energy rating & working on NABERS rating for waste
C46: Number of HC working in this location as of Sept 2025 | D46: 619
C47: thereof No. of HC non-OPS | D47: 229
C48: thereof No. of HC OPS | D48: 390
C50: Number of workstations2 in this location | D50: 386
C51: thereof No. of HC non-OPS | D51: 230
C52: thereof No. of HC OPS | D52: 156
C54: H24 Operations in this site? Yes/No | D54: Yes
C55: Average shifts per day for Operations people | D55: 2
C56: Maximum shifts per day for Operations people | D56: 3
C57: WFO rule for Platform operations people (number of days per week in the office)
C58: WFO rule for non Platform operations people (number of days per week in the office)
D60: 1783* - Accommodation Expenses
D61: 7831005 - Facilities IC rental expense: Premises IC rent → NOT TO BE INCLUDED
D62: 7832001 - Utilities expenses
D63: 7832002 - Maintenance expenses
D64: 7832003 - Other occupancy expenses
D65: 7833001 - Office equipment - scheduled
D66: 7833004 - Other Office Costs
D68: 2 The workstation needs to qualify as regular work place with a sufficient desktop and an appropriate office chair. Agile and collaboration areas are excluded

Sheet Austria
C2: Update date | D2: 45919
C4: Country/BU | D4: BU Austria | E4: BU Austria
C6: Does your BU have multiple locations? (Please choose "Yes" / "No") | E6: Yes
C7: How many locations does your BU have (Please enter the number of office locations in your BU) | E7: 3 (Bulgaria + Hungary)
C9: Contact Person
C10: Location | D10: Location 1 - Vienna | E10: Location 2 - Vienna - Extend | F10: Location 3 - xxx | G10: Location 4 - xxx | H10: Location 5 - xxx | I10: Location 6 - xxx | J10: Location 7 - xxx | K10: Location 8 - xxx | L10: Location 9 - xxx | M10: Location 10 - xxx | N10: Location 11 - xxx | O10: Location 12 - xxx | P10: Location 13 - xxx | Q10: Location 14 - xxx | R10: Location 15 - xxx
C11: Location unique ID | D11: AT01 | E11: AT01
B13: Describe the space: e.g. "Whole Building" or "1st and 2nd Floors" | C13: Unit Description | D13: 3rd floor | E13: 3rd floor
B14: Please provide the postal address | C14: Street Address | D14: Linzer Strasse 225 | E14: Linzer Strasse 225
B15: Try to use the greater metro city where possible | C15: Town | D15: Vienna | E15: Vienna
B16: Postcode or Zip code | C16: Postcode | D16: 1140 | E16: 1140
B17: Country - NOT business unit | C17: Country | D17: Austria | E17: Austria
B18: Please choose | C18: Rental / owned? | D18: Rental | E18: rental
B19: Is the office sublet or rented to you by an Allianz entity? | C19: Is the office located at an Allianz Premises? Yes/No | D19: Yes | E19: Yes
B20: Does the Allianz entity provide the respective services as security, cleaning, etc.? | C20: Is the office also actively managed by an Allianz entity? Yes/No | D20: Yes | E20: Yes
B21: The business name that signed the lease | C21: Tenant Name | D21: AWP Austria GmbH | E21: AWP Austria GmbH
B22: The business name that owns the property | C22: Landlord Name | D22: Allianz Technology GmbH | E22: Allianz Technology GmbH
C23: m² | D23: m² | E23: m²
B24: Please specify the gross area of the office in sq. Ft. or m² as per lease agreement | C24: Total area gross | D24: 890 | E24: 150.91
B25: The number of parking spaces in the lease and NOT the area in sq. Ft. or m² | C25: Parking Spaces | D25: 20
B26: 3 digit international currency code for the local currency e.g. EUR, GBP or USD | C26: Currency Code | D26: EUR | E26: EUR
B27: Total rental costs | C27: Total rental costs
B28: Total rental costs/ total sq. Ft. Or m²; in case location is owned, pls use reference prices | C28: Price per sq. Ft./m² Rent (in local currency) | D28: 16,80/m²
B29: Please specify, by how much the rent increases over which period of time (e.g.7% per year starting 2025) | C29: Indexation of the rent in percent per year | D29: CPI
B30: Please do not include the rental cost | C30: Service fee and facility costs (According to Account 783*)1 - price per sq. Ft. or m² | D30: =(11.85+2.6)*12 -> 173.4 | E30: included in the rent
C31: Total fee and facility costs
B32: Please specify, by how many % the costs increases over which period of time (e.g.7% per year starting 2025) | C32: Indexation of service fee and/or facility cost in percent per year | D32: CPI
B33: What is the start date of the lease? | C33: Lease Start Date | D33: 45261 | E33: 45962
B34: The next fixed break date in the lease | C34: Next Break Date | D34: 45444
B35: The date by which notice must have been served | C35: Next Break Notice Expiry | D35: 6 months
B36: Can the contract be terminated before the end of the lease? | C36: Does a termination clause exist? Yes/No | D36: Yes
B37: Please specify the exact conditions of the clause (date, notice period, penalty payments etc.) | C37: If yes, please specify the termination clause | D37: if terminated early, outstanding depreciation costs need to be paid
B38: Does the lease automatically renew? | C38: Auto Renewing Lease? Yes/No | D38: No
B39: How many months notice to prevent auto-renewal? | C39: Auto Renewal Notice Period (Months) | D39: N/A
B40: The current lease expiry date (leave blank if the lease is open ended) | C40: Lease End Date | D40: 47635 | E40: 46142
B41: Please choose "Yes" / "No"; in case of yes, please specify in the comment field | C41: Does your BU have the contractual possibility to sublet your property? Yes/No | D41: No
B42: Please provide the details of the sublease agreement in a separate column of the document | C42: If there is a sublease agreement in place, please provide the details in a separate column | D42: No
B43: Please state only yes, if the whole energy consumption of the location is covered by renewable energy | C43: Is the location operated with renewable energy? Yes/No | D43: Yes
B44: It could be an internationally recognized certificate (LEED, BREEAM, Green Star, etc.) or a more locally recognized certificate (e.g. DGNB in Germany) | C44: Does the office building hold any sustainability certificate? Yes/No - If yes please specify | D44: No
C46: Number of HC working in this location as of Sept 2025 | D46: 220
C47: thereof No. of HC non-OPS
C48: thereof No. of HC OPS
C50: Number of workstations2 in this location | D50: 87 | E50: 19
C51: thereof No. of HC non-OPS
C52: thereof No. of HC OPS
C54: H24 Operations in this site? Yes/No
C55: Average shifts per day for Operations people
C56: Maximum shifts per day for Operations people
C57: WFO rule for Platform operations people (number of days per week in the office)
C58: WFO rule for non Platform operations people (number of days per week in the office)
D60: 1783* - Accommodation Expenses
D61: 7831005 - Facilities IC rental expense: Premises IC rent → NOT TO BE INCLUDED
D62: 7832001 - Utilities expenses
D63: 7832002 - Maintenance expenses
D64: 7832003 - Other occupancy expenses
D65: 7833001 - Office equipment - scheduled
D66: 7833004 - Other Office Costs
D68: 2 The workstation needs to qualify as regular work place with a sufficient desktop and an appropriate office chair. Agile and collaboration areas are excluded

Sheet Bahrain
C2: Update date | D2: 26/01/2026
C4: Country/BU | D4: Nextcare | E4: Nextcare
C6: Does your BU have multiple locations? (Please choose "Yes" / "No") | E6: Yes
C7: How many locations does your BU have (Please enter the number of office locations in your BU) | E7: 23
C9: Contact Person | D9: Angelyn Valeza | E9: Angelyn Valeza
C10: Location | D10: Location 21 - Manama | E10: Location 22 - Manama | F10: Location 3 - | G10: Location 4 - | H10: Location 5 - | I10: Location 6 - | J10: Location 7 - | K10: Location 8 - | L10: Location 9 - | M10: Location 10 -
C11: Location unique ID | D11: BH01 | E11: BH01
B13: Describe the space: e.g. "Whole Building" or "1st and 2nd Floors" | C13: Unit Description | D13: 12th floor - office 1501 + 1502 | E13: 12th floor - office 1503 + 1504
B14: Please provide the postal address | C14: Street Address | D14: Exhibition Tower, Building No. 614, Road No. 1011, Block No. 410, Sanabis | E14: Exhibition Tower, Building No. 614, Road No. 1011, Block No. 410, Sanabis
B15: Try to use the greater metro city where possible | C15: Town | D15: Manama | E15: Manama
B16: Postcode or Zip code | C16: Postcode | D16: N/A | E16: N/A
B17: Country - NOT business unit | C17: Country | D17: Kingdom of Bahrain | E17: Kingdom of Bahrain
B18: Please choose | C18: Rental / owned? | D18: Rental | E18: Rental
B19: Is the office sublet or rented to you by an Allianz entity? | C19: Is the office located at an Allianz Premises? Yes/No | D19: No | E19: No
B20: Does the Allianz entity provide the respective services as security, cleaning, etc.? | C20: Is the office also actively managed by an Allianz entity? Yes/No | D20: No | E20: No
B21: The business name that signed the lease | C21: Tenant Name | D21: Nextcare Bahrain Ancillary Services B.S.C. Closed | E21: AWP MEA Holdings Co WLL
B22: The business name that owns the property | C22: Landlord Name | D22: Tylos Building Materials W.L.L. | E22: Tylos Building Materials W.L.L.
B23: Unit sq FT or m² | C23: m² | D23: m² | E23: m²
B24: Please specify the gross area of the office in sq. Ft. or m² as per lease agreement | C24: Total area gross | D24: 275 | E24: 275
B25: The number of parking spaces in the lease and NOT the area in sq. Ft. or m² | C25: Parking Spaces | D25: 3 | E25: 3
B26: 3 digit international currency code for the local currency e.g. EUR, GBP or USD | C26: Currency Code | D26: BHD | E26: BHD
B27: Total rental costs | C27: Total rental costs | D27: 10200 | E27: 10200
B28: Total rental costs/ total sq. Ft. Or m²; in case location is owned, pls use reference prices | C28: Price per sq. Ft./m² Rent (in local currency) | D28: =D27/D24 -> 37.090909 | E28: =E27/E24 -> 37.090909
B29: Please specify, by how much the rent increases over which period of time (e.g.7% per year starting 2025) | C29: Indexation of the rent in percent per year | D29: 6% every two years | E29: 6% every two years
B30: Please do not include the rental cost | C30: Service fee and facility costs (According to Account 783*)1 - price per sq. Ft. or m² | D30: =D31/D24 -> 3.1540727 | E30: =E31/E24 -> 0
C31: Total fee and facility costs | D31: 867.37 | E31: 0
B32: Please specify, by how many % the costs increases over which period of time (e.g.7% per year starting 2025) | C32: Indexation of service fee and/or facility cost in percent per year
B33: What is the start date of the lease? | C33: Lease Start Date | D33: 44713 | E33: 44713
B34: The next fixed break date in the lease | C34: Next Break Date | D34: anytime | E34: anytime
B35: The date by which notice must have been served | C35: Next Break Notice Expiry | D35: N/A | E35: N/A
B36: Can the contract be terminated before the end of the lease? | C36: Does a termination clause exist? Yes/No | D36: Yes | E36: Yes
B37: Please specify the exact conditions of the clause (date, notice period, penalty payments etc.) | C37: If yes, please specify the termination clause | D37: 1 month notice can be given to vacate but after 1 year | E37: 1 month notice can be given to vacate but after 1 year
B38: Does the lease automatically renew? | C38: Auto Renewing Lease? Yes/No | D38: Yes | E38: Yes
B39: How many months notice to prevent auto-renewal? | C39: Auto Renewal Notice Period (Months) | D39: 1 month | E39: 1 month
B40: The current lease expiry date (leave blank if the lease is open ended) | C40: Lease End Date | D40: 46538 | E40: 46538
B41: Please choose "Yes" / "No"; in case of yes, please specify in the comment field | C41: Does your BU have the contractual possibility to sublet your property? Yes/No | D41: No | E41: No
B42: Please provide the details of the sublease agreement in a separate column of the document | C42: If there is a sublease agreement (external or internal) in place, please provide the details in a separate column | D42: No | E42: No
B43: Please state only yes, if the whole energy consumption of the location is covered by renewable energy | C43: Is the location operated with renewable energy? Yes/No | D43: N/A | E43: N/A
B44: It could be an internationally recognized certificate (LEED, BREEAM, Green Star, etc.) or a more locally recognized certificate (e.g. DGNB in Germany) | C44: Does the office building hold any sustainability certificate? Yes/No - If yes please specify | D44: No | E44: No
C46: Number of HC working in this location | D46: 23 | E46: 0
C47: thereof No. of HC not working on operations platforms (call centers) | D47: 2 | E47: 0
C48: thereof No. of HC working in operations platforms (call centers) | D48: 21 | E48: 0
C50: Number of workstations2 in this location | D50: 21 | E50: 0
C51: thereof No. of HC non-platform operations | D51: 5 | E51: 0
C52: thereof No. of HC platform operations | D52: 16 | E52: 0
C54: H24 Operations in this site? Yes/No | D54: No | E54: 0
C55: Average shifts per day for Platform Operations people | D55: 3 | E55: 0
C56: Maximum shifts per day for Platform Operations people | D56: 3 | E56: 0
C57: WFO rule for Platform operations people (number of days per week in the office)
C58: WFO rule for non Platform operations people (number of days per week in the office)

Sheet Belgium
C2: Update date | D2: 46070
C4: Country/BU | D4: International Health
C6: Does your BU have multiple locations? (Please choose "Yes" / "No") | E6: No
C7: How many locations does your BU have (Please enter the number of office locations in your BU) | E7: 1
C9: Contact Person
C10: Location | D10: Location 1 - Brussels Office | E10: Location 2 - | F10: Location 3 - | G10: Location 4 - | H10: Location 5 - | I10: Location 6 - | J10: Location 7 - | K10: Location 8 - | L10: Location 9 - | M10: Location 10 -
C11: Location unique ID | D11: BE01
B13: Describe the space: e.g. "Whole Building" or "1st and 2nd Floors" | C13: Unit Description | D13: 4th floor & 50% of the 5th floor
B14: Please provide the postal address | C14: Street Address | D14: Allianz Tower Koning Boulevard du Roi Albert II, 32 (Albert II Laan)
B15: Try to use the greater metro city where possible | C15: Town | D15: Brussels
B16: Postcode or Zip code | C16: Postcode | D16: 1000
B17: Country - NOT business unit | C17: Country | D17: Belgium
B18: Please choose | C18: Rental / owned? | D18: Rental
B19: Is the office sublet or rented to you by an Allianz entity? | C19: Is the office located at an Allianz Premises? Yes/No | D19: Yes
B20: Does the Allianz entity provide the respective services as security, cleaning, etc.? | C20: Is the office also actively managed by an Allianz entity? Yes/No | D20: Yes
B21: The business name that signed the lease | C21: Tenant Name | D21: AWP P&C SA - Belgian Branch
B22: The business name that owns the property | C22: Landlord Name | D22: AZ Benelux
B23: Unit sq FT or m² | C23: m² | D23: m²
B24: Please specify the gross area of the office in sq. Ft. or m² as per lease agreement | C24: Total area gross | D24: 1658
B25: The number of parking spaces in the lease and NOT the area in sq. Ft. or m² | C25: Parking Spaces | D25: 12
B26: 3 digit international currency code for the local currency e.g. EUR, GBP or USD | C26: Currency Code | D26: EUR
B27: Total rental costs | C27: Total rental costs | D27: =D28*D24 -> 618434
B28: Total rental costs/ total sq. Ft. Or m²; in case location is owned, pls use reference prices | C28: Price per sq. Ft./m² Rent (in local currency) | D28: 373
B29: Please specify, by how much the rent increases over which period of time (e.g.7% per year starting 2025) | C29: Indexation of the rent in percent per year | D29: app. 3%
B30: Please do not include the rental cost | C30: Service fee and facility costs (According to Account 783*)1 - price per sq. Ft. or m² | D30: 259
C31: Total fee and facility costs | D31: =D30*D24 -> 429422
B32: Please specify, by how many % the costs increases over which period of time (e.g.7% per year starting 2025) | C32: Indexation of service fee and/or facility cost in percent per year | D32: app. 3%
B33: What is the start date of the lease? | C33: Lease Start Date | D33: 43922
B34: The next fixed break date in the lease | C34: Next Break Date | D34: 47208
B35: The date by which notice must have been served | C35: Next Break Notice Expiry | D35: 47208
B36: Can the contract be terminated before the end of the lease? | C36: Does a termination clause exist? Yes/No | D36: NO
B37: Please specify the exact conditions of the clause (date, notice period, penalty payments etc.) | C37: If yes, please specify the termination clause
B38: Does the lease automatically renew? | C38: Auto Renewing Lease? Yes/No | D38: No
B39: How many months notice to prevent auto-renewal? | C39: Auto Renewal Notice Period (Months) | D39: N/A
B40: The current lease expiry date (leave blank if the lease is open ended) | C40: Lease End Date | D40: 47208
B41: Please choose "Yes" / "No"; in case of yes, please specify in the comment field | C41: Does your BU have the contractual possibility to sublet your property? Yes/No | D41: NO
B42: Please provide the details of the sublease agreement in a separate column of the document | C42: If there is a sublease agreement (external or internal) in place, please provide the details in a separate column | D42: No
B43: Please state only yes, if the whole energy consumption of the location is covered by renewable energy | C43: Is the location operated with renewable energy? Yes/No | D43: Yes
B44: It could be an internationally recognized certificate (LEED, BREEAM, Green Star, etc.) or a more locally recognized certificate (e.g. DGNB in Germany) | C44: Does the office building hold any sustainability certificate? Yes/No - If yes please specify | D44: Unknown
C46: Number of HC working in this location | D46: 222
C47: thereof No. of HC not working on operations platforms (call centers) | D47: 18
C48: thereof No. of HC working in operations platforms (call centers) | D48: 204
C50: Number of workstations2 in this location | D50: 142 | E50: Incl. RSA, TCC, MGCC, OPS Finance, P&N
C51: thereof No. of HC non-platform operations | D51: 128
C52: thereof No. of HC platform operations | D52: 14 | E52: Sales, Board, etc…
C54: H24 Operations in this site? Yes/No
C55: Average shifts per day for Platform Operations people | D55: 7,5 hours
C56: Maximum shifts per day for Platform Operations people | D56: 7,5 hours
C57: WFO rule for Platform operations people (number of days per week in the office)
C58: WFO rule for non Platform operations people (number of days per week in the office)

Sheet Bulgaria
C2: Update date | D2: 45919
C4: Country/BU | D4: BU Austria
C6: Does your BU have multiple locations? (Please choose "Yes" / "No") | E6: Yes
C7: How many locations does your BU have (Please enter the number of office locations in your BU) | E7: 3
C9: Contact Person
C10: Location | D10: Location 1 - Sofia | E10: Location 2 - xxx | F10: Location 3 - xxx | G10: Location 4 - xxx | H10: Location 5 - xxx | I10: Location 6 - xxx | J10: Location 7 - xxx | K10: Location 8 - xxx | L10: Location 9 - xxx | M10: Location 10 - xxx | N10: Location 11 - xxx | O10: Location 12 - xxx | P10: Location 13 - xxx | Q10: Location 14 - xxx | R10: Location 15 - xxx
C11: Location unique ID | D11: BU01
B13: Describe the space: e.g. "Whole Building" or "1st and 2nd Floors" | C13: Unit Description | D13: part of a floor
B14: Please provide the postal address | C14: Street Address | D14: 16 Srebarna Str.
B15: Try to use the greater metro city where possible | C15: Town | D15: Sofia
B16: Postcode or Zip code | C16: Postcode | D16: 1407
B17: Country - NOT business unit | C17: Country | D17: Bulgaria
B18: Please choose | C18: Rental / owned? | D18: Rental
B19: Is the office sublet or rented to you by an Allianz entity? | C19: Is the office located at an Allianz Premises? Yes/No | D19: No
B20: Does the Allianz entity provide the respective services as security, cleaning, etc.? | C20: Is the office also actively managed by an Allianz entity? Yes/No | D20: No
B21: The business name that signed the lease | C21: Tenant Name | D21: AWP P&C S.A., branch Bulgaria
B22: The business name that owns the property | C22: Landlord Name | D22: Park Lane Srebarna
C23: m² | D23: m²
B24: Please specify the gross area of the office in sq. Ft. or m² as per lease agreement | C24: Total area gross | D24: 45.77
B25: The number of parking spaces in the lease and NOT the area in sq. Ft. or m² | C25: Parking Spaces | D25: 1
B26: 3 digit international currency code for the local currency e.g. EUR, GBP or USD | C26: Currency Code | D26: EUR
B27: Total rental costs | C27: Total rental costs
B28: Total rental costs/ total sq. Ft. Or m²; in case location is owned, pls use reference prices | C28: Price per sq. Ft./m² Rent (in local currency) | D28: 156
B29: Please specify, by how much the rent increases over which period of time (e.g.7% per year starting 2025) | C29: Indexation of the rent in percent per year | D29: CPI
B30: Please do not include the rental cost | C30: Service fee and facility costs (According to Account 783*)1 - price per sq. Ft. or m² | D30: 53.6
C31: Total fee and facility costs
B32: Please specify, by how many % the costs increases over which period of time (e.g.7% per year starting 2025) | C32: Indexation of service fee and/or facility cost in percent per year | D32: CPI
B33: What is the start date of the lease? | C33: Lease Start Date | D33: 44378
B34: The next fixed break date in the lease | C34: Next Break Date | D34: 48029
B35: The date by which notice must have been served | C35: Next Break Notice Expiry | D35: N/A
B36: Can the contract be terminated before the end of the lease? | C36: Does a termination clause exist? Yes/No | D36: No
B37: Please specify the exact conditions of the clause (date, notice period, penalty payments etc.) | C37: If yes, please specify the termination clause | D37: N/A
B38: Does the lease automatically renew? | C38: Auto Renewing Lease? Yes/No | D38: No
B39: How many months notice to prevent auto-renewal? | C39: Auto Renewal Notice Period (Months) | D39: No
B40: The current lease expiry date (leave blank if the lease is open ended) | C40: Lease End Date | D40: 48029
B41: Please choose "Yes" / "No"; in case of yes, please specify in the comment field | C41: Does your BU have the contractual possibility to sublet your property? Yes/No | D41: Yes
B42: Please provide the details of the sublease agreement in a separate column of the document | C42: If there is a sublease agreement in place, please provide the details in a separate column | D42: No
B43: Please state only yes, if the whole energy consumption of the location is covered by renewable energy | C43: Is the location operated with renewable energy? Yes/No | D43: No
B44: It could be an internationally recognized certificate (LEED, BREEAM, Green Star, etc.) or a more locally recognized certificate (e.g. DGNB in Germany) | C44: Does the office building hold any sustainability certificate? Yes/No - If yes please specify | D44: No
C46: Number of HC working in this location as of Sept 2025 | D46: 6
C47: thereof No. of HC non-OPS
C48: thereof No. of HC OPS
C50: Number of workstations2 in this location | D50: 6
C51: thereof No. of HC non-OPS
C52: thereof No. of HC OPS
C54: H24 Operations in this site? Yes/No
C55: Average shifts per day for Operations people
C56: Maximum shifts per day for Operations people
C57: WFO rule for Platform operations people (number of days per week in the office)
C58: WFO rule for non Platform operations people (number of days per week in the office)

Sheet Brazil
C2: Update date | D2: 45961
C4: Country/BU | D4: BU Brazil | E4: BU Brazil
C6: Does your BU have multiple locations? (Please choose "Yes" / "No") | E6: Yes
C7: How many locations does your BU have (Please enter the number of office locations in your BU) | E7: 2
C9: Contact Person
C10: Location | D10: Location 1 - Sao Bernardo do Campo | E10: Location 1 - Sao Bernardo do Campo | F10: Location 4 - xxx | G10: Location 5 - xxx | H10: Location 6 - xxx | I10: Location 7 - xxx | J10: Location 8 - xxx | K10: Location 9 - xxx | L10: Location 10 - xxx | M10: Location 11 - xxx | N10: Location 12 - xxx | O10: Location 13 - xxx | P10: Location 14 - xxx | Q10: Location 15 - xxx
C11: Location unique ID | D11: BR01 | E11: BR01
B13: Describe the space: e.g. "Whole Building" or "1st and 2nd Floors" | C13: Unit Description | D13: 5th, 6th, 8th and 9th floor | E13: 50% of the 6th floor
B14: Please provide the postal address | C14: Street Address | D14: Rua José Versolato, 101 | E14: Rua José Versolato, 101 (2nd contract)
B15: Try to use the greater metro city where possible | C15: Town | D15: São Bernardo do Campo | E15: São Bernardo do Campo
B16: Postcode or Zip code | C16: Postcode | D16: 09751-020 | E16: 09751-020
B17: Country - NOT business unit | C17: Country | D17: Brazil | E17: Brazil
B18: Please choose | C18: Rental / owned? | D18: Rental | E18: Rental
B19: Is the office sublet or rented to you by an Allianz entity? | C19: Is the office located at an Allianz Premises? Yes/No | D19: No | E19: No
B20: Does the Allianz entity provide the respective services as security, cleaning, etc.? | C20: Is the office also actively managed by an Allianz entity? Yes/No | D20: No | E20: No
B21: The business name that signed the lease | C21: Tenant Name | D21: Allianz Partners Brazil | E21: Allianz Partners Brazil
B22: The business name that owns the property | C22: Landlord Name | D22: Domo Corporate | E22: Domo Corporate
B23: Please type in "sq. Ft." or "m²" | C23: Office size measured in sq. Ft. or m² | D23: m² | E23: m²
B24: Please specify the gross area of the office in sq. Ft. or m² as per lease agreement | C24: Total area gross | D24: 3256 | E24: 711
B25: The number of parking spaces in the lease and NOT the area in sq. Ft. or m² | C25: Parking Spaces | D25: 100 | E25: 10
B26: 3 digit international currency code for the local currency e.g. EUR, GBP or USD | C26: Currency Code | D26: BRL | E26: BRL
C27: Total Rental Cost
B28: Total rental costs/ total sq. Ft. Or m²; in case location is owned, pls use reference prices | C28: Price per sq. Ft./m² Rent (in local currency) | D28: 577 | E28: 600
B29: Please specify, by how much the rent increases over which period of time (e.g.7% per year starting 2025) | C29: Indexation of the rent in percent per year | D29: 0.09 | E29: 0.09
B30: Please do not include the rental cost | C30: Service fee and facility costs (According to Account 783*)1 - price per sq. Ft. or m² | D30: 114 | E30: 21
C31: Total fee and facility costs
B32: Please specify, by how many % the costs increases over which period of time (e.g.7% per year starting 2025) | C32: Indexation of service fee and/or facility cost in percent per year | D32: 2023 - 7% 2024 - 7% 2025 - 7% | E32: 2023 - 0% 2024 - 7% 2025 - 7%
B33: What is the start date of the lease? | C33: Lease Start Date | D33: 42614 | E33: 44927
B34: The next fixed break date in the lease | C34: Next Break Date | D34: 42582 | E34: 46387
B35: The date by which notice must have been served | C35: Next Break Notice Expiry | D35: N/A | E35: N/A
B36: Can the contract be terminated before the end of the lease? | C36: Does a termination clause exist? Yes/No | D36: Yes | E36: Yes
B37: Please specify the exact conditions of the clause (date, notice period, penalty payments etc.) | C37: If yes, please specify the termination clause | D37: Break penalty: (1 year rent / months of contract duration) * remaining months of the contract | E37: Break penalty: (1 year rent / months of contract duration) * remaining months of the contract
B38: Does the lease automatically renew? | C38: Auto Renewing Lease? Yes/No | D38: No | E38: No
B39: How many months notice to prevent auto-renewal? | C39: Auto Renewal Notice Period (Months) | D39: N/A | E39: N/A
B40: The current lease expiry date (leave blank if the lease is open ended) | C40: Lease End Date | D40: 46234 | E40: 46387
B41: Please choose "Yes" / "No"; in case of yes, please specify in the comment field | C41: Does your BU have the contractual possibility to sublet your property? Yes/No | D41: No | E41: No
B42: Please provide the details of the sublease agreement in a separate column of the document | C42: If there is a sublease agreement in place, please provide the details in a separate column | D42: N/A | E42: N/A
B43: Please state only yes, if the whole energy consumption of the location is covered by renewable energy | C43: Is the location operated with renewable energy? Yes/No | D43: No | E43: No
B44: It could be an internationally recognized certificate (LEED, BREEAM, Green Star, etc.) or a more locally recognized certificate (e.g. DGNB in Germany) | C44: Does the office building hold any sustainability certificate? Yes/No - If yes please specify | D44: No | E44: No
C46: Number of HC working in this location as of Sept 2025 | D46: 1300 | E46: 200
C47: thereof No. of HC non-OPS
C48: thereof No. of HC OPS
C50: Number of workstations2 in this location | D50: 752 | E50: 154
C51: thereof No. of HC non-OPS
C52: thereof No. of HC OPS
C54: H24 Operations in this site? Yes/No
C55: Average shifts per day for Operations people
C56: Maximum shifts per day for Operations people
C57: WFO rule for Platform operations people (number of days per week in the office)
C58: WFO rule for non Platform operations people (number of days per week in the office) | D58: 1 | E58: 1
D60: 1783* - Accommodation Expenses
D61: 7831005 - Facilities IC rental expense: Premises IC rent → NOT TO BE INCLUDED
D62: 7832001 - Utilities expenses
D63: 7832002 - Maintenance expenses
D64: 7832003 - Other occupancy expenses
D65: 7833001 - Office equipment - scheduled
D66: 7833004 - Other Office Costs
D68: 2 The workstation needs to qualify as regular work place with a sufficient desktop and an appropriate office chair. Agile and collaboration areas are excluded

Sheet Canada
C2: Update date | D2: 45961
C4: Country/BU | D4: BU Canada
C6: Does your BU have multiple locations? (Please choose "Yes" / "No") | E6: No
C7: How many locations does your BU have (Please enter the number of office locations in your BU) | E7: 1
C9: Contact Person
C10: Location | D10: Location 1 - Cambridge | E10: Location 2 - Subleaese 1 | F10: Location 3 - Sublease 2 | G10: Location 4 - xxx | H10: Location 5 - xxx | I10: Location 6 - xxx | J10: Location 7 - xxx | K10: Location 8 - xxx | L10: Location 9 - xxx | M10: Location 10 - xxx | N10: Location 11 - xxx | O10: Location 12 - xxx | P10: Location 13 - xxx | Q10: Location 14 - xxx | R10: Location 15 - xxx
C11: Location unique ID | D11: CA01 | E11: CA01 | F11: CA01
B13: Describe the space: e.g. "Whole Building" or "1st and 2nd Floors" | C13: Unit Description | D13: Single story unattached office dwelling
B14: Please provide the postal address | C14: Street Address | D14: 700 Jamieson Pkwy. Cambridge
B15: Try to use the greater metro city where possible | C15: Town | D15: Cambridge
B16: Postcode or Zip code | C16: Postcode | D16: N3C 4N6
B17: Country - NOT business unit | C17: Country | D17: Canada
B18: Please choose | C18: Rental / owned? | D18: Rental | E18: Sublease | F18: Sublease
B19: Is the office sublet or rented to you by an Allianz entity? | C19: Is the office located at an Allianz Premises? Yes/No | D19: No
B20: Does the Allianz entity provide the respective services as security, cleaning, etc.? | C20: Is the office also actively managed by an Allianz entity? Yes/No | D20: NO
B21: The business name that signed the lease | C21: Tenant Name | D21: AZGA | E21: Superior Propane | F21: Reid's Heritage Homes
B22: The business name that owns the property | C22: Landlord Name | D22: CF Property Management | E22: AZGA | F22: AZGA
C23: m² | D23: m² | E23: m² | F23: m²
B24: Please specify the gross area of the office in sq. Ft. or m² as per lease agreement | C24: Total area gross | D24: =111242*0.092903 -> 10334.716 | E24: =36344*0.092903 -> 3376.4666 | F24: =24965*0.092903 -> 2319.3234
B25: The number of parking spaces in the lease and NOT the area in sq. Ft. or m² | C25: Parking Spaces | D25: 431 | E25: 254 | F25: 96
B26: 3 digit international currency code for the local currency e.g. EUR, GBP or USD | C26: Currency Code | D26: CAD | E26: CAD | F26: CAD
C27: Total Rental Cost
B28: Total rental costs/ total sq. Ft. Or m²; in case location is owned, pls use reference prices | C28: Price per sq. Ft./m² Rent (in local currency) | D28: 17.5 | E28: 17 | F28: 18.5
B29: Please specify, by how much the rent increases over which period of time (e.g.7% per year starting 2025) | C29: Indexation of the rent in percent per year | D29: Year 1-5 - $17.50 Year 6-10 - $19.35 Year 11-15- $21.35 | E29: Year 1-5 - $17.00 Year 6-10 - $18.00 Year 11-14 - $19.00 | F29: Year 1-4 - $18.50 Year 5-8- $19.50 Year 9-11 - $20.50
B30: Please do not include the rental cost | C30: Service fee and facility costs (According to Account 783*)1 - price per sq. Ft. or m² | D30: =1.91/0.092903 -> 20.559078
C31: Total fee and facility costs
B32: Please specify, by how many % the costs increases over which period of time (e.g.7% per year starting 2025) | C32: Indexation of service fee and/or facility cost in percent per year | D32: Not indexed. Actual costs updaded yearly
B33: What is the start date of the lease? | C33: Lease Start Date | D33: 43459 | E33: 44075 | F33: 45078
B34: The next fixed break date in the lease | C34: Next Break Date | D34: 49302 | E34: N/A | F34: N/A
B35: The date by which notice must have been served | C35: Next Break Notice Expiry | D35: N/A | E35: N/A | F35: N/A
B36: Can the contract be terminated before the end of the lease? | C36: Does a termination clause exist? Yes/No | D36: No | E36: No | F36: No
B37: Please specify the exact conditions of the clause (date, notice period, penalty payments etc.) | C37: If yes, please specify the termination clause | D37: N/A | E37: N/A | F37: N/A
B38: Does the lease automatically renew? | C38: Auto Renewing Lease? Yes/No | D38: No | E38: No | F38: No
B39: How many months notice to prevent auto-renewal? | C39: Auto Renewal Notice Period (Months) | D39: N/A | E39: N/A | F39: N/A
B40: The current lease expiry date (leave blank if the lease is open ended) | C40: Lease End Date | D40: 49058 | E40: 49033 | F40: 49033
B41: Please choose "Yes" / "No"; in case of yes, please specify in the comment field | C41: Does your BU have the contractual possibility to sublet your property? Yes/No | D41: Yes
B42: Please provide the details of the sublease agreement in a separate column of the document | C42: If there is a sublease agreement in place, please provide the details in a separate column | D42: Yes | E42: Sublet: Superior Propane Aug 01/20-Mar 30/34 | F42: 2nd Sublet: Reeds Heritage Homes(no details at this time)
B43: Please state only yes, if the whole energy consumption of the location is covered by renewable energy | C43: Is the location operated with renewable energy? Yes/No | D43: Yes
B44: It could be an internationally recognized certificate (LEED, BREEAM, Green Star, etc.) or a more locally recognized certificate (e.g. DGNB in Germany) | C44: Does the office building hold any sustainability certificate? Yes/No - If yes please specify | D44: LEED Silver
C46: Number of HC working in this location as of Sept 2025 | D46: 668
C47: thereof No. of HC non-OPS
C48: thereof No. of HC OPS
C50: Number of workstations2 in this location | D50: 420
C51: thereof No. of HC non-OPS
C52: thereof No. of HC OPS
C54: H24 Operations in this site? Yes/No
C55: Average shifts per day for Operations people | D55: 2 (8 hours)
C56: Maximum shifts per day for Operations people | D56: 2 (8 hours)
C57: WFO rule for Platform operations people (number of days per week in the office)
C58: WFO rule for non Platform operations people (number of days per week in the office) | D58: 2 days in the office (recommended but not mandatory)
D60: 1783* - Accommodation Expenses
D61: 7831005 - Facilities IC rental expense: Premises IC rent → NOT TO BE INCLUDED
D62: 7832001 - Utilities expenses
D63: 7832002 - Maintenance expenses
D64: 7832003 - Other occupancy expenses
D65: 7833001 - Office equipment - scheduled
D66: 7833004 - Other Office Costs
D68: 2 The workstation needs to qualify as regular work place with a sufficient desktop and an appropriate office chair. Agile and collaboration areas are excluded

Sheet Colombia
C2: Update date | D2: 45961
C4: Country/BU | D4: BU Colombia
C6: Does your BU have multiple locations? (Please choose "Yes" / "No") | E6: No
C7: How many locations does your BU have (Please enter the number of office locations in your BU) | E7: 1
C9: Contact Person
C10: Location | D10: Location 1 - Bogota | E10: Location 2 - xxx | F10: Location 3 - xxx | G10: Location 4 - xxx | H10: Location 5 - xxx | I10: Location 6 - xxx | J10: Location 7 - xxx | K10: Location 8 - xxx | L10: Location 9 - xxx | M10: Location 10 - xxx | N10: Location 11 - xxx | O10: Location 12 - xxx | P10: Location 13 - xxx | Q10: Location 14 - xxx | R10: Location 15 - xxx
C11: Location unique ID | D11: CO01
B13: Describe the space: e.g. "Whole Building" or "1st and 2nd Floors" | C13: Unit Description | D13: Location from floor 2 to floor 4
B14: Please provide the postal address | C14: Street Address | D14: 72b Street # 6-44
B15: Try to use the greater metro city where possible | C15: Town | D15: Bogota
B16: | | C16: Postcode | D16: 110110
B17: Country - NOT business unit | C17: Country | D17: Colombia
B18: Please choose | C18: Rental / owned? | D18: Rental
B19: Is the office sublet or rented to you by an Allianz entity? | C19: Is the office located at an Allianz Premises? Yes/No | D19: Yes
B20: Does the Allianz entity provide the respective services as security, cleaning, etc.? | C20: Is the office also actively managed by an Allianz entity? Yes/No | D20: Yes
B21: The business name that signed the lease | C21: Tenant Name | D21: Allianz Partners Colombia
B22: The business name that owns the property | C22: Landlord Name | D22: Allianz Seguros de Vida SAS
B23: Please type in "sq. Ft." or "m²" | C23: m² | D23: m²
B24: Please specify the gross area of the office in sq. Ft. or m² as per lease agreement | C24: Total area gross | D24: =1150-131.07-155 -> 863.93
B25: The number of parking spaces in the lease and NOT the area in sq. Ft. or m² | C25: Parking Spaces | D25: 243 MTR
B26: 3 digit international currency code for the local currency e.g. EUR, GBP or USD | C26: Currency Code | D26: COP
C27: Total Rental Cost
B28: Total rental costs/ total sq. Ft. Or m²; in case location is owned, pls use reference prices | C28: Price per sq. Ft./m² Rent (in local currency) | D28: 475787.52
B29: Please specify, by how much the rent increases over which period of time (e.g.7% per year starting 2025) | C29: Indexation of the rent in percent per year | D29: IPC (CPI)
B30: Please do not include the rental cost | C30: Service fee and facility costs (According to Account 783*)1 - price per sq. Ft. or m² | D30: =229945763/D24 -> 266162.49
C31: Total fee and facility costs
B32: Please specify, by how many % the costs increases over which period of time (e.g.7% per year starting 2025) | C32: Indexation of service fee and/or facility cost in percent per year | D32: N/A
B33: What is the start date of the lease? | C33: Lease Start Date | D33: 44652
B34: The next fixed break date in the lease | C34: Next Break Date | D34: 46112
B35: The date by which notice must have been served | C35: Next Break Notice Expiry | D35: N/A
B36: Can the contract be terminated before the end of the lease? | C36: Does a termination clause exist? Yes/No | D36: Yes
B37: Please specify the exact conditions of the clause (date, notice period, penalty payments etc.) | C37: If yes, please specify the termination clause | D37: 1. With the exception of monetary obligations, in the event of breach of any of the obligations of this Contract by any of the Parties, the Party in breach shall make it debtor, as the case may be, by way of penalty, a sum equal to double the Fee in force at the time of the breach, without the need for private or judicial injunctions. In addition, the Party in default may collect damages and demand performance of the principal obligation. In this way, the payment of the penalty does not extinguish the principal obligation. 2. In the event of early termination of this Contract by the LESSEE without just cause, the LESSEE shall pay to the other party at the time of termination a sum equivalent to three (3) rental fees in force on the same date, proportional to the time elapsed in the contract, all of the above, without prejudice to the judicial or extrajudicial pursuit of the payment of all damages that any of the parties may incur for any reason, as expressly stipulated, in accordance with the power established in Articles 1600 and 1616 of the Civil Code.
B38: Does the lease automatically renew? | C38: Auto Renewing Lease? Yes/No | D38: YES / 1 year
B39: How many months notice to prevent auto-renewal? | C39: Auto Renewal Notice Period (Months) | D39: Three months
B40: The current lease expiry date (leave blank if the lease is open ended) | C40: Lease End Date | D40: 46477
B41: Please choose "Yes" / "No"; in case of yes, please specify in the comment field | C41: Does your BU have the contractual possibility to sublet your property? Yes/No | D41: No
B42: Please provide the details of the sublease agreement in a separate column of the document | C42: If there is a sublease agreement in place, please provide the details in a separate column | D42: No
B43: Please state only yes, if the whole energy consumption of the location is covered by renewable energy | C43: Is the location operated with renewable energy? Yes/No | D43: No
B44: It could be an internationally recognized certificate (LEED, BREEAM, Green Star, etc.) or a more locally recognized certificate (e.g. DGNB in Germany) | C44: Does the office building hold any sustainability certificate? Yes/No - If yes please specify | D44: No
C46: Number of HC working in this location as of Sept 2025 | D46: 136
C47: thereof No. of HC non-OPS | D47: 26
C48: thereof No. of HC OPS | D48: 90
C50: Number of workstations2 in this location | D50: 116
C51: thereof No. of HC non-OPS | D51: 26
C52: thereof No. of HC OPS | D52: 90
C54: H24 Operations in this site? Yes/No
C55: Average shifts per day for Operations people | D55: 3
C56: Maximum shifts per day for Operations people | D56: 3
C57: WFO rule for Platform operations people (number of days per week in the office)
C58: WFO rule for non Platform operations people (number of days per week in the office)
D60: 1783* - Accommodation Expenses
D61: 7831005 - Facilities IC rental expense: Premises IC rent → NOT TO BE INCLUDED
D62: 7832001 - Utilities expenses
D63: 7832002 - Maintenance expenses
D64: 7832003 - Other occupancy expenses
D65: 7833001 - Office equipment - scheduled
D66: 7833004 - Other Office Costs
D68: 2 The workstation needs to qualify as regular work place with a sufficient desktop and an appropriate office chair. Agile and collaboration areas are excluded

Sheet China
C2: Update date
C4: Country/BU | D4: BU China | E4: BU China | F4: BU China
C6: Does your BU have multiple locations? (Please choose "Yes" / "No") | E6: Yes
C7: How many locations does your BU have (Please enter the number of office locations in your BU) | E7: 3
C9: Contact person
C10: Location | D10: Location 1 - Bejing | E10: Location 2 - Chengdu | F10: Location 3 - Shanghai | G10: Location 4 - xxx | H10: Location 5 - xxx | I10: Location 6 - xxx
C11: Location unique ID | D11: CN01 | E11: CN02 | F11: CN03
B13: Describe the space: e.g. "Whole Building" or "1st and 2nd Floors" | C13: Unit Description | D13: A Zone, Building 7# Floor 3-5 | E13: 9F, Tower E2 | F13: Unit 1401
B14: Please provide the postal address | C14: Street Address | D14: Huitong Office Park, No.1 Yaojiayuan South Road, Chaoyang | E14: E zone, Tianfu Software Park, Gaoxin District, Chengdu | F14: Shanghai Tower, No.501 Yincheng Zhong Road, Pudong District
B15: Try to use the greater metro city where possible | C15: Town | D15: Beijing | E15: Chengdu | F15: Shanghai
B16: Postcode or Zip code | C16: Postcode | D16: 100123 | E16: 610041 | F16: 200120
B17: Country - NOT business unit | C17: Country | D17: China | E17: China | F17: China
B18: Please choose | C18: Rental / owned? | D18: Rental | E18: Rental | F18: Rental
B19: Is the office sublet or rented to you by an Allianz entity? | C19: Is the office located at an Allianz Premises? Y/N | D19: No | E19: No | F19: No
B20: Does the Allianz entity provide the respective services as security, cleaning, etc.? | C20: Is the office also actively managed by an Allianz entity? Y/N | D20: N | E20: N | F20: N
B21: The business name that signed the lease | C21: Tenant Name | D21: AzP China - 3594㎡ Fusang - 300㎡ FuAn - 100㎡ Broker - 200㎡ | E21: AzP China Chengdu | F21: AzP China Shanghai
B22: The business name that owns the property | C22: Landlord Name | D22: Beijing Mintong Jiye Investment Management Co., Ltd. | E22: Chengdu Hi-tech Investment Group Co., Ltd. | F22: Shanghai Tower Construction and Development Co., Ltd.
B23: Please type in "sq. Ft." or "m²" | C23: Office size measured in sq. Ft. or m² | D23: m² | E23: m² | F23: m²
B24: Please specify the gross area of the office in sq. Ft. or m² as per lease agreement | C24: Total area gross | D24: 2845 | E24: 2197 | F24: 550.16
B25: The number of parking spaces in the lease and NOT the area in sq. Ft. or m² | C25: Parking Spaces | D25: 10 | E25: 0 | F25: 0
B26: 3 digit international currency code for the local currency e.g. EUR, GBP or USD | C26: Currency Code | D26: CNY | E26: CNY | F26: CNY
C27: Total rental costs
B28: Total rental costs/ total sq. Ft. Or m²; in case location is owned, pls use reference prices | C28: Price per /m² Rent (in local currency) | D28: 1766.6 | E28: 840 | F28: 3650.04
B29: Please specify, by how much the rent increases over which period of time (e.g.7% per year starting 2025) | C29: Indexation of the rent in percent per year | D29: 0 | E29: 0 | F29: 0
B30: Please do not include the rental cost | C30: Service fee and facility costs (According to Account 783*)1 - price per m² | D30: 837.86 | E30: 624.35321 | F30: 1231.5327
C31: Total fee and facility costs
B32: Please specify, by how many % the costs increases over which period of time (e.g.7% per year starting 2025) | C32: Indexation of service fee and/or facility cost in percent per year | D32: - | E32: - | F32: -
B33: What is the start date of the lease? | C33: Lease Start Date | D33: 45301 | E33: 45246 | F33: 42975
B34: The next fixed break date in the lease | C34: Next Break Date | D34: 46031 | E34: 46022 | F34: 45940
B35: The date by which notice must have been served | C35: Next Break Notice Expiry
B36: Can the contract be terminated before the end of the lease? | C36: Does a termination clause exist? Y/N | D36: Y | E36: Y | F36: Y
B37: Please specify the exact conditions of the clause (date, notice period, penalty payments etc.) | C37: If yes, please specify the termination clause | D37: Application with offical notification letter to the landlord via 3 months in advance and also need bear limit 3 momths rental fee as dedit. | E37: Application with offical notification letter to the landlord via 3 months in advance and also need bear limit 3 momths rental fee as dedit.
B38: Does the lease automatically renew? | C38: Auto Renewing Lease? Y/N | D38: N | E38: N | F38: N
B39: How many months notice to prevent auto-renewal? | C39: Auto Renewal Notice Period (Months) | D39: - | E39: - | F39: -
B40: The current lease expiry date (leave blank if the lease is open ended) | C40: Lease End Date | D40: 46396 | E40: 46934 | F40: 46644
B41: Please choose "Yes" / "No"; in case of yes, please specify in the comment field | C41: Does your BU have the contractual possibility to sublet your property? Y/N | D41: N | E41: N | F41: N
B42: Name of the tenant, no. of floors, size of the area, etc. | C42: If there is a sublet contract in place, please provide details for all the agreements in place | D42: - | E42: - | F42: -
B43: Please state only yes, if the whole energy consumption of the location is covered by renewable energy | C43: Is the location operated with renewable energy? Y/N | D43: N | E43: N | F43: N
B44: It could be an internationally recognized certificate (LEED, BREEAM, Green Star, etc.) or a more locally recognized certificate (e.g. DGNB in Germany) | C44: Does the office building hold any sustainability certificate? Y/N - If yes please specify | D44: No | E44: No | F44: No
C46: Number of HC working in this location as of Sept 2025 | D46: 319 | E46: 256 | F46: 37 | J46: HRO = Human Resource Outsourcing, employees who signed a lanor contract with a 3rd party provider
C47: thereof No. of HC non-OPS
C48: thereof No. of HC OPS
C50: Number of workstations2 in this location | D50: 303 | E50: 398 | F50: 52
C51: thereof No. of HC non-OPS
C52: thereof No. of HC OPS
C54: H24 Operations in this site? Yes/No | D54: Yes
C55: Average shifts per day for Operations people | D55: 8working Hrs/Day | E55: 8 working Hrs/Day | F55: 8 working Hrs/Day
C56: Maximum shifts per day for Operations people | D56: - | E56: - | F56: -
C57: WFO rule for Platform operations people (number of days per week in the office)
C58: WFO rule for non Platform operations people (number of days per week in the office)
D60: 1783* - Accommodation Expenses
D61: 7831005 - Facilities IC rental expense: Premises IC rent → NOT TO BE INCLUDED
D62: 7832001 - Utilities expenses
D63: 7832002 - Maintenance expenses
D64: 7832003 - Other occupancy expenses
D65: 7833001 - Office equipment - scheduled
D66: 7833004 - Other Office Costs
D68: 2 The workstation needs to qualify as regular work place with a sufficient desktop and an appropriate office chair. Agile and collaboration areas are excluded

Sheet CzechRepublic
C2: Update date | D2: 45925
C4: Country/BU | D4: BU Czech Republic | E4: BU Czech Republic
C6: Does your BU have multiple locations? (Please choose "Yes" / "No") | E6: Yes
C7: How many locations does your BU have (Please enter the number of office locations in your BU) | E7: 2
C9: Contact Person
C10: Location | D10: Location 1 - Prague | E10: Location 2 - Bratislava | F10: Location 3 - xxx | G10: Location 4 - xxx | H10: Location 5 - xxx | I10: Location 6 - xxx | J10: Location 7 - xxx | K10: Location 8 - xxx | L10: Location 9 - xxx | M10: Location 10 - xxx | N10: Location 11 - xxx | O10: Location 12 - xxx | P10: Location 13 - xxx | Q10: Location 14 - xxx | R10: Location 15 - xxx
D11: CZ01 | E11: CZ02
B13: Describe the space: e.g. "Whole Building" or "1st and 2nd Floors" | C13: Unit Description | D13: 2nd floor in new constructed bulding | E13: 2nd floor old bulding, downtown of the city
B14: Please provide the postal address | C14: Street Address | D14: Jankovcova 1596/14B | E14: Čajakova 18
B15: Try to use the greater metro city where possible | C15: Town | D15: Prague | E15: Bratislava
B16: Postcode or Zip code | C16: Postcode | D16: 170 00 | E16: 811 05
B17: Country - NOT business unit | C17: Country | D17: Czech Republic | E17: Slovakia
B18: Please choose | C18: Rental / owned? | D18: Rental | E18: Rental
B19: Is the office sublet or rented to you by an Allianz entity? | C19: Is the office located at an Allianz Premises? Yes/No | D19: No | E19: No
B20: Does the Allianz entity provide the respective services as security, cleaning, etc.? | C20: Is the office also actively managed by an Allianz entity? Yes/No | D20: No | E20: No
B21: The business name that signed the lease | C21: Tenant Name | D21: AP Solutions GmbH Česká republika - odštěpný závod zahraniční právnické osoby | E21: AP Solutions GmbH Slovenská republika, organizačná zložka
B22: The business name that owns the property | C22: Landlord Name | D22: PM Office center One s.r.o. | E22: Sintec spol s.r.o.
C23: m² | D23: m² | E23: m²
B24: Please specify the gross area of the office in sq. Ft. or m² as per lease agreement | C24: Total area gross | D24: 1293.19 | E24: 74
B25: The number of parking spaces in the lease and NOT the area in sq. Ft. or m² | C25: Parking Spaces | D25: 14 | E25: 1
B26: 3 digit international currency code for the local currency e.g. EUR, GBP or USD | C26: Currency Code | D26: CZK/EUR | E26: EUR
B27: Total rental costs | C27: Total rental costs
B28: Total rental costs/ total sq. Ft. Or m²; in case location is owned, pls use reference prices | C28: Price per sq. Ft./m² Rent (in local currency) | D28: 144 | E28: 168
B29: Please specify, by how much the rent increases over which period of time (e.g.7% per year starting 2025) | C29: Indexation of the rent in percent per year | D29: indexation only for the price per offices - for 2025 = 2,5% | E29: no indexation
B30: Please do not include the rental cost | C30: Service fee and facility costs (According to Account 783*)1 - price per sq. Ft. or m² | D30: 90855.8 | E30: 50.4
C31: Total fee and facility costs
B32: Please specify, by how many % the costs increases over which period of time (e.g.7% per year starting 2025) | C32: Indexation of service fee and/or facility cost in percent per year | D32: no indexation | E32: The possibility of indexation is in the agreement. But there was no indexation for previous years.
B33: What is the start date of the lease? | C33: Lease Start Date | D33: 40210 | E33: 37669
B34: The next fixed break date in the lease | C34: Next Break Date | D34: 45900 | E34: 3 months notice at any given time
B35: The date by which notice must have been served | C35: Next Break Notice Expiry | D35: 1.2.2025 - 14.2.2025 | E35: -
B36: Can the contract be terminated before the end of the lease? | C36: Does a termination clause exist? Yes/No | D36: Yes | E36: Yes
B37: Please specify the exact conditions of the clause (date, notice period, penalty payments etc.) | C37: If yes, please specify the termination clause | D37: If the notice is delivered between 1.2.2025 and 14.2.2025 there is a possibility to terminater the lease before the lease end date without any penatly payments. The notice period in 6 months and begins from the first day of the calendar month following the calendar month in which the notice was delivered. The tenant is entitled to terminate the Lease Agreement early before the Lease End Date only for the following reasons: 1. The premises or part of them cannot be used for reasons not attributable to the tenant. 2. The landlord repeatedly violates the obligations arising from the Lease Agreement by limiting the tenant's use of the premises. 3. The premises becime demonstrably unfit for the contracted use through no fault of the tenant and this will not be rectified by the landlord. 4. The court will make a final decision on the declaration of bankruptcy ot the landlord. 5. The landlord general meeting will decide on the landlord's entry into liquidation. These clauses are detailed int he Lease Agreement in paragraph 10. Early termination of the Lease | E37: Termination may be given without giving any reason. The notice period is 3 months and starts from the first day of the month following the month in which the notice was delivered. The landlord is entitled to give the tenant immediate notice in the event of violation of the deadlines of the rent and energy pamyents if the delay is more than 30 days. Tenant is entitled to give immediate notice if there is no possibility to use the premises for the agreed purposes for more than 30 days. The lease agreement ends with the demise of subject of the lease ot the demise of the tenant.
B38: Does the lease automatically renew? | C38: Auto Renewing Lease? Yes/No | D38: No | E38: No
B39: How many months notice to prevent auto-renewal? | C39: Auto Renewal Notice Period (Months) | D39: - | E39: -
B40: The current lease expiry date (leave blank if the lease is open ended) | C40: Lease End Date | D40: 46599 | E40: Indefinite
B41: Please choose "Yes" / "No"; in case of yes, please specify in the comment field | C41: Does your BU have the contractual possibility to sublet your property? Yes/No | D41: only with the landlord's consent | E41: only with the landlord's consent
B42: Please provide the details of the sublease agreement in a separate column of the document | C42: If there is a sublease agreement in place, please provide the details in a separate column | D42: No | E42: No
B43: Please state only yes, if the whole energy consumption of the location is covered by renewable energy | C43: Is the location operated with renewable energy? Yes/No | D43: No | E43: No
B44: It could be an internationally recognized certificate (LEED, BREEAM, Green Star, etc.) or a more locally recognized certificate (e.g. DGNB in Germany) | C44: Does the office building hold any sustainability certificate? Yes/No - If yes please specify | D44: No | E44: No
C46: Number of HC working in this location as of Sept 2025 | D46: 171 | E46: 5
C47: thereof No. of HC non-OPS | D47: 24 | E47: 4
C48: thereof No. of HC OPS | D48: 147 | E48: 1
C50: Number of workstations2 in this location | D50: 126 | E50: 6
C51: thereof No. of HC non-OPS | D51: 104 | E51: 5
C52: thereof No. of HC OPS | D52: 22 | E52: 1
C54: H24 Operations in this site? Yes/No | D54: Yes | E54: No
C55: Average shifts per day for Operations people | D55: 80 | E55: 0
C56: Maximum shifts per day for Operations people | D56: 100 | E56: 0
C57: WFO rule for Platform operations people (number of days per week in the office) | D57: 2 | E57: 2
C58: WFO rule for non Platform operations people (number of days per week in the office) | D58: 1 | E58: 1
D60: 1783* - Accommodation Expenses
D61: 7831005 - Facilities IC rental expense: Premises IC rent → NOT TO BE INCLUDED
D62: 7832001 - Utilities expenses
D63: 7832002 - Maintenance expenses
D64: 7832003 - Other occupancy expenses
D65: 7833001 - Office equipment - scheduled
D66: 7833004 - Other Office Costs
D68: 2 The workstation needs to qualify as regular work place with a sufficient desktop and an appropriate office chair. Agile and collaboration areas are excluded

Sheet Egypt
C2: Update date | D2: 46042
C4: Country/BU | D4: Nextcare | E4: Nextcare | F4: Nextcare
C6: Does your BU have multiple locations? (Please choose "Yes" / "No") | E6: No
C7: How many locations does your BU have (Please enter the number of office locations in your BU)
C9: Contact Person | D9: Ismail Abdelfatah /Amal Evram | E9: Ismail Abdelfatah /Amal Evram | F9: Ismail Abdelfatah /Amal Evram
C10: Location | D10: Location 7 - Cairo | E10: Location 8 - Cairo | F10: Location 9 - Cairo | G10: Location 4 - | H10: Location 5 - | I10: Location 6 - | J10: Location 7 - | K10: Location 8 - | L10: Location 9 - | M10: Location 10 -
C11: Location unique ID | D11: EG01 | E11: EG01 | F11: EG02
E12: Car Parking Contract | F12: Warehouse Rental Contract
B13: Describe the space: e.g. "Whole Building" or "1st and 2nd Floors" | C13: Unit Description | D13: 2nd floor | E13: M1 | F13: ground floor
B14: Please provide the postal address | C14: Street Address | D14: Emerald Twin Plaza, Plot No. (6), 1st settlement, New Cairo, Cairo, Egypt | E14: Emerald Twin Plaza, Plot No. (6), 1st settlement, New Cairo, Cairo, Egypt | F14: Street 9, Plot no. 8230, Mokattam city, Cairo
B15: Try to use the greater metro city where possible | C15: Town | D15: New Cairo | E15: New Cairo | F15: Mokattem city
B16: Postcode or Zip code | C16: Postcode | D16: N/A | E16: N/A | F16: N/A
B17: Country - NOT business unit | C17: Country | D17: Egypt | E17: Egypt | F17: Egypt
B18: Please choose | C18: Rental / owned? | D18: Rental | E18: Rental | F18: Rental
B19: Is the office sublet or rented to you by an Allianz entity? | C19: Is the office located at an Allianz Premises? Yes/No | D19: No | E19: No | F19: No
B20: Does the Allianz entity provide the respective services as security, cleaning, etc.? | C20: Is the office also actively managed by an Allianz entity? Yes/No | D20: No | E20: No | F20: No
B21: The business name that signed the lease | C21: Tenant Name | D21: Nextcare LLC | E21: Nextcare LLC | F21: NEXTCARE LLC
B22: The business name that owns the property | C22: Landlord Name | D22: Egyptians for housing and development, joint stock company | E22: Egyptians for housing and development, joint stock company | F22: Ali Hassan Ali
B23: Unit sq FT or m² | C23: m² | D23: m² | E23: slot | F23: m²
B24: Please specify the gross area of the office in sq. Ft. or m² as per lease agreement | C24: Total area gross | D24: 5380 | E24: 130 | F24: 37.16
B25: The number of parking spaces in the lease and NOT the area in sq. Ft. or m² | C25: Parking Spaces | D25: 130 | E25: 130 | F25: 0
B26: 3 digit international currency code for the local currency e.g. EUR, GBP or USD | C26: Currency Code | D26: EGP | E26: EGP | F26: EGP
B27: Total rental costs | C27: Total rental costs | D27: =2196331.2*12 -> 26355974 | E27: 1170000 | F27: 300000
B28: Total rental costs/ total sq. Ft. Or m²; in case location is owned, pls use reference prices | C28: Price per sq. Ft./m² Rent (in local currency)/ month | D28: =D27/D24 -> 4898.88 | E28: =E27/E24 -> 9000 | F28: =F27/F24 -> 8073.197
B29: Please specify, by how much the rent increases over which period of time (e.g.7% per year starting 2025) | C29: Indexation of the rent in percent per year | D29: 8% annual | E29: NA | F29: 10% Annual
B30: Please do not include the rental cost | C30: Service fee and facility costs (According to Account 783*)1 - price per sq. Ft. or m² | D30: =D31/D24 -> 1554.8204 | E30: =E31/E24 -> 0 | F30: =F31/F24 -> 0
C31: Total fee and facility costs | D31: =5647708.8+2717224.8 -> 8364933.6
B32: Please specify, by how many % the costs increases over which period of time (e.g.7% per year starting 2025) | C32: Indexation of service fee and/or facility cost in percent per year | D32: 8% for service fee
B33: What is the start date of the lease? | C33: Lease Start Date | D33: 45078 | E33: 45261 | F33: 44501
B34: The next fixed break date in the lease | C34: Next Break Date | D34: 48365 | E34: 46356 | F34: 46325
B35: The date by which notice must have been served | C35: Next Break Notice Expiry | D35: N/A | E35: NA | F35: NA
B36: Can the contract be terminated before the end of the lease? | C36: Does a termination clause exist? Yes/No | D36: Yes | E36: NO | F36: Yes
B37: Please specify the exact conditions of the clause (date, notice period, penalty payments etc.) | C37: If yes, please specify the termination clause | D37: the minimum leasing term is 2 years. If we wish to terminate the lease after 2 years, we need to give notice of 3 months before exit date | F37: 2 months notice period
B38: Does the lease automatically renew? | C38: Auto Renewing Lease? Yes/No | D38: No | E38: NO | F38: NO
B39: How many months notice to prevent auto-renewal? | C39: Auto Renewal Notice Period (Months) | D39: No | E39: NO | F39: NO
B40: The current lease expiry date (leave blank if the lease is open ended) | C40: Lease End Date | D40: 48365 | E40: 46356 | F40: 46325
B41: Please choose "Yes" / "No"; in case of yes, please specify in the comment field | C41: Does your BU have the contractual possibility to sublet your property? Yes/No | D41: No | E41: NO | F41: NO
B42: Please provide the details of the sublease agreement in a separate column of the document | C42: If there is a sublease agreement (external or internal) in place, please provide the details in a separate column | D42: No | E42: No | F42: NO
B43: Please state only yes, if the whole energy consumption of the location is covered by renewable energy | C43: Is the location operated with renewable energy? Yes/No | D43: N/A | E43: NO | F43: NO
B44: It could be an internationally recognized certificate (LEED, BREEAM, Green Star, etc.) or a more locally recognized certificate (e.g. DGNB in Germany) | C44: Does the office building hold any sustainability certificate? Yes/No - If yes please specify | D44: No | E44: NO | F44: NO
C46: Number of HC working in this location | D46: 1251 | E46: 0 | F46: 0
C47: thereof No. of HC not working on operations platforms (call centers) | D47: 61 | E47: 0 | F47: 0
C48: thereof No. of HC working in operations platforms (call centers) | D48: =D46-D47 -> 1190 | E48: 0 | F48: 0
C50: Number of workstations2 in this location | D50: 769 | E50: 0 | F50: 0
C51: thereof No. of HC non-platform operations | E51: 0 | F51: 0
C52: thereof No. of HC platform operations | F52: 0
C54: H24 Operations in this site? Yes/No | D54: Yes | E54: No | F54: No
C55: Average shifts per day for Platform Operations people | D55: 2 | E55: 0 | F55: 0
C56: Maximum shifts per day for Platform Operations people | D56: 2 | E56: 0 | F56: 0
C57: WFO rule for Platform operations people (number of days per week in the office)
C58: WFO rule for non Platform operations people (number of days per week in the office)

Sheet France
C2: Update date | D2: 45979
C4: Country/BU | D4: BU France | E4: BU France | F4: BU France | G4: BU France | H4: BU France | I4: Global Office
C6: Does your BU have multiple locations? (Please choose "Yes" / "No") | E6: Yes
C7: How many locations does your BU have (Please enter the number of office locations in your BU) | E7: 5
C9: Contact Person
C10: Location | D10: Location 1 - ESQ 2 | E10: Location 2 - Le Mans | F10: Location 3 - ESQ 1 | G10: Location 4 - Chatillon | H10: Location 5 - Armentières | I10: St. Ouen / Eurosquare 2 | J10: Location 7 - | K10: Location 8 - | L10: Location 9 - | M10: Location 10 -
C11: Location unique ID | D11: FR01 | E11: FR02 | F11: FR03 | G11: FR05 | H11: FR06 | I11: FR01
B13: Describe the space: e.g. "Whole Building" or "1st and 2nd Floors" | C13: Unit Description | D13: Group of 2 buildings composed of all ground floor part of 1st floor 2nd, 3rd, 4th, 5th,7th floors | E13: Group of 2 buildings | F13: 3rd floor | G13: Ground, 1st and 2nd Floor | H13: Whole Building | I13: 6 & 8th floor
B14: Please provide the postal address | C14: Street Address | D14: 7 rue Dora Maar | E14: Chemin aux bœuf & les Hunaudières | F14: 151 Boulevard Victor Hugo | G14: 79-81 Rue Pierre Semard | H14: 85 Quai de Beauvais | I14: 7rue Dora Maar
B15: Try to use the greater metro city where possible | C15: Town | D15: Saint Ouen | E15: Le Mans | F15: Saint Ouen | G15: Chatillon | H15: Armentières | I15: Saint Ouen
B16: Postcode or Zip code | C16: Postcode | D16: 93400 | E16: 72000 | F16: 93400 | G16: 92320 | H16: 59280 | I16: 93400
B17: Country - NOT business unit | C17: Country | D17: France | E17: France | F17: France | G17: France | H17: France | I17: France
B18: Please choose | C18: Rental / owned? | D18: Rental | E18: Rental | F18: Rental | G18: Rental | H18: Rental | I18: Rental
B19: Is the office sublet or rented to you by an Allianz entity? | C19: Is the office located at an Allianz Premises? Yes/No | D19: No | E19: No | F19: No | G19: No | H19: No | I19: No
B20: Does the Allianz entity provide the respective services as security, cleaning, etc.? | C20: Is the office also actively managed by an Allianz entity? Yes/No | D20: No | E20: No | F20: Yes | G20: No | H20: No | I20: Yes
B21: The business name that signed the lease | C21: Tenant Name | D21: AWP France SAS | E21: AWP France SAS | F21: Allianz Partners SAS | G21: GTS | H21: GTS | I21: Allianz Partners SAS
B22: The business name that owns the property | C22: Landlord Name | D22: SCPI ACCIMO - PIERRE | E22: SECOS | F22: HECF FRANCE 2 SCI | G22: PF1 | H22: SOCIETE CIVILE IMMOBILIERE DU STADE | I22: SCPI ACCIMMO PIERRE
B23: Unit sq FT or m² | C23: m² | D23: m² | E23: m² | F23: m² | G23: m² | H23: m² | I23: m²
B24: Please specify the gross area of the office in sq. Ft. or m² as per lease agreement | C24: Total area gross | D24: 12407 | E24: 4403 | F24: 2127 | G24: 1269 | H24: 235 | I24: 5148
B25: The number of parking spaces in the lease and NOT the area in sq. Ft. or m² | C25: Parking Spaces | D25: 151 | E25: 220 | F25: 37 | G25: 20 | H25: 5 | I25: 50
B26: 3 digit international currency code for the local currency e.g. EUR, GBP or USD | C26: Currency Code | D26: EUR | E26: EUR | F26: EUR | G26: EUR | H26: EUR | I26: EUR
B27: Total rental costs | C27: Total rental costs
B28: Total rental costs/ total sq. Ft. Or m²; in case location is owned, pls use reference prices | C28: Price per sq. Ft./m² Rent (in local currency) | D28: 353.15 | E28: 127.46 | F28: 368.4598 | G28: 308.12 | H28: 129.31 | I28: 349.65035
B29: Please specify, by how much the rent increases over which period of time (e.g.7% per year starting 2025) | C29: Indexation of the rent in percent per year | D29: ILAT Indice | E29: ILAT indice | F29: ILAT | G29: yearly ILAT | H29: yearly ILC | I29: 0.03
B30: Please do not include the rental cost | C30: Service fee and facility costs (According to Account 783*)1 - price per sq. Ft. or m² | D30: =3209000/D24 -> 258.64431 | E30: =344000/E24 -> 78.128549 | F30: 235.07287 | G30: 195000 | H30: 50000 | I30: 213.67521
C31: Total fee and facility costs
B32: Please specify, by how many % the costs increases over which period of time (e.g.7% per year starting 2025) | C32: Indexation of service fee and/or facility cost in percent per year | D32: between 7 and 9 % depending on the evolution of wage costs and energy | E32: between 7 and 9 % depending on the evolution of wage costs and energy | F32: N/A | G32: 2024 vs 2023 : +7 % | H32: 2024 vs 2023 / + 29 %
B33: What is the start date of the lease? | C33: Lease Start Date | D33: 42125 | E33: 43891 | F33: 45078 | G33: 43009 | H33: 43739 | I33: 42491
B34: The next fixed break date in the lease | C34: Next Break Date | D34: 47968 | E34: 46082 | F34: 46173 | G34: 46295 | H34: 45930 | I34: 47968
B35: The date by which notice must have been served | C35: Next Break Notice Expiry | D35: 47603 | E35: 45897 | F35: 45808 | G35: 46082 | H35: 45747 | I35: 47603
B36: Can the contract be terminated before the end of the lease? | C36: Does a termination clause exist? Yes/No | D36: yes | E36: Each triennium | F36: 12 months notification to end on next break date | G36: No | H36: 46295 | I36: 12 months notification to end on next break date
B37: Please specify the exact conditions of the clause (date, notice period, penalty payments etc.) | C37: If yes, please specify the termination clause | D37: 12 months notification to cancel the contract after the first 6 years | E37: 6 months notice before each triennium | G37: No | H37: 6 month before the end of the triennal period | I37: 12 months notification to cancel the contract after the first 6 years
B38: Does the lease automatically renew? | C38: Auto Renewing Lease? Yes/No | D38: no | E38: no | F38: No | G38: Yes | H38: Yes | I38: no
B39: How many months notice to prevent auto-renewal? | C39: Auto Renewal Notice Period (Months) | D39: 12 months | E39: 6 months | F39: No | G39: 6 | H39: 6 | I39: no
B40: The current lease expiry date (leave blank if the lease is open ended) | C40: Lease End Date | D40: 49064 | E40: 47177 | F40: 46356 | G40: 46295 | H40: 47026 | I40: 49064
B41: Please choose "Yes" / "No"; in case of yes, please specify in the comment field | C41: Does your BU have the contractual possibility to sublet your property? Yes/No | D41: Only for a company belonging to ALLIANZ PARTNERS with prior consent of the owner | E41: Only for a company belonging to ALLIANZ PARTNERS with prior consent of the owner | F41: Yes | G41: Yes | H41: No | I41: Yes
B42: Please provide the details of the sublease agreement in a separate column of the document | C42: If there is a sublease agreement (external or internal) in place, please provide the details in a separate column | D42: Yes | E42: No | F42: Yes | G42: No | H42: No | I42: Yes
B43: Please state only yes, if the whole energy consumption of the location is covered by renewable energy | C43: Is the location operated with renewable energy? Yes/No | D43: NO | E43: NO | F43: Yes | G43: No | H43: No | I43: Yes
B44: It could be an internationally recognized certificate (LEED, BREEAM, Green Star, etc.) or a more locally recognized certificate (e.g. DGNB in Germany) | C44: Does the office building hold any sustainability certificate? Yes/No - If yes please specify | D44: No | E44: No | F44: HQE exploitation | G44: No | H44: No | I44: No
C46: Number of HC working in this location | D46: 1193 | E46: 602 | F46: 123 | G46: 99 | H46: 13 | I46: 350
C47: thereof No. of HC not working on operations platforms (call centers) | D47: 190 | E47: 5
C48: thereof No. of HC working in operations platforms (call centers) | D48: =D46-D47 -> 1003 | E48: =E46-E47 -> 597
C50: Number of workstations2 in this location | D50: =172+183+170+162+155+157+21 -> 1020 | E50: =346+55+29 -> 430 | F50: 136 | G50: 117 | H50: 27 | I50: 298
C51: thereof No. of HC non-platform operations | D51: =14+16+170+161+135+13 -> 509 | E51: 29 | F51: 136 | I51: 298
C52: thereof No. of HC platform operations | D52: =158+167+1+20+157+8 -> 511 | E52: 401
D53: 1
C54: H24 Operations in this site? Yes/No | D54: 2 | E54: 3
C55: Average shifts per day for Platform Operations people | D55: 4 | E55: 4
C56: Maximum shifts per day for Platform Operations people
C57: WFO rule for Platform operations people (number of days per week in the office)
C58: WFO rule for non Platform operations people (number of days per week in the office)

Sheet Germany
C2: Update date | D2: 45947
C4: Country/BU | D4: Germany | E4: Germany | F4: BU Germany (AHS) | G4: BU Germany (REHACARE) | H4: BU Germany (AHS) | I4: BU Germany (AHS) | J4: BU Germany (AHS) | K4: BU Germany (REHACARE) | L4: BU Germany (REHACARE) | M4: BU Germany (AHS) | N4: BU Germany (REHACARE) | O4: BU Germany (REHACARE) | P4: BU Germany (REHACARE) | Q4: BU Germany (REHACARE) | R4: BU Germany (AHS) | S4: BU Germany (MKS) | T4: BU Germany (REHACARE) | U4: BU Germany (MAWISTA) | V4: BU Germany (REHACARE) | W4: BU Germany (AVS) | X4: BU Germany (REHACARE) | Y4: BU Germany (AHS) | Z4: BU Germany (REHACARE) | AA4: BU Germany (REHACARE) | AB4: BU Germany (AZ Warranty) | AC4: Allianz Global Benefits | AD4: Allianz Global Benefits | AE4: Global Office
C6: Does your BU have multiple locations? (Please choose "Yes" / "No") | E6: Yes
C7: How many locations does your BU have (Please enter the number of office locations in your BU) | E7: 30
C8: Remarks | D8: we are no longer in the building; rental contract taken over by Allianz ONE | E8: we are no longer in the building; rental contract taken over by Allianz ONE | F8: Move to Allianz Campus planned for Q2/26 - contract terminated | N8: Contract terminated as of 31 March 2026 | W8: Data missing - need to follow up | AB8: under evaluation
C9: Contact Person | D9: Daniel Krauss | E9: Daniel Krauss | F9: Daniel Krauss | G9: Daniel Krauss | H9: Daniel Krauss | I9: Daniel Krauss | J9: Daniel Krauss | K9: Daniel Krauss | L9: Daniel Krauss | M9: Daniel Krauss | N9: Daniel Krauss | O9: Daniel Krauss | P9: Daniel Krauss | Q9: Daniel Krauss | R9: Daniel Krauss | S9: Daniel Krauss | T9: Daniel Krauss | U9: Daniel Krauss | V9: Daniel Krauss | W9: Daniel Krauss | X9: Daniel Krauss | Y9: Daniel Krauss | Z9: Daniel Krauss | AA9: Daniel Krauss | AB9: Daniel Krauss
C10: Location | D10: Location 1 - Aschheim - AP Deutschland GmbH | E10: Location 2 - Aschheim - AHS | F10: Location 3 - Berlin - AHS | G10: Location 5 - Bad Vibel - Rehacare | H10: Location 8 - Düsseldorf AHS | I10: Location 9 - Frankfurt - AHS | J10: Location 10 - Hamburg - AHS | K10: Location 11 - Hamburg - Rehacare | L10: Location 12 - Jena - Rehacare | M10: Location 13 - Leipzig - AHS | N10: Location 14 - Ludwigsburg - Rehacare | O10: Location 15 - Magdeburg - Rehacare | P10: Location 16 - Meisenheim - Rehacare | Q10: Location 17 - München - Rehacare | R10: Location 18 - Neustadt - AHS | S10: Location 19 - Nürnberg - MKS | T10: Location 20 - Nürnberg - Rehacare | U10: Location 22 - Plochingen - Mawista | V10: Location 23 - Pulsnitz - Rehacare | W10: Location 24 - Rüsselsheim - AVS | X10: Location 25 - Siegen - Rehacare | Y10: Location 26 - Stuttgart - AHS | Z10: Location 28 - Weinheim - Rehacare | AA10: Location 29 - Unna - Rehacare | AB10: Location 30 - Unterföhring - Az Warranty | AC10: Location 1 - Munich | AD10: Location 2 - Stuttgart | AE10: Location 1 - Munich
C11: Location unique ID | F11: DE02 | G11: DE14 | H11: DE03 | I11: DE04 | J11: DE05 | K11: DE16 | L11: DE17 | M11: DE06 | N11: DE18 | O11: DE19 | P11: DE20 | Q11: DE21 | R11: DE07 | S11: DE13 | T11: DE22 | U11: DE12 | V11: DE24 | W11: DE09 | X11: DE25 | Y11: DE08 | Z11: DE27 | AA11: DE28 | AB11: DE10 | AC11: AGB01 | AD11: AGB02 | AE11: DE29
B13: Describe the space: e.g. "Whole Building" or "1st and 2nd Floors" | C13: Unit Description | D13: Ground floor, 1st- 4th floor | E13: Ground floor | F13: Ground floor, 1st and 2nd floor | G13: 1st Floor | H13: 3rd floor | I13: 2nd floor | J13: part of second floor | K13: 1st Floor | L13: 1st Floor | M13: 2nd floor | N13: 1st Floor | O13: 6th Floor | P13: 1st Floor | Q13: 2nd Floor | R13: 1st floor | S13: 2nd Floor Building B | T13: 3rd Floor | U13: Whole 1st floor | V13: 1st Floor | W13: ? | X13: 5th Floor | Y13: part of the 4th floor | Z13: 1st Floor | AA13: Ground Floor | AB13: 50% ground floor | AC13: part of ground floor | AD13: part of 1st floor | AE13: 4th and 5th floor
B14: Please provide the postal address | C14: Street Address | D14: Bahnhofstrasse 16 | E14: Bahnhofstrasse 16 | F14: Albert-Einstein-Strasse 1a | G14: Frankfurter Str. 40 | H14: Heltorfer Strasse 4 | I14: Herriotstraße 1 | J14: Kapstadtring 2 | K14: Stormsweg 3 | L14: Dornburger Str. 161 | M14: Springerstrasse 25 | N14: Voithstr. 4 | O14: Otto-von-Guericke-Straße 87a | P14: Marktgasse 7b | Q14: Kapuzinerstraße 9D | R14: Maximilianstr. 5 | S14: Deutschherrnstraße 15-19 | T14: Karl-Grillenberger-Str. 1 | U14: Esslinger Str. 83 | V14: Robert-Koch-Straße 9 | W14: Ferdinand-Stuttmann-Str. 10 | X14: Weidenauer Str. 167a | Y14: Heßbrühlstraße 2 | Z14: Hildastr. 10 | AA14: Max-Planck-Str. 7 | AB14: Beta-Str. 13 | AC14: Seidlstrasse 24-24a | AD14: Uhlandstrasse 2 | AE14: Atelierstrasse 14
B15: Try to use the greater metro city where possible | C15: Town | D15: Aschheim/München | E15: Aschheim/München | F15: Berlin | G15: Bad Vilbel | H15: Düsseldorf | I15: Frankfurt | J15: Hamburg | K15: Hamburg | L15: Jena | M15: Leipzig | N15: Ludwigsburg | O15: Magdeburg | P15: Meisenheim | Q15: München | R15: Neustadt | S15: Nürnberg | T15: Nürnberg | U15: Plochingen | V15: Pulsnitz | W15: Rüsselsheim | X15: Siegen | Y15: Stuttgart | Z15: Weinheim | AA15: Unna | AB15: Unterföhring | AC15: Munich | AD15: Stuttgart | AE15: Munich
B16: Postcode or Zip code | C16: Postcode | D16: 85609 | E16: 85609 | F16: 12489 | G16: 61118 | H16: 40472 | I16: 60528 | J16: 22297 | K16: 22805 | L16: 07743 | M16: 04105 | N16: 71640 | O16: 39104 | P16: 55590 | Q16: 80337 | R16: 67433 | S16: 90429 | T16: 90402 | U16: 73207 | V16: 01896 | W16: 65428 | X16: 57076 | Y16: 70565 | Z16: 69469 | AA16: 59423 | AB16: 85774 | AC16: 80335 | AD16: 70182 | AE16: 81671
B17: Country - NOT business unit | C17: Country | D17: Germany | E17: Germany | F17: Germany | G17: Germany | H17: Germany | I17: Germany | J17: Germany | K17: Germany | L17: Germany | M17: Germany | N17: Germany | O17: Germany | P17: Germany | Q17: Germany | R17: Germany | S17: Germany | T17: Germany | U17: Germany | V17: Germany | W17: Germany | X17: Germany | Y17: Germany | Z17: Germany | AA17: Germany | AB17: Germany | AC17: Germany | AD17: Germany | AE17: Germany
B18: Please choose | C18: Rental / owned? | D18: Rental | E18: Rental | F18: Rental | G18: Rental | H18: Rental | I18: Rental | J18: Rental | K18: Rental | L18: Rental | M18: Rental | N18: Rental | O18: Rental | P18: Rental | Q18: Rental | R18: Rental | S18: Rental | T18: Rental | U18: Rental | V18: Rental | W18: Rental | X18: Rental | Y18: Rental | Z18: Rental | AA18: Rental | AB18: Rental | AC18: Rental | AD18: Rental | AE18: Rental
B19: Is the office sublet or rented to you by an Allianz entity? | C19: Is the office located at an Allianz Premises? Yes/No | D19: No | E19: No | F19: No | G19: No | H19: No | I19: No | J19: Yes | K19: No | L19: No | M19: No | N19: No | O19: No | P19: No | Q19: No | R19: No | S19: No | T19: No | U19: No | V19: No | W19: No | X19: No | Y19: Yes | Z19: No | AA19: No | AB19: Yes | AC19: Yes | AD19: Yes | AE19: No
B20: Does the Allianz entity provide the respective services as security, cleaning, etc.? | C20: Is the office also actively managed by an Allianz entity? Yes/No | D20: No | E20: No | F20: No | G20: No | H20: No | I20: No | J20: Yes | K20: No | L20: No | M20: No | N20: No | O20: No | P20: No | Q20: No | R20: No | S20: No | T20: No | U20: No | V20: No | W20: No | X20: No | Y20: Yes | Z20: No | AA20: No | AB20: Yes | AC20: Yes | AD20: Yes | AE20: Yes
B21: The business name that signed the lease | C21: Tenant Name | D21: AP Solution GmbH | E21: included in Location 1 | F21: AP Solution GmbH | G21: Rehacare | H21: AP Solution GmbH | I21: AP Solution GmbH | J21: AP Solution GmbH | K21: Rehacare | L21: Rehacare | M21: AP Solution GmbH | N21: Rehacare | O21: Rehacare | P21: Rehacare | Q21: Rehacare | R21: AP Solution GmbH | S21: AP Solution GmbH | T21: Rehacare | U21: MAWISTA GmbH | V21: Rehacare | W21: AP Solution GmbH | X21: Rehacare | Y21: AP Solution GmbH | Z21: Rehacare | AA21: Rehacare | AB21: Warranty GmbH | AC21: Allianz Global Benefits GmbH | AD21: Allianz Global Benefits GmbH | AE21: Allianz Partners S.A.S. German Branch
B22: The business name that owns the property | C22: Landlord Name | D22: MG-Dornach Bestandsgebäude GmbH | E22: included in Location 1 | F22: Europa-Center AG | G22: Knodt, Lothar | H22: Sirius Narcissus GmbH & Go. KG | I22: Deka Immobilien Investment GmbH | J22: Allianz ONE Business | K22: Wördemann, Gerd | L22: Kommunale Immobilien Jena | M22: LE Property 2 GmbH | N22: Weda, Peter | O22: Trigon Grundstücks-gesellschaft mbH & Co | P22: Haas, Constanze | Q22: Grundbesitzgesell- schaft Gebrüder Kurz GbR | R22: Bruchteilsgemeinschaft/ Hausgemeinschaft Maximilianstraße 5 | S22: Plum Crocos Property GmbH (AroundTown) | T22: Tetris Grundbesitz GmbH & Co.KG | U22: Grundstücksgemeinschaft Plochingen – Dagmar, Thomas und Oliver Kube Esslinger Straße 8, 73207 Plochingen/N. | V22: Schelzel, Falk | X22: ImPro Immobilienprojektierung und Verwaltungs-GmbH | Y22: Allianz ONE Business | Z22: Dr. Fischer, Gerd | AA22: Moritz Andersen GmbH | AB22: Allianz ONE Business | AC22: Allianz One- Business Solutions GmbH | AD22: Allianz One - Business Solutions GmbH | AE22: Werksviertel Vermietungs GmbH
C23: m² | D23: 8118.35 | E23: included in Location 1 | F23: 2391.74 | H23: 480.14 | I23: 497 | J23: 144.85 | K23: 42 | L23: 48.16 | M23: 322.97 | N23: 108 | O23: 433 | P23: 30 | Q23: 385.15 | R23: 349 | S23: 660 | T23: 53.4 | U23: 394.61 | V23: 40 | X23: 20 | Y23: 81.16 | Z23: 70 | AA23: 25 | AB23: 320.36 | AC23: m² | AD23: m² | AE23: m²
B24: Please specify the gross area of the office in sq. Ft. or m² as per lease agreement | C24: Total area gross | D24: 8118.35 | E24: included in Location 1 | F24: 2391.74 | G24: 45 | H24: 480.14 | I24: 497 | J24: 144.85 | K24: 42 | L24: 48.16 | M24: 322.97 | N24: 108 | O24: 433 | P24: 30 | Q24: 385.15 | R24: 349 | S24: 660 | T24: 53.4 | U24: 394.61 | V24: 40 | X24: 20 | Y24: 81.16 | Z24: 70 | AA24: 25 | AB24: 320.36 | AC24: 191.14 | AD24: 360 | AE24: 1266
B25: The number of parking spaces in the lease and NOT the area in sq. Ft. or m² | C25: Parking Spaces | D25: 172 | E25: included in Location 1 | F25: 20 | G25: 1 (+80 € / month) | H25: 18 | I25: 15 | J25: 0 | K25: 0 | L25: 1 (+35 € / month) | M25: 0 | N25: 1 | O25: 8 (+432 €) | P25: 0 | Q25: 2 (+320 €) | R25: 4 | S25: 10 | T25: 1 (+142,80 €) | U25: 4 | V25: 0 | X25: 0 | Y25: 0 | Z25: 1 (+79,56 €) | AA25: 1 (+29 €) | AB25: 0 | AC25: 0 | AD25: 0 | AE25: 15
B26: 3 digit international currency code for the local currency e.g. EUR, GBP or USD | C26: Currency Code | D26: EUR | E26: included in Location 1 | F26: EUR | G26: EUR | H26: EUR | I26: EUR | J26: EUR | K26: EUR | L26: EUR | M26: EUR | N26: EUR | O26: EUR | P26: EUR | Q26: EUR | R26: EUR | S26: EUR | T26: EUR | U26: EUR | V26: EUR | X26: EUR | Y26: EUR | Z26: EUR | AA26: EUR | AB26: EUR | AC26: EUR | AD26: EUR | AE26: EUR
B27: Total rental costs | C27: Total rental costs | D27: 162643.58 | E27: included in Location 1 | F27: 50733.87 | G27: 700 | H27: =H28*H23 -> 7811.8778 | I27: 9975.77 | J27: 13741.71 | K27: 749.7 | L27: 596.1 | M27: 2987.47 | N27: 1492.26 | O27: 4474.04 | P27: 321.3 | Q27: 11480.92 | R27: =2870+80+100 -> 3050 | S27: 13.135,67 EUR | T27: 1149.27 | U27: 5148.69 | V27: 375 | X27: 407.62 | Y27: =Y28*Y23 -> 6383.234 | Z27: 1180.3 | AA27: 274 | AB27: ??? | AC27: =AC28*AC24 -> 188081.76 | AD27: =AD28*AD24 -> 146880
B28: Total rental costs/ total sq. Ft. Or m²; in case location is owned, pls use reference prices | C28: Price per sq. Ft./m² Rent (in local currency) | D28: =D27/D23 -> 20.034068 | E28: included in Location 1 | F28: =F27/F23 -> 21.212118 | G28: =G27/G24 -> 15.555556 | H28: 16.27 | I28: =I27/I24 -> 20.071972 | J28: =J27/J24 -> 94.868554 | K28: =K27/K24 -> 17.85 | L28: =L27/L24 -> 12.377492 | M28: =M27/M24 -> 9.2499923 | N28: =N27/N24 -> 13.817222 | O28: =O27/O24 -> 10.332656 | P28: =P27/P24 -> 10.71 | Q28: =Q27/Q24 -> 29.808958 | R28: =R27/R23 -> 8.739255 | S28: 3,57 EUR/m² | T28: =T27/T24 -> 21.52191 | U28: 15 | V28: =V27/V24 -> 9.375 | X28: =X27/X24 -> 20.381 | Y28: 78.65 | Z28: =Z27/Z24 -> 16.861429 | AA28: =AA27/AA24 -> 10.96 | AC28: =82*12 -> 984 | AD28: =34*12 -> 408 | AE28: 434
B29: Please specify, by how much the rent increases over which period of time (e.g.7% per year starting 2025) | C29: Indexation of the rent in percent per year | D29: 0.043745 | E29: included in Location 1 | F29: 0.05 | H29: 0.05 | I29: 0.05 | J29: --- | K29: 2 % per year starting 2027 | M29: 0.05 | Q29: 5 % index if consumer-index is high enough | R29: 0.05 | U29: Indexation according to Consumer Price Index (VPI); adjustment if VPI increases by ≥ 5 %. No fixed annual percentage. | Y29: --- | AB29: --- | AC29: N/A | AD29: N/A | AE29: CPI
B30: Please do not include the rental cost | C30: Service fee and facility costs (According to Account 783*)1 - price per sq. Ft. or m² | D30: --- | E30: included in Location 1 | F30: --- | H30: 3.5 | I30: --- | J30: --- | K30: --- | L30: --- | M30: 2.23 | N30: --- | O30: --- | P30: --- | Q30: --- | R30: --- | S30: --- | T30: --- | U30: =U31/U23 -> 2.0222498 | V30: --- | X30: --- | Y30: --- | AB30: --- | AC30: =21*12 -> 252 | AD30: =9*12 -> 108 | AE30: 400000
C31: Total fee and facility costs | D31: --- | E31: included in Location 1 | F31: --- | G31: 282.64 | H31: =H30*H23 -> 1680.49 | I31: --- | J31: --- | K31: 114 | L31: 0 | M31: =M30*M23 -> 720.2231 | N31: 332.96 | O31: 398.39 | P31: 70 | Q31: 941.77 | R31: --- | S31: --- | T31: 171.88 | U31: 798 | V31: 60 | X31: 188.25 | Y31: incl | Z31: 296.6 | AA31: 29 | AB31: --- | AC31: =AC30*AC24 -> 48167.28 | AD31: =AD30*AD24 -> 38880
B32: Please specify, by how many % the costs increases over which period of time (e.g.7% per year starting 2025) | C32: Indexation of service fee and/or facility cost in percent per year | D32: --- | E32: included in Location 1 | F32: --- | H32: --- | I32: --- | J32: --- | K32: --- | L32: --- | M32: --- | N32: --- | O32: --- | P32: --- | Q32: --- | R32: --- | S32: --- | T32: --- | U32: N/A | V32: --- | X32: --- | Y32: --- | AB32: --- | AC32: N/A | AD32: N/A | AE32: CPI
B33: What is the start date of the lease? | C33: Lease Start Date | D33: 41257 | E33: included in Location 1 | F33: 01.05.2019 | G33: 43922 | H33: 43466 | I33: 39692 | J33: 43101 | K33: 45884 | L33: 43040 | M33: 43070 | N33: 42826 | O33: 40269 | P33: 43282 | Q33: 43770 | R33: 43497 | S33: 43770 | T33: 43497 | U33: 43922 | V33: 43891 | X33: 41730 | Y33: 45839 | Z33: 43466 | AA33: 42979 | AB33: 45870 | AC33: 45261 | AD33: 43101 | AE33: 44317
B34: The next fixed break date in the lease | C34: Next Break Date | D34: 47269 | E34: included in Location 1 | F34: 46143 | G34: not fixed | H34: 46477 | I34: 46266 | J34: undetermined | K34: undetermined | L34: undetermined | M34: 46356 | N34: Contract terminated as of 31 March 2026 | O34: 47573 | P34: undetermined | Q34: 46691 | R34: 46418 | S34: 46326 | T34: undetermined | U34: 46477 | V34: undetermined | X34: undetermined | Y34: undetermined | Z34: undetermined | AA34: undetermined | AB34: undetermined | AC34: 47087 | AD34: anytime | AE34: 46142
B35: The date by which notice must have been served | C35: Next Break Notice Expiry | D35: --- | E35: included in Location 1 | F35: 45778 | G35: 45961 | H35: 46234 | I35: 46023 | J35: undetermined | K35: 46142 | L35: 46053 | M35: 45991 | N35: Contract terminated as of 31 March 2026 | O35: 47483 | P35: 45961 | Q35: 46387 | R35: 46234 | S35: The tenancy ends automatically at the end of the fixed rental period, on 31.12.2026, without requiring notice | T35: 45961 | U35: 31.03.2026 (12 months before break date) | V35: 45961 | X35: 46022 | Y35: undetermined | Z35: 45961 | AA35: 45961 | AB35: undetermined | AC35: 46721 | AD35: anytime | AE35: 46142
B36: Can the contract be terminated before the end of the lease? | C36: Does a termination clause exist? Yes/No | D36: no | E36: included in Location 1 | G36: no | H36: Yes | I36: Yes | J36: no | K36: no | L36: no | M36: Yes | N36: no | O36: no | P36: no | Q36: no | R36: Yes | S36: No | T36: no | U36: Yes | V36: no | X36: no | Y36: No | Z36: no | AA36: no | AB36: No | AC36: No | AD36: No | AE36: No
B37: Please specify the exact conditions of the clause (date, notice period, penalty payments etc.) | C37: If yes, please specify the termination clause | D37: --- | E37: included in Location 1 | H37: Notice Period: 9 months | I37: Notice Period: 8 months | M37: Notice Period: 12 months | R37: Notice Period: 6 months | U37: Ordinary termination with 12 months’ notice is possible; immediate termination without notice in the event of a breach of contractual obligations (§5). | AC37: N/A | AD37: N/A | AE37: Termination after 3 years with a penalty payment of 9 months of rent
B38: Does the lease automatically renew? | C38: Auto Renewing Lease? Yes/No | D38: no | E38: included in Location 1 | F38: Yes | G38: yes | H38: Yes | I38: Yes | J38: Yes | K38: yes | L38: yes | M38: Yes | N38: Contract terminated as of 31 March 2026 | O38: no | P38: yes | Q38: yes, 3 Years for 2 times | R38: Yes | S38: No | T38: yes | U38: Yes | V38: yes | X38: yes | Y38: No | Z38: yes | AA38: yes | AB38: No | AC38: No | AD38: No | AE38: No
B39: How many months notice to prevent auto-renewal? | C39: Auto Renewal Notice Period (Months) | D39: --- | E39: included in Location 1 | F39: 12 | G39: 6 | H39: 9 | I39: 8 | J39: undetermined | K39: 3 | L39: 3 | M39: 12 | N39: 6 | O39: 3 | P39: 3 | Q39: 9 | R39: 12 | S39: n.a. | T39: 3 | U39: 12 Months | V39: 3 | X39: 3 | Y39: undetermined | Z39: 3 | AA39: 3 | AB39: undetermined | AC39: N/A | AD39: N/A | AE39: N/A
B40: The current lease expiry date (leave blank if the lease is open ended) | C40: Lease End Date | D40: 47269 | E40: included in Location 1 | F40: 46157 | G40: undetermined | H40: undetermined | I40: undetermined | J40: undetermined | K40: undetermined | L40: undetermined | M40: 47452 | N40: 46112 | O40: undetermined | P40: undetermined | Q40: undetermined | R40: 47149 | S40: 46326 | U40: 46477 | Y40: undetermined | AB40: undetermined | AC40: 48913 | AD40: indefinite | AE40: 46142
B41: Please choose "Yes" / "No"; in case of yes, please specify in the comment field | C41: Does your BU have the contractual possibility to sublet your property? Yes/No | D41: yes | E41: included in Location 1 | F41: Yes | G41: No | H41: Yes | I41: Yes | J41: no | K41: No | L41: No | M41: Yes | N41: No | O41: yes | P41: no | Q41: yes | R41: Yes | S41: No, but In individual cases, the landlord can approve a sublease | T41: yes | U41: Yes (with landlord’s consent) | V41: no | X41: no | Y41: No | Z41: yes | AA41: no | AB41: No | AC41: No | AD41: No | AE41: Yes but only in consensus with the landlord
B42: Please provide the details of the sublease agreement in a separate column of the document | C42: If there is a sublease agreement in place, please provide the details in a separate column | D42: --- | E42: included in Location 1 | F42: No | H42: No | I42: No | J42: No | R42: No | U42: No sublease agreement currently in place | V42: no | X42: no | Y42: No | Z42: no | AA42: no | AB42: No | AC42: No | AD42: No | AE42: No
B43: Please state only yes, if the whole energy consumption of the location is covered by renewable energy | C43: Is the location operated with renewable energy? Yes/No | D43: partially | E43: included in Location 1 | F43: No | G43: No | H43: No | I43: No | J43: Yes | K43: No | L43: No | M43: No | N43: No | O43: yes | P43: No | Q43: yes | R43: No | S43: No | T43: No | U43: No | V43: No | X43: no | Y43: Yes | Z43: no | AA43: no | AB43: Yes | AC43: Yes | AD43: Yes | AE43: Yes
B44: It could be an internationally recognized certificate (LEED, BREEAM, Green Star, etc.) or a more locally recognized certificate (e.g. DGNB in Germany) | C44: Does the office building hold any sustainability certificate? Yes/No - If yes please specify | D44: no | E44: included in Location 1 | F44: No | G44: No | H44: No | I44: No | J44: Yes | K44: No | L44: No | M44: No | N44: No | O44: no | P44: No | Q44: No | R44: No | S44: No | T44: No | U44: No | V44: No | X44: No | Y44: Yes | AA44: No | AB44: Yes | AC44: No | AD44: No | AE44: No
C46: Number of HC working in this location as of Sept 2025 | D46: moved out of the building | E46: included in Location 1 | G46: 2 | K46: 2 | L46: 2 | N46: 3 | O46: 11 | P46: 1 | Q46: 16 | T46: 3 | U46: 14, possible second workplace line (20-24) | V46: 3 | X46: 1 | Z46: 3 | AA46: 1 | AC46: 30 | AD46: 30 | AE46: 150
C47: thereof No. of HC non-OPS | D47: moved out of the building | E47: included in Location 1 | G47: 0 | K47: 0 | L47: 0 | N47: 0 | O47: 5 | P47: 0 | Q47: 1 | T47: 0 | U47: 6 | V47: 0 | X47: 0 | Z47: 0 | AA47: 0
C48: thereof No. of HC OPS | D48: moved out of the building | E48: included in Location 1 | G48: 2 | K48: 2 | L48: 2 | N48: 3 | O48: 6 | P48: 1 | Q48: 15 | T48: 3 | U48: 8 | V48: 3 | X48: 1 | Z48: 3 | AA48: 1
C50: Number of workstations2 in this location | D50: moved out of the building | E50: included in Location 1 | G50: 2 | K50: 2 | L50: 2 | N50: 3 | O50: 11 | P50: 1 | Q50: 16 | T50: 3 | U50: 14 | V50: 3 | X50: 1 | Z50: 3 | AA50: 1 | AC50: 22 | AD50: 26 | AE50: 65
C51: thereof No. of HC non-OPS | D51: moved out of the building | E51: included in Location 1 | G51: 0 | K51: 0 | L51: 0 | N51: 0 | O51: 5 | P51: 0 | Q51: 1 | T51: 0 | U51: 6 | V51: 0 | X51: 0 | Z51: 0 | AA51: 0
C52: thereof No. of HC OPS | D52: moved out of the building | E52: included in Location 1 | G52: 2 | K52: 2 | L52: 2 | N52: 3 | O52: 6 | P52: 1 | Q52: 15 | T52: 3 | U52: 8 | V52: 3 | X52: 1 | Z52: 3 | AA52: 1
C54: H24 Operations in this site? Yes/No | D54: moved out of the building | E54: included in Location 1 | G54: No | K54: No | L54: No | N54: No | O54: No | P54: No | Q54: No | T54: No | U54: NO | V54: No | X54: No | Z54: No | AA54: No
C55: Average shifts per day for Operations people | D55: moved out of the building | E55: included in Location 1 | G55: 1 | K55: 1 | L55: 1 | N55: 1 | O55: 1 | P55: 1 | Q55: 1 | S55: 3 | T55: 1 | U55: normal day shift | V55: 1 | X55: 1 | Z55: 1 | AA55: 1
C56: Maximum shifts per day for Operations people | D56: moved out of the building | E56: included in Location 1 | G56: 1 | K56: 1 | L56: 1 | N56: 1 | O56: 1 | P56: 1 | Q56: 1 | S56: 3 | T56: 1 | U56: 1 | V56: 1 | X56: 1 | Z56: 1 | AA56: 1
C57: WFO rule for Platform operations people (number of days per week in the office) | D57: moved out of the building | E57: included in Location 1 | G57: 1 | K57: 1 | L57: 1 | N57: 1 | O57: 1 | P57: 1 | Q57: 1 | S57: officially 1 office day per week, but there are also employees who come in more often or daily | T57: 1 | U57: 2 - 5 Days Week | V57: 1 | X57: 1 | Z57: 1 | AA57: 1
C58: WFO rule for non Platform operations people (number of days per week in the office) | D58: moved out of the building | E58: included in Location 1 | G58: no non Plattform Ops | K58: no non Plattform Ops | L58: no non Plattform Ops | N58: no non Plattform Ops | O58: 3 till 5 | P58: 1 | Q58: 1 | S58: officially 1 office day per week, but there are also employees who come in more often or daily | T58: 1 | U58: 2 - 5 Days Week | V58: 1 | X58: 1 | Z58: 1 | AA58: 1
D60: 1783* - Accommodation Expenses
D61: 7831005 - Facilities IC rental expense: Premises IC rent → NOT TO BE INCLUDED
D62: 7832001 - Utilities expenses
D63: 7832002 - Maintenance expenses
D64: 7832003 - Other occupancy expenses
D65: 7833001 - Office equipment - scheduled
D66: 7833004 - Other Office Costs
D68: 2 The workstation needs to qualify as regular work place with a sufficient desktop and an appropriate office chair. Agile and collaboration areas are excluded

Sheet Greece
C2: Update date | D2: 45926
C4: Country/BU | D4: BU Greece | E4: BU Greece | F4: BU Greece | G4: BU Greece
C6: Does your BU have multiple locations? (Please choose "Yes" / "No") | E6: Yes
C7: How many locations does your BU have (Please enter the number of office locations in your BU) | E7: 4
C9: Contact Person
